Workbook

Sheet Estructura
A1: FACTOR 1 | B1: CONDICIONES HABILITANTES
A2: PILAR 1: INSTITUCIONES | C2: INVERSA | D2: Año de corte | O2: Nueva serie | P2: Antigua serie
A3: INS-1 | B3: Desempeño administrativo | N3: 2005 | O3: 41671878 | P3: 41671878
A4: INS-1-1 | B4: Gestión de recursos | C4: No | D4: 2020-2022 | N4: 2006 | O4: 42170126 | P4: 42170126
A5: INS-1-2 | B5: Gestión de regalías | C5: No | D5: 2021-2023 | N5: 2007 | O5: 42658630 | P5: 42658630
A6: INS-1-3 | B6: Índice de Gobierno Digital para el Estado | C6: No | D6: 2022 | N6: 2008 | O6: 43134017 | P6: 43134017
A7: INS-2 | B7: Gestión fiscal | N7: 2009 | O7: 43608630 | P7: 43608630
A8: INS-2-1 | B8: Autonomía fiscal | C8: No | D8: 2017-2022 | N8: 2010 | O8: 44086292 | P8: 44086292
A9: INS-2-2 | B9: Capacidad local de recaudo | C9: No | D9: 2017-2022 | N9: 2011 | O9: 44553416 | P9: 44553416
A10: INS-2-3 | B10: Capacidad de ahorro | C10: No | D10: 2017-2022 | N10: 2012 | O10: 45001571 | P10: 45001571
A11: INS-3 | B11: Transparencia y contratación pública | N11: 2013 | O11: 45434942 | P11: 45434942
A12: INS-3-1 | B12: Índice de Gobierno Digital para la Sociedad | C12: No | D12: 2022 | N12: 2014 | O12: 45866010 | P12: 45866010
A13: INS-3-2 | B13: Transparencia en el uso de regalías | C13: No | D13: 2021-2023 | N13: 2015 | O13: 46313898 | P13: 46313898
A14: INS-3-3 | B14: Procesos de contratación en SECOP II | C14: No | D14: 2019-2022 | N14: 2016 | O14: 46830116 | P14: 46830116
A15: INS-4 | B15: Seguridad y justicia | N15: 2017 | O15: 47419200 | P15: 47419200
A16: INS-4-1 | B16: Tasa de homicidios | C16: Sí | D16: 2018-2023 | N16: 2018 | O16: 48258494 | P16: 48258494
A17: INS-4-2 | B17: Tasa de secuestro | C17: Sí | D17: 2018-2023 | N17: 2019 | O17: 49395678 | P17: 49395678
A18: INS-4-3 | B18: Tasa de extorsión | C18: Sí | D18: 2018-2023 | N18: 2020 | O18: 50407647 | P18: 50372424
A19: INS-4-4 | B19: Eficiencia de la justicia | C19: No | D19: 2017-2023 | N19: 2021 | O19: 51117378 | P19: 51049498
A20: INS-4-5 | B20: Productividad de jueces | C20: No | D20: 2017-2023 | N20: 2022 | O20: 51682692 | P20: 51609474
A21: INS-4-6 | B21: Eficiencia de los métodos de resolución de conflictos | C21: No | D21: 2018-2023 | N21: 2023 | O21: 52215503 | P21: 52156254
A22: PILAR 2: INFRAESTRUCTURA | N22: 2024 | O22: 52695952 | P22: 52691440
A23: INF-1 | B23: Infraestructura de servicios | N23: 2025 | O23: 53110609 | P23: 53216592
A24: INF-1-1 | B24: Cobertura de acueducto | C24: No | D24: 2018-2022 | N24: 2026 | O24: 53474637 | P24: 53732415
A25: INF-1-2 | B25: Cobertura efectiva de gas natural | C25: No | D25: 2018-2023 | N25: 2027 | O25: 53808013
A26: INF-1-3 | B26: Cobertura efectiva de GLP | C26: No | D26: 2018-2023
A27: INF-1-4 | B27: Cobertura de la energía eléctrica | C27: No | D27: 2018-2022 | N27: 2028 | O27: 54119568
A28: INF-1-5 | B28: Costo de la energía eléctrica | C28: Sí | D28: 2018-2023 | N28: 2029 | O28: 54416612
A29: INF-1-6 | B29: Cobertura de alcantarillado | C29: No | D29: 2018-2022 | N29: 2030 | O29: 54705567
A30: INF-2 | B30: Infraestructura vial | N30: 2031 | O30: 54986438
A31: INF-2-1 | B31: Red vial primaria por cada 100.000 habitantes | C31: No | D31: 2018-2022 | N31: 2032 | O31: 55255685
A32: INF-2-2 | B32: Red vial primaria por área | C32: No | D32: 2018-2022 | N32: 2033 | O32: 55512668
A33: INF-2-3 | B33: Porcentaje de vías primarias en buen estado | C33: No | D33: 2018-2022 | N33: 2034 | O33: 55757459
A34: INF-2-4 | B34: Red vial a cargo del departamento por cada 100.000 habitantes | C34: No | D34: 2018-2023 | N34: 2035 | O34: 55990158
A35: INF-2-5 | B35: Red vial a cargo del departamento por área | C35: No | D35: 2018-2023
A36: INF-2-6 | B36: Porcentaje de vías a cargo del departamento en buen estado | C36: No | D36: 2018-2023
A37: INF-3 | B37: Conectividad
A38: INF-3-1 | B38: Costo de transporte terrestre a mercado interno | C38: Sí | D38: 2018-2023
A39: INF-3-2 | B39: Costo de transporte terrestre a aduanas | C39: Sí | D39: 2018-2023
A40: INF-3-3 | B40: Pasajeros movilizados vía aérea | C40: No | D40: 2018-2023
A41: INF-3-4 | B41: Índice de conectividad aérea | C41: No | D41: 2018-2023
A42: PILAR 3: ADOPCIÓN DE TIC
A43: TIC-1 | B43: Infraestructura TIC
A44: TIC-1-1 | B44: Penetración de internet banda ancha fijo | C44: No | D44: 2017-2022
A45: TIC-1-2 | B45: Ancho de banda de internet | C45: No | D45: 2017-2022
A46: TIC-1-3 | B46: Hogares con computador, portátil o Tablet | C46: No | D46: 2020-2022
A47: TIC-1-4 | B47: Uso de Internet | C47: No | D47: 2020-2022
A48: TIC-2 | B48: Capacidades TIC
A49: TIC-2-1 | B49: Matriculados en programas TIC | C49: No | D49: 2018-2022
A50: TIC-2-2 | B50: Graduados en programas TIC | C50: No | D50: 2018-2022
A51: TIC-2-3 | B51: Programas TIC | C51: No | D51: 2018-2022
A52: PILAR 4: SOSTENIBILIDAD AMBIENTAL
A53: AMB-1 | B53: Activos naturales
A54: AMB-1-1 | B54: Hectáreas de bosque deforestadas | C54: Sí | D54: 2018-2022
A55: AMB-1-2 | B55: Áreas protegidas | C55: No | D55: 2018-2023
A56: AMB-1-3 | B56: Emisiones de CO2 de fuentes fijas | C56: Sí | D56: 2018-2022
A57: AMB-1-4 | B57: Emisiones de CO2 de fuentes móviles | C57: Sí | D57: 2018-2023
A58: AMB-2 | B58: Gestión ambiental y del riesgo
A59: AMB-2-1 | B59: Negocios verdes | C59: No | D59: 2017-2022
A60: AMB-2-2 | B60: Vida útil del sitio de disposición final de residuos sólidos | C60: No | D60: 2017-2022
A61: FACTOR 2 | B61: CAPITAL HUMANO
A62: PILAR 5: SALUD
A63: SAL-1 | B63: Acceso a salud
A64: SAL-1-1 | B64: Cobertura de vacunación triple viral | C64: No | D64: 2017-2022
A65: SAL-1-2 | B65: Cobertura de vacunación pentavalente (DTP) | C65: No | D65: 2017-2022
A66: SAL-1-3 | B66: Controles prenatales | C66: No | D66: 2017-2022
A67: SAL-2 | B67: Resultados en salud
A68: SAL-2-1 | B68: Mortalidad infantil | C68: Sí | D68: 2017-2022
A69: SAL-2-2 | B69: Mortalidad materna | C69: Sí | D69: 2017-2022
A70: SAL-2-3 | B70: Expectativa de vida al nacer | C70: No | D70: 2019-2024
A71: SAL-3 | B71: Calidad en salud
A72: SAL-3-1 | B72: Comunidad de la salud | C72: No | D72: 2016-2020
A73: SAL-3-2 | B73: Médicos generales | C73: No | D73: 2016-2020
A74: SAL-3-3 | B74: Médicos especialistas | C74: No | D74: 2016-2020
A75: SAL-3-4 | B75: Camas generales y especializadas | C75: No | D75: 2018-2023
A76: PILAR 6: EDUCACIÓN BÁSICA Y MEDIA
A77: EDU-1 | B77: Cobertura en educación
A78: EDU-1-1 | B78: Cobertura neta en preescolar | C78: No | D78: 2018-2022
A79: EDU-1-2 | B79: Cobertura neta en educación primaria | C79: No | D79: 2018-2022
A80: EDU-1-3 | B80: Cobertura neta en educación secundaria | C80: No | D80: 2018-2022
A81: EDU-1-4 | B81: Cobertura neta en educación media | C81: No | D81: 2018-2022
A82: EDU-1-5 | B82: Deserción escolar en educación básica y media | C82: Sí | D82: 2018-2022
A83: EDU-2 | B83: Calidad en educación
A84: EDU-2-1 | B84: Puntaje pruebas Saber 11 | C84: No | D84: 2020-2023
A85: EDU-2-2 | B85: Puntaje pruebas Saber 11 en colegios oficiales | C85: No | D85: 2020-2023
A86: EDU-2-3 | B86: Docentes de colegios oficiales con posgrado | C86: No | D86: 2017-2022
A87: EDU-2-4 | B87: Relación estudiantes-docentes | C87: Sí | D87: 2018-2022
A88: PILAR 7: EDUCACIÓN SUPERIOR Y FORMACIÓN PARA EL TRABAJO
A89: EDS-1 | B89: Cobertura en educación superior
A90: EDS-1-1 | B90: Cobertura bruta en formación universitaria | C90: No | D90: 2017-2022
A91: EDS-1-2 | B91: Graduados en posgrado | C91: No | D91: 2017-2022
A92: EDS-1-3 | B92: Cobertura bruta en formación técnica y tecnológica | C92: No | D92: 2017-2022
A93: EDS-2 | B93: Calidad en educación superior
A94: EDS-2-1 | B94: Puntaje pruebas Saber Pro | C94: No | D94: 2017-2022
A95: EDS-2-2 | B95: Calidad de docentes de educación superior | C95: No | D95: 2018-2022
A96: EDS-2-3 | B96: Cobertura instituciones de educación superior con acreditación de alta calidad | C96: No | D96: 2017-2022
A97: EDS-2-4 | B97: Dominio de inglés | C97: No | D97: 2017-2022
A98: EDS-3 | B98: Educación para el trabajo y el desarrollo humano
A99: EDS-3-1 | B99: Proporción de estudiantes en IETDH matriculados en instituciones certificadas | C99: No | D99: 2017-2022
A100: EDS-3-2 | B100: Egresados del SENA vinculados al mercado laboral | C100: No | D100: 2018-2023
...

Sheet Dato_original
A1: Departamento | B1: Año | C1: INS-1-1 | D1: INS-1-2 | E1: INS-1-3 | F1: INS-2-1 | G1: INS-2-2 | H1: INS-2-3 | I1: INS-3-1 | J1: INS-3-2 | K1: INS-3-3 | L1: INS-4-1 | M1: INS-4-2 | N1: INS-4-3 | O1: INS-4-4 | P1: INS-4-5 | Q1: INS-4-6 | R1: INF-1-1 | S1: INF-1-2 | T1: INF-1-3 | U1: INF-1-4 | V1: INF-1-5 | W1: INF-1-6 | X1: INF-2-1 | Y1: INF-2-2 | Z1: INF-2-3 | AA1: INF-2-4 | AB1: INF-2-5 | AC1: INF-2-6 | AD1: INF-3-1 | AE1: INF-3-2 | AF1: INF-3-3 | AG1: INF-3-4 | AH1: TIC-1-1 | AI1: TIC-1-2 | AJ1: TIC-1-3 | AK1: TIC-1-4 | AL1: TIC-2-1 | AM1: TIC-2-2 | AN1: TIC-2-3 | AO1: AMB-1-1 | AP1: AMB-1-2 | AQ1: AMB-1-3 | AR1: AMB-1-4 | AS1: AMB-2-1 | AT1: AMB-2-2 | AU1: SAL-1-1 | AV1: SAL-1-2 | AW1: SAL-1-3 | AX1: SAL-2-1 | AY1: SAL-2-2 | AZ1: SAL-2-3 | BA1: SAL-3-1 | BB1: SAL-3-2 | BC1: SAL-3-3 | BD1: SAL-3-4 | BE1: EDU-1-1 | BF1: EDU-1-2 | BG1: EDU-1-3 | BH1: EDU-1-4 | BI1: EDU-1-5 | BJ1: EDU-2-1 | BK1: EDU-2-2 | BL1: EDU-2-3 | BM1: EDU-2-4 | BN1: EDS-1-1 | BO1: EDS-1-2 | BP1: EDS-1-3 | BQ1: EDS-2-1 | BR1: EDS-2-2 | BS1: EDS-2-3 | BT1: EDS-2-4 | BU1: EDS-3-1 | BV1: EDS-3-2 | BW1: NEG-1-1 | BX1: NEG-1-2 | BY1: NEG-1-3 | BZ1: NEG-2-1 | CA1: NEG-2-2 | CB1: NEG-2-3 | CC1: LAB-1-1 | CD1: LAB-1-2 | CE1: LAB-1-3 | CF1: LAB-1-4 | CG1: LAB-1-5 | CH1: FIN-1-1 | CI1: FIN-1-2 | CJ1: FIN-1-3 | CK1: FIN-1-4 | CL1: TAM-1-1 | CM1: TAM-2-1 | CN1: TAM-2-2 | CO1: SOF-1-1 | CP1: SOF-1-2 | CQ1: INN-1-1 | CR1: INN-1-2 | CS1: INN-1-3 | CT1: INN-1-4 | CU1: INN-1-5 | CV1: INN-1-6 | CW1: INN-2-1 | CX1: INN-2-2 | CY1: INN-2-3 | CZ1: INN-2-4
A2: Amazonas | B2: 2019 | C2: 94.551979 | D2: 76.954873 | E2: 33.241429 | F2: 0.083040651 | G2: 0.017309501 | H2: 26.15 | I2: 45.35 | J2: 94.404236 | K2: 0 | L2: 10.445364 | M2: 0 | N2: 2.6113411 | O2: n/a | P2: n/a | Q2: 0.66666667 | R2: 0.22533666 | S2: - | T2: n/a | U2: 85.479294 | V2: 567.3488 | W2: 0.18499224 | X2: 26.204807 | Y2: 0.01830119 | Z2: 0.88012048 | AA2: 12.338586 | AB2: 0.0086171522 | AC2: 0.28042328 | AD2: NA | AE2: - | AF2: 247911 | AG2: 0.2282 | AH2: 0.0052342587 | AI2: 1.5219093 | AJ2: 0.10872453 | AK2: 0.30864158 | AL2: 426.645 | AM2: 41.288 | AN2: 0.5556 | AO2: 6.9221614e-05 | AP2: 20.921 | AQ2: 0.35538667 | AR2: 0.19517787 | AS2: 3.7426901 | AT2: 10.65 | AU2: 0.79731243 | AV2: 0.80639535 | AW2: 56.280361 | AX2: 14.502762 | AY2: 69.060773 | AZ2: 72.12 | BA2: 37.267922 | BB2: 7.0741293 | BC2: 1.1248137 | BD2: 257.21709 | BE2: 0.4599 | BF2: 0.7833 | BG2: 0.6151 | BH2: 0.3151 | BI2: 0.0487 | BJ2: 224 | BK2: 230 | BL2: 0.18372703 | BM2: 28.015748 | BN2: 5.301 | BO2: 25.298 | BP2: 4.422 | BQ2: 138.82334 | BR2: 47.058824 | BS2: 16.787265 | BT2: 8.4337349 | BU2: 0 | BV2: 0.46202532 | BW2: 0.026490066 | BX2: 0.1582474 | BY2: 0.0180783 | BZ2: 4.7 | CA2: 3.3294598 | CB2: 0.0314 | CC2: 60.972763 | CD2: 5.293581 | CE2: 39.110294 | CF2: 2.5024974 | CG2: 0.6046183 | CH2: 13.873275 | CI2: 43.246346 | CJ2: 0.0017239361 | CK2: 0.23181611 | CL2: 27.288739 | CM2: 0 | CN2: 9.4793981e-05 | CO2: 1 | CP2: 1 | CQ2: 5.2226821 | CR2: 0 | CS2: 235.02069 | CT2: 0.02356 | CU2: 0.44 | CV2: 37.9056 | CW2: 0 | CX2: 0 | CY2: 0 | CZ2: 186.40818
A3: Antioquia | B3: 2019 | C3: 143.55973 | D3: 69.434146 | E3: 83.688889 | F3: 0.4807036 | G3: 0.0094169316 | H3: 49.29 | I3: 67.65 | J3: 95.935148 | K3: 0.021478217 | L3: 38.987986 | M3: 0.21850752 | N3: 18.401455 | O3: 0.6267244 | P3: 633.50973 | Q3: 0.53897059 | R3: 0.86388918 | S3: 0.68041991 | T3: n/a | U3: 99.330783 | V3: 452.99494 | W3: 0.77727684 | X3: 32.509393 | Y3: 3.2743979 | Z3: 0.87803337 | AA3: 23.1937 | AB3: 2.3361064 | AC3: 0.75086135 | AD3: 373.3275 | AE3: 297.39888 | AF3: 8785527 | AG3: 0.5348 | AH3: 0.16616111 | AI3: 6.5211786 | AJ3: 0.42085284 | AK3: 0.71721344 | AL3: 5711.979 | AM3: 717.971 | AN3: 2.5395 | AO3: 0.0019680995 | AP3: 10.838 | AQ3: 0.50197328 | AR3: 0.18671402 | AS3: 4.5614035 | AT3: 6.8448 | AU3: 0.94387858 | AV3: 0.93167917 | AW3: 90.629114 | AX3: 9.1093644 | AY3: 49.450835 | AZ3: 76.03 | BA3: 33.361068 | BB3: 8.4893498 | BC3: 6.0154763 | BD3: 208.19085 | BE3: 0.6798 | BF3: 0.9189 | BG3: 0.8129 | BH3: 0.4383 | BI3: 0.0397 | BJ3: 252.58375 | BK3: 251 | BL3: 0.39197332 | BM3: 29.908373 | BN3: 36.191 | BO3: 189.794 | BP3: 20.056 | BQ3: 153.60075 | BR3: 11.213383 | BS3: 37.469734 | BT3: 32.632578 | BU3: 56.235707 | BV3: 0.60913972 | BW3: 0.036311914 | BX3: 0.0064338 | BY3: 0.0269354 | BZ3: 11.79 | CA3: 10.048849 | CB3: 0.0776 | CC3: 61.781702 | CD3: 11.861609 | CE3: 45.762608 | CF3: 8.664365 | CG3: 0.32600623 | CH3: 24.251797 | CI3: 93.268581 | CJ3: 0.034608815 | CK3: 0.61454705 | CL3: 32.556507 | CM3: 29.976 | CN3: 24.034845 | CO3: 0.175 | CP3: 0.098 | CQ3: 3.9019201 | CR3: 0.68673794 | CS3: 373.80394 | CT3: 0.01 | CU3: 1.04 | CV3: 21.37 | CW3: 14.292877 | CX3: 7.6228675 | CY3: 24.29789 | CZ3: 1898.4116
A4: Arauca | B4: 2019 | C4: 99.315437 | D4: 74.552247 | E4: 30.83625 | F4: 0.088665625 | G4: 0.0098706935 | H4: 37.19 | I4: 84.62 | J4: 94.906511 | K4: 0.060117411 | L4: 57.976764 | M4: 2.3523131 | N4: 42.71972 | O4: 0.49490215 | P4: 348.42857 | Q4: 0.5877193 | R4: 0.7182601 | S4: 0.063957275 | T4: n/a | U4: 95.114412 | V4: 557.21299 | W4: 0.53978742 | X4: 168.4492 | Y4: 1.8541859 | Z4: 0.51086394 | AA4: 64.61701 | AB4: 0.71126459 | AC4: 0 | AD4: 395.49172 | AE4: 419.23856 | AF4: 114012 | AG4: 0.1088 | AH4: 0.039728798 | AI4: 4.9541882 | AJ4: 0.16453447 | AK4: 0.60897068 | AL4: 556.646 | AM4: 164.19 | AN4: 0.375 | AO4: 0.0017308964 | AP4: 21.607 | AQ4: 0.166212 | AR4: 0.27352665 | AS4: 0.35087719 | AT4: 10.285714 | AU4: 1 | AV4: 1 | AW4: 81.41953 | AX4: 10.459795 | AY4: 65.37372 | AZ4: 75.48 | BA4: 30.609404 | BB4: 6.490422 | BC4: 1.1834271 | BD4: 215.12431 | BE4: 0.6166 | BF4: 0.9381 | BG4: 0.7465 | BH4: 0.3666 | BI4: 0.0263 | BJ4: 248.89507 | BK4: 252 | BL4: 0.54144107 | BM4: 28.163599 | BN4: 7.485 | BO4: 10.778 | BP4: 4.219 | BQ4: 133.81393 | BR4: 45.454545 | BS4: 1.0582011 | BT4: 2.4113475 | BU4: 30.179445 | BV4: 0.48094374 | BW4: 0.031512605 | BX4: 0.0814861 | BY4: 0.50010912 | BZ4: 4.35 | CA4: 3.8333321 | CB4: 0.0249 | CC4: 61.895839 | CD4: 18.969049 | CE4: 28.028531 | CF4: 14.110578 | CG4: 0.53325791 | CH4: 24.502962 | CI4: 45.893117 | CJ4: 0.00022401635 | CK4: 0.13635767 | CL4: 28.808006 | CM4: 26.984 | CN4: 25.744955 | CO4: 1 | CP4: 1 | CQ4: 0 | CR4: 0 | CS4: 3.8142608 | CT4: 0.003 | CU4: 0 | CV4: 0 | CW4: 0 | CX4: 0 | CY4: 0 | CZ4: 31.935873
A5: Atlántico | B5: 2019 | C5: 135.76416 | D5: 79.594878 | E5: 74.765 | F5: 0.46872423 | G5: 0.011018587 | H5: 66.21 | I5: 75.58 | J5: 96.298918 | K5: 0.18191705 | L5: 22.283424 | M5: 0.039439688 | N5: 5.9553929 | O5: 0.57405721 | P5: 383.14359 | Q5: 0.46442406 | R5: 0.98462606 | S5: 0.87842557 | T5: n/a | U5: 99.638348 | V5: 452.66841 | W5: 0.85891767 | X5: 14.652672 | Y5: 10.965791 | Z5: 1 | AA5: 16.529962 | AB5: 12.37072 | AC5: 0.7911338 | AD5: 196.79923 | AE5: 196.79923 | AF5: 2482372 | AG5: 0.3158 | AH5: 0.13042194 | AI5: 6.1121835 | AJ5: 0.42942046 | AK5: 0.76209119 | AL5: 5443.658 | AM5: 695.529 | AN5: 2.3784 | AO5: 0 | AP5: 1.683 | AQ5: 0.63590838 | AR5: 0.13330752 | AS5: 0.93567251 | AT5: 21.46087 | AU5: 0.9957191 | AV5: 0.99294562 | AW5: 89.972231 | AX5: 12.554883 | AY5: 73.573039 | AZ5: 77.42 | BA5: 42.661738 | BB5: 9.4406946 | BC5: 3.4642936 | BD5: 378.22661 | BE5: 0.6154 | BF5: 0.8902 | BG5: 0.7655 | BH5: 0.4927 | BI5: 0.0155 | BJ5: 248.4899 | BK5: 241 | BL5: 0.5035776 | BM5: 30.910148 | BN5: 39.378 | BO5: 207.419 | BP5: 18.95 | BQ5: 147.06064 | BR5: 13.395079 | BS5: 53.32355 | BT5: 28.352631 | BU5: 58.173619 | BV5: 0.49643485 | BW5: 0.014423077 | BX5: 0.0250715 | BY5: 0.0672318 | BZ5: 16.54 | CA5: 10.53 | CB5: 0.063 | CC5: 63.897616 | CD5: 7.521595 | CE5: 31.086066 | CF5: 12.83905 | CG5: 0.52357124 | CH5: 34.179478 | CI5: 65.294625 | CJ5: 0.024289586 | CK5: 0.57741188 | CL5: 31.435324 | CM5: 28.881 | CN5: 29.126133 | CO5: 0.127 | CP5: 0.04 | CQ5: 4.0228482 | CR5: 0.43383657 | CS5: 363.23953 | CT5: 0.005 | CU5: 1 | CV5: 22.09 | CW5: 5.6716235 | CX5: 1.2153479 | CY5: 0.81023193 | CZ5: 812.25751
A6: Bogotá, D.C. | B6: 2019 | C6: 161.39709 | D6: 79.6 | E6: 91.9025 | F6: 0.54928466 | G6: 0.034935851 | H6: 62.92 | I6: 48.215 | J6: 98.6 | K6: 0.31486151 | L6: 14.542872 | M6: 0.14839666 | N6: 10.25286 | O6: 0.53574517 | P6: 679.81404 | Q6: 0.36015982 | R6: 0.99570168 | S6: 0.96346458 | T6: n/a | U6: 99.894262 | V6: 475.98583 | W6: 0.99460532 | X6: - | Y6: - | Z6: - | AA6: - | AB6: - | AC6: - | AD6: 325.03334 | AE6: 226.57396 | AF6: 25686743 | AG6: 1 | AH6: 0.22346138 | AI6: 8.8035763 | AJ6: 0.63750727 | AK6: 0.87104408 | AL6: 10166.292 | AM6: 1601.455 | AN6: 2.7656 | AO6: 6.7894537e-05 | AP6: 36.427 | AQ6: 0.63111998 | AR6: 0.17577393 | AS6: 1.754386 | AT6: 4.2 | AU6: 0.92496506 | AV6: 0.88670345 | AW6: 88.39084 | AX6: 9.4075217 | AY6: 43.452756 | AZ6: 79.49 | BA6: 55.171692 | BB6: 13.942219 | BC6: 7.0441761 | BD6: 240.33513 | BE6: 0.7065 | BF6: 0.9781 | BG6: 0.8597 | BH6: 0.5601 | BI6: 0.0165 | BJ6: 272.38782 | BK6: 257 | BL6: 0.32906263 | BM6: 40.983516 | BN6: 79.512 | BO6: 539.09988 | BP6: 30.591 | BQ6: 155.69302 | BR6: 8.2291743 | BS6: 33.25359 | BT6: 36.889667 | BU6: 29.86135 | BV6: 0.69293538 | BW6: 0.077423018 | BX6: 0.0052625 | BY6: 0.0067017 | BZ6: 17.182 | CA6: 15.2912 | CB6: 0.0731 | CC6: 71.179768 | CD6: 10.597089 | CE6: 51.246018 | CF6: 7.8052914 | CG6: 0.31766841 | CH6: 57.462528 | CI6: 133.21161 | CJ6: 0.038261655 | CK6: 0.72267587 | CL6: 33.331571 | CM6: 29.349 | CN6: 32.451936 | CO6: 0.132 | CP6: 0.018 | CQ6: 6.043791 | CR6: 0.92594823 | CS6: 588.46019 | CT6: 0.01 | CU6: 1.79 | CV6: 18.7 | CW6: 16.601493 | CX6: 9.6925781 | CY6: 25.048644 | CZ6: 1955.9603
A7: Bolívar | B7: 2019 | C7: 111.78606 | D7: 71.624394 | E7: 52.02 | F7: 0.30215054 | G7: 0.008713199 | H7: 46.82 | I7: 97.67 | J7: 95.231565 | K7: 0.18785311 | L7: 19.322645 | M7: 0.048306612 | N7: 8.8884166 | O7: 0.54775499 | P7: 382.98851 | Q7: 0.34727626 | R7: 0.80527502 | S7: 0.88356823 | T7: 0.3745583 | U7: 95.802788 | V7: 447.10164 | W7: 0.46285066 | X7: 40.529537 | Y7: 3.229679 | Z7: 0.95758803 | AA7: 7.8256711 | AB7: 0.62360459 | AC7: 0.87962963 | AD7: 214.54526 | AE7: 219.53608 | AF7: 5259812 | AG7: 0.4566 | AH7: 0.082540332 | AI7: 6.1635568 | AJ7: 0.23990779 | AK7: 0.57425134 | AL7: 2573.871 | AM7: 484.638 | AN7: 1.4419 | AO7: 0.0010610434 | AP7: 0.157 | AQ7: 0.54956694 | AR7: 0.14292086 | AS7: 1.0526316 | AT7: 6.8695652 | AU7: 0.87835834 | AV7: 0.86419662 | AW7: 87.511508 | AX7: 11.750372 | AY7: 100.17598 | AZ7: 76.38 | BA7: 30.44893 | BB7: 7.0993189 | BC7: 2.6656599 | BD7: 256.99117 | BE7: 0.6974 | BF7: 0.9725 | BG7: 0.7938 | BH7: 0.4417 | BI7: 0.0275 | BJ7: 232.90635 | BK7: 228 | BL7: 0.12574215 | BM7: 26.412205 | BN7: 22.358 | BO7: 104.632 | BP7: 17.611 | BQ7: 144.47017 | BR7: 5.9440559 | BS7: 42.394084 | BT7: 22.918641 | BU7: 38.269486 | BV7: 0.41007498 | BW7: 0.061779242 | BX7: 0.3013539 | BY7: 0.012989 | BZ7: 10.47 | CA7: 6.45 | CB7: 0.0617 | CC7: 68.445475 | CD7: 5.1506881 | CE7: 23.400639 | CF7: 10.936752 | CG7: 0.64178857 | CH7: 25.678853 | CI7: 51.374402 | CJ7: 0.010198837 | CK7: 0.24369 | CL7: 31.179053 | CM7: 29.049 | CN7: 34.132082 | CO7: 0.099 | CP7: 0.087 | CQ7: 1.8839579 | CR7: 0.24153306 | CS7: 165.20861 | CT7: 0.002 | CU7: 1.03 | CV7: 22.49 | CW7: 0.98245773 | CX7: 0.49122886 | CY7: 1.4736866 | CZ7: 268.21096
A8: Boyacá | B8: 2019 | C8: 113.55077 | D8: 68.072861 | E8: 76.728889 | F8: 0.25142099 | G8: 0.011484815 | H8: 49.41 | I8: 47.675 | J8: 90.99082 | K8: 0.08329369 | L8: 7.5572379 | M8: 0.16428778 | N8: 15.853771 | O8: 0.68105995 | P8: 190.64173 | Q8: 0.64 | R8: 0.84987168 | S8: 0.92335332 | T8: 0.22335518 | U8: 98.538834 | V8: 460.14025 | W8: 0.630598 | X8: 105.65405 | Y8: 5.5466256 | Z8: 0.56716747 | AA8: 58.915816 | AB8: 3.0929622 | AC8: 0.43492507 | AD8: 178.88546 | AE8: 161.3445 | AF8: - | AG8: - | AH8: 0.082339614 | AI8: 5.3592886 | AJ8: 0.3320431 | AK8: 0.63096509 | AL8: 5677.143 | AM8: 729.528 | AN8: 2.5238 | AO8: 0.00023965025 | AP8: 16.473 | AQ8: 0.52525 | AR8: 0.21869638 | AS8: 2.6900585 | AT8: 22.46087 | AU8: 0.95690129 | AV8: 0.95007186 | AW8: 90.006123 | AX8: 8.3673469 | AY8: 68.027211 | AZ8: 77.4 | BA8: 24.096275 | BB8: 7.5501384 | BC8: 2.0142036 | BD8: 188.10951 | BE8: 0.7066 | BF8: 0.9285 | BG8: 0.8925 | BH8: 0.5796 | BI8: 0.0207 | BJ8: 262.60908 | BK8: 260 | BL8: 0.66293499 | BM8: 21.214755 | BN8: 46.094 | BO8: 537.732 | BP8: 14.687 | BQ8: 151.9658 | BR8: 9.257175 | BS8: 56.644877 | BT8: 17.095409 | BU8: 10.800781 | BV8: 0.55072464 | BW8: 0.025118544 | BX8: 0.2732924 | BY8: 0.0104808 | BZ8: 6.83 | CA8: 4.75 | CB8: 0.0257 | CC8: 60.249927 | CD8: 7.5286727 | CE8: 28.223997 | CF8: 6.421692 | CG8: 0.51945522 | CH8: 35.328795 | CI8: 65.031461 | CJ8: 0.0067533166 | CK8: 0.17766802 | CL8: 30.796903 | CM8: 27.395 | CN8: 6.1210477 | CO8: 0.35 | CP8: 0.648 | CQ8: 1.3143022 | CR8: 0.65715112 | CS8: 230.82433 | CT8: 0.003 | CU8: 0.92 | CV8: 17.77 | CW8: 0.8280442 | CX8: 0.8280442 | CY8: 0.8280442 | CZ8: 210.32323
A9: Caldas | B9: 2019 | C9: 131.8794 | D9: 73.765719 | E9: 81.273333 | F9: 0.31902021 | G9: 0.013035196 | H9: 42.76 | I9: 46.8 | J9: 93.857373 | K9: 0.065826071 | L9: 20.43566 | M9: 0.20034961 | N9: 10.017481 | O9: 0.57286077 | P9: 446.84559 | Q9: 0.57094134 | R9: 0.8906426 | S9: 0.7619908 | T9: n/a | U9: 99.708547 | V9: 499.88903 | W9: 0.80029131 | X9: 42.728261 | Y9: 5.4074163 | Z9: 0.88142179 | AA9: 49.038423 | AB9: 13.28106 | AC9: 0.78803181 | AD9: 240.45884 | AE9: 201.36414 | AF9: 217271 | AG9: 0.1268 | AH9: 0.12027 | AI9: 5.9453979 | AJ9: 0.41098517 | AK9: 0.70654343 | AL9: 6579.506 | AM9: 998.882 | AN9: 3.0588 | AO9: 0.00037414637 | AP9: 4.765 | AQ9: 0.45296047 | AR9: 0.14113618 | AS9: 0.11695906 | AT9: 6.4592593 | AU9: 0.9481336 | AV9: 0.97097861 | AW9: 93.420911 | AX9: 9.1447015 | AY9: 32.275417 | AZ9: 78.12 | BA9: 30.132271 | BB9: 8.8410416 | BC9: 4.4215337 | BD9: 261.25589 | BE9: 0.6568 | BF9: 0.8301 | BG9: 0.7781 | BH9: 0.4519 | BI9: 0.0296 | BJ9: 256.123 | BK9: 255.65906 | BL9: 0.36990395 | BM9: 22.375774 | BN9: 40.035 | BO9: 259.441 | BP9: 16.567 | BQ9: 151.44973 | BR9: 17.084363 | BS9: 66.337046 | BT9: 23.520386 | BU9: 49.375 | BV9: 0.55753791 | BW9: 0.03531218 | BX9: 0.05482 | BY9: 0.0405993 | BZ9: 5.77 | CA9: 5.09 | CB9: 0.0651 | CC9: 58.563257 | CD9: 10.477586 | CE9: 41.662948 | CF9: 4.8564997 | CG9: 0.32686599 | CH9: 28.217217 | CI9: 67.655382 | CJ9: 0.018416453 | CK9: 0.33294904 | CL9: 30.196277 | CM9: 28.241 | CN9: 23.826574 | CO9: 0.143 | CP9: 0.391 | CQ9: 6.2108379 | CR9: 0.90157325 | CS9: 419.73243 | CT9: 0.008 | CU9: 0.62 | CV9: 20.39 | CW9: 5.0435612 | CX9: 3.0261367 | CY9: 3.0261367 | CZ9: 743.42093
A10: Caquetá | B10: 2019 | C10: 94.699524 | D10: 70.913518 | E10: 42.105714 | F10: 0.17595467 | G10: 0.013861755 | H10: 41.09 | I10: 88.37 | J10: 97.465875 | K10: 0.12252461 | L10: 45.539494 | M10: 0.24884969 | N10: 33.345859 | O10: 0.037437164 | P10: 628.7 | Q10: 0.58580858 | R10: 0.68155708 | S10: 0.89457851 | T10: 0.82497467 | U10: 90.558367 | V10: 587.03222 | W10: 0.59367835 | X10: 148.94027 | Y10: 0.67275333 | Z10: 0.53255073 | AA10: 36.50625 | AB10: 0.16489631 | AC10: 0.072256305 | AD10: 456.23177 | AE10: 513.11381 | AF10: 110539 | AG10: 0.1192 | AH10: 0.039715869 | AI10: 5.4630733 | AJ10: 0.24430547 | AK10: 0.58371176 | AL10: 2023.8 | AM10: 234.835 | AN10: 2.25 | AO10: 0.0052399242 | AP10: 39.064 | AQ10: 0.17382988 | AR10: 0.14813036 | AS10: 0.81871345 | AT10: 17.35 | AU10: 0.81037484 | AV10: 0.79170594 | AW10: 78.99124 | AX10: 11.071132 | AY10: 55.35566 | AZ10: 73.21 | BA10: 14.58812 | BB10: 4.7001998 | BC10: 0.69252943 | BD10: 215.25498 | BE10: 0.5917 | BF10: 0.9089 | BG10: 0.6946 | BH10: 0.3222 | BI10: 0.055 | BJ10: 244 | BK10: 246 | BL10: 0.37330317 | BM10: 20.19491 | BN10: 26.117 | BO10: 91.249 | BP10: 4.092 | BQ10: 136.74031 | BR10: 3.9577836 | BS10: 0.57923403 | BT10: 8.1924577 | BU10: 3.3898305 | BV10: 0.35719348 | BW10: 0.028820961 | BX10: 0.044557 | BY10: 0.0787038 | BZ10: 5.33 | CA10: 2.75 | CB10: 0.0307 | CC10: 60.506879 | CD10: 8.3967707 | CE10: 18.383532 | CF10: 7.8190272 | CG10: 0.53438481 | CH10: 37.635071 | CI10: 47.610551 | CJ10: 0.0059094694 | CK10: 0.29206174 | CL10: 28.983461 | CM10: 0 | CN10: 0.061511893 | CO10: 1 | CP10: 1 | CQ10: 0 | CR10: 0 | CS10: 116.95936 | CT10: 0.005 | CU10: 1.19 | CV10: 16.07 | CW10: 2.4931501 | CX10: 0 | CY10: 0 | CZ10: 57.342452
A11: Casanare | B11: 2019 | C11: 119.77925 | D11: 75.583265 | E11: 73.7125 | F11: 0.16285019 | G11: 0.0069178998 | H11: 35.38 | I11: 51.36 | J11: 94.693843 | K11: 0.17021647 | L11: 12.841733 | M11: 0.47561973 | N11: 43.043586 | O11: 0.50776889 | P11: 285.2549 | Q11: 0.51093439 | R11: 0.86065757 | S11: 0.78211504 | T11: n/a | U11: 97.581804 | V11: 509.30231 | W11: 0.74504389 | X11: 117.65855 | Y11: 1.1295721 | Z11: 0.65166785 | AA11: 70.629401 | AB11: 1.0959229 | AC11: 0.76572912 | AD11: 250.42867 | AE11: 223.08726 | AF11: 322762 | AG11: 0.1456 | AH11: 0.091718181 | AI11: 5.3418619 | AJ11: 0.3459189 | AK11: 0.68286184 | AL11: 2228.75 | AM11: 154.595 | AN11: 1 | AO11: 0.00041995405 | AP11: 2.928 | AQ11: 0.39550892 | AR11: 0.27502573 | AS11: 2.2222222 | AT11: 3.2263158 | AU11: 0.8865173 | AV11: 0.89926491 | AW11: 80.596551 | AX11: 6.3664596 | AY11: 108.69565 | AZ11: 76.96 | BA11: 30.439545 | BB11: 6.903661 | BC11: 1.2538595 | BD11: 185.01608 | BE11: 0.7143 | BF11: 0.9101 | BG11: 0.7886 | BH11: 0.4409 | BI11: 0.0269 | BJ11: 256.54004 | BK11: 257 | BL11: 0.36454984 | BM11: 24.038238 | BN11: 18.655 | BO11: 56.17 | BP11: 7.018 | BQ11: 139.9098 | BR11: 1.6574586 | BS11: 10.600744 | BT11: 8.0123267 | BU11: 0 | BV11: 0.59469942 | BW11: 0.031607263 | BX11: 0.0281223 | BY11: 0.3033634 | BZ11: 9.63 | CA11: 7.65 | CB11: 0.0379 | CC11: 71.703718 | CD11: 11.43427 | CE11: 36.191358 | CF11: 6.8981206 | CG11: 0.42751285 | CH11: 41.244004 | CI11: 67.953078 | CJ11: 0.003258767 | CK11: 0.12949347 | CL11: 29.840037 | CM11: 29.006 | CN11: 30.841403 | CO11: 0.29 | CP11: 1 | CQ11: 0 | CR11: 0 | CS11: 30.915283 | CT11: 0 | CU11: 0 | CV11: 0 | CW11: 0 | CX11: 2.4315814 | CY11: 0 | CZ11: 124.01065
A12: Cauca | B12: 2019 | C12: 79.987688 | D12: 76.299137 | E12: 59.20875 | F12: 0.13714163 | G12: 0.0071091905 | H12: 46.39 | I12: 46.22 | J12: 95.568468 | K12: 0.11841672 | L12: 47.388575 | M12: 1.7070812 | N12: 31.205445 | O12: 0.54502968 | P12: 299.06818 | Q12: 0.6604534 | R12: 0.76631045 | S12: 0.7134298 | T12: 0.79145026 | U12: 96.265853 | V12: 500.24672 | W12: 0.45466039 | X12: 103.87323 | Y12: 5.1904292 | Z12: 0.53822147 | AA12: 13.939479 | AB12: 0.69654019 | AC12: 0 | AD12: 308.17985 | AE12: 234.61708 | AF12: 110207 | AG12: 0.1192 | AH12: 0.046679082 | AI12: 5.4009864 | AJ12: 0.22426921 | AK12: 0.5454322 | AL12: 3739.885 | AM12: 421.076 | AN12: 1.5556 | AO12: 0.00043182666 | AP12: 8.965 | AQ12: 0.22025081 | AR12: 0.10309208 | AS12: 2.6900585 | AT12: 12.22381 | AU12: 0.9520505 | AV12: 0.94953245 | AW12: 85.361561 | AX12: 11.767838 | AY12: 69.222577 | AZ12: 75.96 | BA12: 19.27642 | BB12: 5.3667226 | BC12: 1.3998933 | BD12: 153.36418 | BE12: 0.5516 | BF12: 0.8455 | BG12: 0.6621 | BH12: 0.3358 | BI12: 0.0258 | BJ12: 235.91948 | BK12: 243 | BL12: 0.30626866 | BM12: 24.14519 | BN12: 24.4 | BO12: 67.019 | BP12: 11.409 | BQ12: 145.66846 | BR12: 8.2398619 | BS12: 38.444478 | BT12: 13.543565 | BU12: 45.146809 | BV12: 0.41091854 | BW12: 0.035407725 | BX12: 0.5597757 | BY12: 0.240367 | BZ12: 3.07 | CA12: 2.02 | CB12: 0.0567 | CC12: 64.938012 | CD12: 9.4940086 | CE12: 19.978739 | CF12: 14.404556 | CG12: 0.67527521 | CH12: 20.350791 | CI12: 38.080115 | CJ12: 0.0078667276 | CK12: 0.14370684 | CL12: 30.436786 | CM12: 27.576 | CN12: 11.917225 | CO12: 0.191 | CP12: 0.244 | CQ12: 0.75111575 | CR12: 0 | CS12: 104.47337 | CT12: 0.003 | CU12: 1.55 | CV12: 20.9 | CW12: 2.0706263 | CX12: 1.3804175 | CY12: 0.69020877 | CZ12: 185.66616
A13: Cesar | B13: 2019 | C13: 106.64053 | D13: 69.578485 | E13: 40.0925 | F13: 0.18750214 | G13: 0.0069562247 | H13: 42.39 | I13: 88.37 | J13: 95.842515 | K13: 0.072043937 | L13: 20.823373 | M13: 0.083293491 | N13: 13.743426 | O13: 0.53119227 | P13: 593.32967 | Q13: 0.63091716 | R13: 0.8530805 | S13: 0.88634777 | T13: 0.046553647 | U13: 95.440166 | V13: 410.26724 | W13: 0.73088433 | X13: 55.631223 | Y13: 2.915931 | Z13: 0.90380712 | AA13: 29.58918 | AB13: 1.5509277 | AC13: 0.5911215 | AD13: 301.76062 | AE13: 256.5899 | AF13: 389395 | AG13: 0.2354 | AH13: 0.075523387 | AI13: 5.4660211 | AJ13: 0.25003847 | AK13: 0.65990108 | AL13: 2927.427 | AM13: 395.428 | AN13: 1.1579 | AO13: 0.00014879789 | AP13: 0.786 | AQ13: 0.41503033 | AR13: 0.36489591 | AS13: 3.5087719 | AT13: 16.568 | AU13: 0.95618853 | AV13: 0.9220092 | AW13: 86.823747 | AX13: 14.53375 | AY13: 73.156457 | AZ13: 75.66 | BA13: 31.489071 | BB13: 7.4461035 | BC13: 1.4899247 | BD13: 335.2563 | BE13: 0.5881 | BF13: 0.878 | BG13: 0.7127 | BH13: 0.3994 | BI13: 0.0398 | BJ13: 244.37976 | BK13: 243 | BL13: 0.29209979 | BM13: 31.993888 | BN13: 23.87 | BO13: 98.416 | BP13: 8.768 | BQ13: 140.84189 | BR13: 5.9563758 | BS13: 1.3627734 | BT13: 9.6908442 | BU13: 61.608911 | BV13: 0.37015465 | BW13: 0.015972618 | BX13: 0.0639779 | BY13: 0.0083807 | BZ13: 6.75 | CA13: 3.5 | CB13: 0.0414 | CC13: 62.029944 | CD13: 10.545526 | CE13: 21.584854 | CF13: 8.5164379 | CG13: 0.64146875 | CH13: 17.458446 | CI13: 45.509842 | CJ13: 0.0027748296 | CK13: 0.16786763 | CL13: 29.560006 | CM13: 29.683 | CN13: 65.027019 | CO13: 0.068 | CP13: 0.872 | CQ13: 0.49976095 | CR13: 0 | CS13: 45.81142 | CT13: 0.003 | CU13: 0.73 | CV13: 22.5 | CW13: 0 | CX13: 0 | CY13: 0.86027796 | CZ13: 86.888074
A14: Chocó | B14: 2019 | C14: 77.355501 | D14: 67.081743 | E14: 50.434286 | F14: 0.13090081 | G14: 0.015652709 | H14: 10.14 | I14: 48.255 | J14: 89.030192 | K14: 0.22572766 | L14: 39.63906 | M14: 2.2437204 | N14: 24.306971 | O14: 0.56148076 | P14: 172.56061 | Q14: 0.58498584 | R14: 0.35023394 | S14: 0.10309032 | T14: 0.57623143 | U14: 84.901817 | V14: 654.37009 | W14: 0.21905762 | X14: 52.152102 | Y14: 0.59944767 | Z14: 0.68050631 | AA14: 5.5294619 | AB14: 0.063556845 | AC14: 0.12278092 | AD14: 507.51043 | AE14: 453.4192 | AF14: 329654 | AG14: 0.0162 | AH14: 0.040219823 | AI14: 4.5260503 | AJ14: 0.12942524 | AK14: 0.41009819 | AL14: 1226.619 | AM14: 76.787 | AN14: 1 | AO14: 0.0010349102 | AP14: 8.492 | AQ14: 0.084316579 | AR14: 0.1488883 | AS14: 5.6140351 | AT14: 4.5233333 | AU14: 0.83313211 | AV14: 0.77321834 | AW14: 68.391837 | AX14: 25.5515 | AY14: 317.40993 | AZ14: 71.19 | BA14: 14.055427 | BB14: 3.1530158 | BC14: 0.42258902 | BD14: 182.67623 | BE14: 0.5599 | BF14: 0.8174 | BG14: 0.5112 | BH14: 0.2321 | BI14: 0.0316 | BJ14: 209 | BK14: 216 | BL14: 0.17443609 | BM14: 26.032617 | BN14: 24.216 | BO14: 39.287 | BP14: 2.031 | BQ14: 124.8599 | BR14: 3.248731 | BS14: 1.0039083 | BT14: 3.2324622 | BU14: 0 | BV14: 0.30136986 | BW14: 0.0046480744 | BX14: 0.0514227 | BY14: 0.0338902 | BZ14: 3.65 | CA14: 2.24 | CB14: 0.015 | CC14: 55.4474 | CD14: 7.8662978 | CE14: 17.929254 | CF14: 3.7313879 | CG14: 0.71902171 | CH14: 17.987918 | CI14: 27.745963 | CJ14: 0.0027319128 | CK14: 0.12753857 | CL14: 28.865675 | CM14: 25.549 | CN14: 13.31866 | CO14: 0.437 | CP14: 0.929 | CQ14: 0 | CR14: 0 | CS14: 29.916272 | CT14: 0.005 | CU14: 0.69 | CV14: 36.36 | CW14: 0 | CX14: 1.8979366 | CY14: 0 | CZ14: 58.836033
A15: Córdoba | B15: 2019 | C15: 82.444697 | D15: 63.659973 | E15: 30.57 | F15: 0.17985429 | G15: 0.012652246 | H15: 40.28 | I15: 45.545 | J15: 92.165109 | K15: 0.083404367 | L15: 21.010958 | M15: 0 | N15: 8.124237 | O15: 0.50530691 | P15: 427.20202 | Q15: 0.58462181 | R15: 0.7432796 | S15: 0.86791347 | T15: n/a | U15: 97.942677 | V15: 434.50409 | W15: 0.37236573 | X15: 49.420462 | Y15: 3.5253717 | Z15: 0.84312084 | AA15: 11.506902 | AB15: 0.82083624 | AC15: 0 | AD15: 246.43365 | AE15: 230.21704 | AF15: 925753 | AG15: 0.2496 | AH15: 0.048876331 | AI15: 4.8614073 | AJ15: 0.17345443 | AK15: 0.47804867 | AL15: 2193.125 | AM15: 270.307 | AN15: 1.3043 | AO15: 0.00055677171 | AP15: 25.393 | AQ15: 0.28746695 | AR15: 0.11419744 | AS15: 3.2748538 | AT15: 15.273333 | AU15: 0.88454324 | AV15: 0.90385222 | AW15: 88.343834 | AX15: 15.036748 | AY15: 108.74456 | AZ15: 76.53 | BA15: 16.541742 | BB15: 5.0055783 | BC15: 1.1322892 | BD15: 209.43723 | BE15: 0.5831 | BF15: 0.9071 | BG15: 0.7821 | BH15: 0.4356 | BI15: 0.0223 | BJ15: 237.14631 | BK15: 240 | BL15: 0.39566969 | BM15: 25.011018 | BN15: 22.539 | BO15: 36.925 | BP15: 3.239 | BQ15: 139.13119 | BR15: 8.5295657 | BS15: 72.890981 | BT15: 11.107449 | BU15: 40.794424 | BV15: 0.29819967 | BW15: 0.017821782 | BX15: 0.0834352 | BY15: 0.4388173 | BZ15: 3.6 | CA15: 2.43 | CB15: 0.0554 | CC15: 69.008985 | CD15: 8.6217907 | CE15: 16.956615 | CF15: 8.5494578 | CG15: 0.62315815 | CH15: 15.288362 | CI15: 32.940546 | CJ15: 0.0062545293 | CK15: 0.24143959 | CL15: 30.311118 | CM15: 27.275 | CN15: 9.2250847 | CO15: 0.222 | CP15: 0.588 | CQ15: 0.67235064 | CR15: 0.05602922 | CS15: 100.2923 | CT15: 0.004 | CU15: 0.83 | CV15: 31.75 | CW15: 0 | CX15: 0.56719792 | CY15: 0 | CZ15: 87.915678
A16: Cundinamarca | B16: 2019 | C16: 144.18284 | D16: 61.706289 | E16: 84.7875 | F16: 0.48655343 | G16: 0.020287608 | H16: 55.87 | I16: 55.4 | J16: 90.713432 | K16: 0.020422388 | L16: 13.600269 | M16: 0.10277281 | N16: 9.1125225 | O16: 0.48984797 | P16: 348.9359 | Q16: 0.65842261 | R16: 0.89980724 | S16: 0.83743364 | T16: 0.13056321 | U16: 99.419599 | V16: 461.79977 | W16: 0.74068375 | X16: 40.389989 | Y16: 5.2092431 | Z16: 0.88971076 | AA16: 70.213356 | AB16: 9.0556709 | AC16: 0.73542987 | AD16: 378.40007 | AE16: 309.41371 | AF16: - | AG16: - | AH16: 0.12298066 | AI16: 5.8441392 | AJ16: 0.40159293 | AK16: 0.73188396 | AL16: 3060.362 | AM16: 388.078 | AN16: 1.6129 | AO16: 0.00013032052 | AP16: 13.095 | AQ16: 0.58090073 | AR16: 0.25717516 | AS16: 8.9076023 | AT16: 10.960345 | AU16: 0.95109055 | AV16: 0.95088364 | AW16: 88.397775 | AX16: 9.3930838 | AY16: 64.297895 | AZ16: 78.61 | BA16: 14.097635 | BB16: 2.8845327 | BC16: 1.0893353 | BD16: 130.72701 | BE16: 0.67 | BF16: 0.9858 | BG16: 0.864 | BH16: 0.5034 | BI16: 0.0289 | BJ16: 264.56589 | BK16: 255 | BL16: 0.36553199 | BM16: 29.415754 | BN16: 17.112 | BO16: 85.783 | BP16: 15.235 | BQ16: 149.63025 | BR16: 8.6237981 | BS16: 25.010079 | BT16: 20.681937 | BU16: 20.133994 | BV16: 0.60675546 | BW16: 0.040355424 | BX16: 0.0644177 | BY16: 0.004294 | BZ16: 10.4 | CA16: 6.93 | CB16: 0.0783 | CC16: 71.705998 | CD16: 10.348636 | CE16: 38.911065 | CF16: 9.4360209 | CG16: 0.35166523 | CH16: 36.2003 | CI16: 58.193603 | CJ16: 0.0041558815 | CK16: 0.16290081 | CL16: 31.722889 | CM16: 28.937 | CN16: 25.310466 | CO16: 0.125 | CP16: 0.058 | CQ16: 0.75366728 | CR16: 0.20554562 | CS16: 88.727193 | CT16: 0.006 | CU16: 0.92 | CV16: 24.05 | CW16: 3.9664153 | CX16: 3.9664153 | CY16: 8.653997 | CZ16: 644.36219
A17: Guainía | B17: 2019 | C17: 99.162656 | D17: 74.790565 | E17: 45.51375 | F17: 0.072117949 | G17: 0.031187739 | H17: 58.76 | I17: 41.86 | J17: 100 | K17: 0.0011648224 | L17: 6.2351914 | M17: 0 | N17: 39.489546 | O17: n/a | P17: n/a | Q17: 0.95238095 | R17: 0.15504416 | S17: - | T17: n/a | U17: 65.588954 | V17: 848.60133 | W17: 0.21133375 | X17: - | Y17: - | Z17: - | AA17: 37.587971 | AB17: 0.02706055 | AC17: 0 | AD17: NA | AE17: - | AF17: 50938 | AG17: 0.0064 | AH17: 0.0087196391 | AI17: 1.1717185 | AJ17: 0.13831799 | AK17: 0.29481309 | AL17: 2086.923 | AM17: 172.315 | AN17: 2.6667 | AO17: 0.00031676615 | AP17: 15.178 | AQ17: 0.040778302 | AR17: 0.17142291 | AS17: 1.6374269 | AT17: 0 | AU17: 0.99886364 | AV17: 0.93277311 | AW17: 33.413462 | AX17: 21.608643 | AY17: 0 | AZ17: 72.3 | BA17: 28.017531 | BB17: 4.4273512 | BC17: 0.58136935 | BD17: 108.07665 | BE17: 0.464 | BF17: 0.6195 | BG17: 0.2893 | BH17: 0.0679 | BI17: 0.0714 | BJ17: 225 | BK17: 246 | BL17: 0.18684211 | BM17: 31.347938 | BN17: 3.954 | BO17: 17.297 | BP17: 7.908 | BQ17: 133.45161 | BR17: 0 | BS17: 0 | BT17: 0 | BU17: 0 | BV17: 0.39939024 | BW17: 0 | BX17: 0.2112118 | BY17: 0.0284206 | BZ17: 3.95 | CA17: 1.62 | CB17: 0.0128 | CC17: 56.630991 | CD17: 12.181499 | CE17: 34.456794 | CF17: 12.264845 | CG17: 0.57186505 | CH17: 9.1611046 | CI17: 63.386119 | CJ17: 0 | CK17: 0.065242378 | CL17: 26.548902 | CM17: 0 | CN17: 0.27013891 | CO17: 1 | CP17: 1 | CQ17: 0 | CR17: 0 | CS17: 83.135886 | CT17: 0.02 | CU17: 0 | CV17: 0 | CW17: 0 | CX17: 0 | CY17: 0 | CZ17: 0
A18: Guaviare | B18: 2019 | C18: 132.91686 | D18: 75.671267 | E18: 65.67875 | F18: 0.12734789 | G18: 0.030977582 | H18: 46.74 | I18: 49.36 | J18: 95.850461 | K18: 0.00038729667 | L18: 33.829908 | M18: 0 | N18: 47.120229 | O18: 0.55917933 | P18: n/a | Q18: 0 | R18: 0.45135703 | S18: 0.37061619 | T18: n/a | U18: 83.954403 | V18: 679.44129 | W18: 0.42074713 | X18: 173.71658 | Y18: 0.26894875 | Z18: 0.57428791 | AA18: 0 | AB18: 0 | AC18: 0 | AD18: 500.67292 | AE18: 299.93078 | AF18: 26677 | AG18: 0.021 | AH18: 0.015253006 | AI18: 6.263752 | AJ18: 0.24444291 | AK18: 0.5164703 | AL18: 4937.816 | AM18: 209.334 | AN18: 1.4 | AO18: 0.0064015139 | AP18: 36.642 | AQ18: 0.15845195 | AR18: 0.16239682 | AS18: 2.6900585 | AT18: 4 | AU18: 0.94553377 | AV18: 0.93489393 | AW18: 65.757819 | AX18: 11.128776 | AY18: 0 | AZ18: 75.29 | BA18: 24.988578 | BB18: 6.8150668 | BC18: 0.30458399 | BD18: 166.73312 | BE18: 0.4244 | BF18: 0.821 | BG18: 0.665 | BH18: 0.3114 | BI18: 0.0336 | BJ18: 237 | BK18: 237 | BL18: 0.38875 | BM18: 29.108073 | BN18: 7.137 | BO18: 7.453 | BP18: 19.425 | BQ18: 138.07665 | BR18: 0 | BS18: 0 | BT18: 1.6806723 | BU18: 0 | BV18: 0.43478261 | BW18: 0.070886076 | BX18: 0.1950994 | BY18: 0.0403202 | BZ18: 6.89 | CA18: 2.92 | CB18: 0.0124 | CC18: 85.349123 | CD18: 10.821974 | CE18: 27.266439 | CF18: 13.337413 | CG18: 0.45346824 | CH18: 38.400261 | CI18: 51.284775 | CJ18: 0 | CK18: 0.18744863 | CL18: 27.353604 | CM18: 0 | CN18: 2.4022698e-05 | CO18: 1 | CP18: 1 | CQ18: 0 | CR18: 0 | CS18: 0 | CT18: 0.018 | CU18: 0 | CV18: 0 | CW18: 0 | CX18: 0 | CY18: 0 | CZ18: 12.42128
A19: Huila | B19: 2019 | C19: 113.84122 | D19: 68.986949 | E19: 57.535 | F19: 0.25605126 | G19: 0.011425822 | H19: 38.8 | I19: 48.835 | J19: 97.665056 | K19: 0.088508876 | L19: 21.719651 | M19: 0.36350881 | N19: 14.085966 | O19: 0.38740125 | P19: 486.32558 | Q19: 0.53862661 | R19: 0.82767957 | S19: 0.91439499 | T19: 0.87716493 | U19: 98.754414 | V19: 460.5719 | W19: 0.64989598 | X19: 89.678713 | Y19: 4.9613474 | Z19: 0.77159388 | AA19: 46.399173 | AB19: 2.5669683 | AC19: 0.65507178 | AD19: 241.10413 | AE19: 193.49194 | AF19: 262455 | AG19: 0.14 | AH19: 0.080902393 | AI19: 5.1347515 | AJ19: 0.30518504 | AK19: 0.6537008 | AL19: 3910.413 | AM19: 633.732 | AN19: 1.1852 | AO19: 0.00024278618 | AP19: 22.015 | AQ19: 0.34156988 | AR19: 0.17138675 | AS19: 5.1461988 | AT19: 14.3 | AU19: 0.93416396 | AV19: 0.93473965 | AW19: 90.706301 | AX19: 9.2945299 | AY19: 50.789781 | AZ19: 75.36 | BA19: 26.955553 | BB19: 8.5434987 | BC19: 3.3037966 | BD19: 224.64844 | BE19: 0.7097 | BF19: 0.924 | BG19: 0.8128 | BH19: 0.4475 | BI19: 0.0421 | BJ19: 256.7725 | BK19: 261 | BL19: 0.50051885 | BM19: 25.52213 | BN19: 26.603 | BO19: 59.449 | BP19: 13.957 | BQ19: 142.47452 | BR19: 4.2132982 | BS19: 40.684351 | BT19: 11.104319 | BU19: 12.659303 | BV19: 0.39900058 | BW19: 0.0093879084 | BX19: 0.0217237 | BY19: 0.0206157 | BZ19: 5.4 | CA19: 4.64 | CB19: 0.0345 | CC19: 63.319322 | CD19: 10.174818 | CE19: 24.03926 | CF19: 10.688051 | CG19: 0.64334497 | CH19: 32.570266 | CI19: 99.087312 | CJ19: 0.011914275 | CK19: 0.31019865 | CL19: 30.260103 | CM19: 28.011 | CN19: 9.409226 | CO19: 0.311 | CP19: 0.762 | CQ19: 0.72701761 | CR19: 0 | CS19: 89.059657 | CT19: 0.003 | CU19: 0.74 | CV19: 19.18 | CW19: 1.8405123 | CX19: 0.92025613 | CY19: 0 | CZ19: 219.02096
A20: La Guajira | B20: 2019 | C20: 76.709381 | D20: 65.232035 | E20: 53.98625 | F20: 0.11866052 | G20: 0.0058112896 | H20: 25.83 | I20: 47.095 | J20: 92.364475 | K20: 0.040539112 | L20: 25.892614 | M20: 0.56782048 | N20: 11.015717 | O20: 0.48746183 | P20: 185.78846 | Q20: 0.16783217 | R20: 0.55438784 | S20: 0.80263243 | T20: n/a | U20: 68.453627 | V20: 482.96905 | W20: 0.38246283 | X20: 42.692718 | Y20: 1.8032185 | Z20: 1 | AA20: 27.430385 | AB20: 1.1585812 | AC20: 0.19679061 | AD20: 128.14046 | AE20: 173.82128 | AF20: 170019 | AG20: 0.218 | AH20: 0.034460563 | AI20: 4.3067936 | AJ20: 0.11015511 | AK20: 0.40610938 | AL20: 1585.219 | AM20: 126.729 | AN20: 1.3636 | AO20: 0.00028213702 | AP20: 13.791 | AQ20: 0.28648286 | AR20: 0.13585629 | AS20: 3.0409357 | AT20: 17.106667 | AU20: 0.91173446 | AV20: 0.86201477 | AW20: 73.227855 | AX20: 16.179216 | AY20: 175.36912 | AZ20: 69.75 | BA20: 22.3119 | BB20: 5.9888173 | BC20: 0.61626352 | BD20: 217.9295 | BE20: 0.6637 | BF20: 0.9009 | BG20: 0.5654 | BH20: 0.2325 | BI20: 0.0277 | BJ20: 229.45375 | BK20: 232.9507 | BL20: 0.33876501 | BM20: 26.31365 | BN20: 16.83 | BO20: 8.865 | BP20: 7.085 | BQ20: 130.70199 | BR20: 6.2845304 | BS20: 2.786617 | BT20: 3.7383178 | BU20: 0 | BV20: 0.39 | BW20: 0.015907448 | BX20: 0.0556425 | BY20: 0.0077778 | BZ20: 4.52 | CA20: 1.97 | CB20: 0.0271 | CC20: 75.908155 | CD20: 3.8821058 | CE20: 18.140438 | CF20: 16.587419 | CG20: 0.73925882 | CH20: 13.359468 | CI20: 33.200011 | CJ20: 0.0029200102 | CK20: 0.091696286 | CL20: 28.948272 | CM20: 29.431 | CN20: 68.271639 | CO20: 0.175 | CP20: 0.989 | CQ20: 0.79494867 | CR20: 0 | CS20: 104.47897 | CT20: 0.003 | CU20: 0.8 | CV20: 18.92 | CW20: 0 | CX20: 0 | CY20: 0 | CZ20: 68.556947
A21: Magdalena | B21: 2019 | C21: 100.34918 | D21: 72.174371 | E21: 85.067778 | F21: 0.25072583 | G21: 0.014906462 | H21: 54.24 | I21: 61.96 | J21: 95.051949 | K21: 0.058553387 | L21: 16.545606 | M21: 0.52170828 | N21: 10.061517 | O21: 0.54621728 | P21: 298.32759 | Q21: 0.46863237 | R21: 0.7937076 | S21: 0.82005417 | T21: n/a | U21: 94.98991 | V21: 419.11668 | W21: 0.50282141 | X21: 48.054401 | Y21: 2.7806107 | Z21: 0.90956275 | AA21: 10.482671 | AB21: 0.60656729 | AC21: 0.74879587 | AD21: 173.93865 | AE21: 194.40458 | AF21: 1985735 | AG21: 0.2664 | AH21: 0.069337256 | AI21: 6.3865512 | AJ21: 0.24077879 | AK21: 0.56539173 | AL21: 2732.049 | AM21: 449.495 | AN21: 1.8125 | AO21: 0.00021760428 | AP21: 14.42 | AQ21: 0.45183848 | AR21: 0.081712686 | AS21: 1.0526316 | AT21: 9.4433333 | AU21: 0.91451978 | AV21: 0.88861583 | AW21: 85.787343 | AX21: 12.826522 | AY21: 110.79388 | AZ21: 75.39 | BA21: 20.32759 | BB21: 5.8922127 | BC21: 1.1386744 | BD21: 246.54443 | BE21: 0.6236 | BF21: 0.917 | BG21: 0.7392 | BH21: 0.4066 | BI21: 0.0326 | BJ21: 229.55982 | BK21: 228 | BL21: 0.15677301 | BM21: 28.531008 | BN21: 22.233 | BO21: 73.248 | BP21: 8.968 | BQ21: 143.5866 | BR21: 7.7883175 | BS21: 63.50553 | BT21: 16.176471 | BU21: 44.0174 | BV21: 0.39268978 | BW21: 0.027138158 | BX21: 0.0680279 | BY21: 0.0347208 | BZ21: 7.29 | CA21: 4.26 | CB21: 0.0551 | CC21: 62.388377 | CD21: 6.6666976 | CE21: 22.85422 | CF21: 9.9422449 | CG21: 0.65862451 | CH21: 18.637647 | CI21: 40.830574 | CJ21: 0.0060638137 | CK21: 0.30320689 | CL21: 29.998534 | CM21: 28.143 | CN21: 19.800018 | CO21: 0.188 | CP21: 0.28 | CQ21: 1.7141844 | CR21: 0.22358926 | CS21: 122.97409 | CT21: 0.005 | CU21: 0.71 | CV21: 25.64 | CW21: 0 | CX21: 0 | CY21: 0.76379082 | CZ21: 112.27725
A22: Meta | B22: 2019 | C22: 108.80451 | D22: 74.514372 | E22: 77.167778 | F22: 0.31470151 | G22: 0.0079748972 | H22: 54.89 | I22: 55.98 | J22: 97.236611 | K22: 0.08732341 | L22: 26.545557 | M22: 0.48089778 | N22: 44.146416 | O22: 0.57823579 | P22: 421.03623 | Q22: 0.62216359 | R22: 0.79842132 | S22: 0.82833083 | T22: 0.096083551 | U22: 97.409934 | V22: 490.8055 | W22: 0.79127854 | X22: 117.84208 | Y22: 1.4307585 | Z22: 0.79592672 | AA22: 4.901214 | AB22: 0.059507211 | AC22: 0.21005122 | AD22: 304.57366 | AE22: 237.8313 | AF22: 114688 | AG22: 0.2742 | AH22: 0.11247172 | AI22: 5.390237 | AJ22: 0.35936299 | AK22: 0.76909465 | AL22: 2079.993 | AM22: 414.277 | AN22: 1.24 | AO22: 0.0052980927 | AP22: 14.735 | AQ22: 0.51353164 | AR22: 0.20131139 | AS22: 3.625731 | AT22: 11.503448 | AU22: 0.85794847 | AV22: 0.84628389 | AW22: 82.145917 | AX22: 8.5637707 | AY22: 52.297836 | AZ22: 75.66 | BA22: 25.129575 | BB22: 6.2440712 | BC22: 1.6772294 | BD22: 247.18146 | BE22: 0.6524 | BF22: 0.9104 | BG22: 0.7831 | BH22: 0.4329 | BI22: 0.0447 | BJ22: 254.73524 | BK22: 254 | BL22: 0.38631634 | BM22: 30.975406 | BN22: 25.641 | BO22: 68.888 | BP22: 7.057 | BQ22: 143.60104 | BR22: 4.9056604 | BS22: 15.45029 | BT22: 12.656187 | BU22: 43.835616 | BV22: 0.49344978 | BW22: 0.036977492 | BX22: 0.010947 | BY22: 0.0504832 | BZ22: 9.87 | CA22: 6.48 | CB22: 0.0429 | CC22: 64.740838 | CD22: 12.167164 | CE22: 29.692489 | CF22: 9.4557911 | CG22: 0.43433329 | CH22: 42.071754 | CI22: 67.743124 | CJ22: 0.0056091314 | CK22: 0.15929475 | CL22: 30.955776 | CM22: 28.376 | CN22: 8.4175654 | CO22: 0.387 | CP22: 1 | CQ22: 0.38471822 | CR22: 0.096179556 | CS22: 65.402098 | CT22: 0.002 | CU22: 0.96 | CV22: 20 | CW22: 1.9570563 | CX22: 0.97852816 | CY22: 0 | CZ22: 209.40503
A23: Nariño | B23: 2019 | C23: 93.264191 | D23: 71.544247 | E23: 57.18 | F23: 0.19145586 | G23: 0.015436176 | H23: 53.64 | I23: 45.64 | J23: 94.25715 | K23: 0.032227976 | L23: 40.292115 | M23: 0.79725646 | N23: 13.30805 | O23: 0.63946439 | P23: 334.66864 | Q23: 0.55359629 | R23: 0.76249138 | S23: 0.23910316 | T23: 0.16132064 | U23: 97.647431 | V23: 523.43273 | W23: 0.43500682 | X23: 57.649246 | Y23: 2.8256102 | Z23: 0.77744309 | AA23: 8.0633905 | AB23: 0.39521763 | AC23: 0.15615184 | AD23: 203.51385 | AE23: 174.17068 | AF23: 320855 | AG23: 0.129 | AH23: 0.051650168 | AI23: 5.1531391 | AJ23: 0.26298032 | AK23: 0.53005205 | AL23: 2271.115 | AM23: 332.022 | AN23: 1.36 | AO23: 0.00081572655 | AP23: 5.93 | AQ23: 0.10550916 | AR23: 0.35469166 | AS23: 3.5087719 | AT23: 11.85 | AU23: 0.91285403 | AV23: 0.9206514 | AW23: 85.497359 | AX23: 9.6111599 | AY23: 115.33392 | AZ23: 76.59 | BA23: 21.399125 | BB23: 6.1685874 | BC23: 1.3591069 | BD23: 220.77871 | BE23: 0.4904 | BF23: 0.8182 | BG23: 0.6966 | BH23: 0.356 | BI23: 0.0134 | BJ23: 252.10576 | BK23: 255 | BL23: 0.52426238 | BM23: 19.381991 | BN23: 23.339 | BO23: 72.812 | BP23: 4.411 | BQ23: 146.4121 | BR23: 6.8456376 | BS23: 34.601889 | BT23: 11.973824 | BU23: 39.119429 | BV23: 0.37964656 | BW23: 0.036423841 | BX23: 0.0606729 | BY23: 0.490331 | BZ23: 3.37 | CA23: 2.34 | CB23: 0.0458 | CC23: 67.200842 | CD23: 6.4933894 | CE23: 15.816187 | CF23: 10.338033 | CG23: 0.68784237 | CH23: 21.954882 | CI23: 43.269857 | CJ23: 0.010465505 | CK23: 0.29517738 | CL23: 30.283051 | CM23: 26.869 | CN23: 5.6299888 | CO23: 0.344 | CP23: 0.442 | CQ23: 0.24530968 | CR23: 0.12265484 | CS23: 112.22918 | CT23: 0.006 | CU23: 0.52 | CV23: 25 | CW23: 0 | CX23: 0.61652889 | CY23: 3.0826445 | CZ23: 93.712392
A24: Norte de Santander | B24: 2019 | C24: 110.93117 | D24: 71.745998 | E24: 52.9725 | F24: 0.24815935 | G24: 0.014019202 | H24: 41.92 | I24: 59.43 | J24: 95.905705 | K24: 0.074770124 | L24: 35.664271 | M24: 1.5418764 | N24: 21.049964 | O24: 0.60328374 | P24: 468.84507 | Q24: 0.61313414 | R24: 0.85052791 | S24: 0.72502147 | T24: 0.61905764 | U24: 98.141035 | V24: 492.67708 | W24: 0.78384818 | X24: 81.432859 | Y24: 5.6086665 | Z24: 0.42858069 | AA24: 21.861702 | AB24: 1.5057189 | AC24: 0.097357428 | AD24: 184.06123 | AE24: 182.54351 | AF24: 909214 | AG24: 0.2514 | AH24: 0.094091261 | AI24: 7.0636987 | AJ24: 0.32110199 | AK24: 0.67936757 | AL24: 5643.528 | AM24: 686.011 | AN24: 2 | AO24: 0.0032918259 | AP24: 13.778 | AQ24: 0.30731527 | AR24: 0.3501505 | AS24: 4.4444444 | AT24: 11.8825 | AU24: 0.99987498 | AV24: 1 | AW24: 88.171581 | AX24: 9.936766 | AY24: 85.579803 | AZ24: 75.46 | BA24: 23.253725 | BB24: 4.7769415 | BC24: 1.3925143 | BD24: 191.79601 | BE24: 0.6588 | BF24: 0.9176 | BG24: 0.745 | BH24: 0.4056 | BI24: 0.0395 | BJ24: 258.12363 | BK24: 261 | BL24: 0.6181951 | BM24: 26.530975 | BN24: 41.819 | BO24: 109.971 | BP24: 10.847 | BQ24: 144.88283 | BR24: 6.7981791 | BS24: 9.5214851 | BT24: 11.316756 | BU24: 45.282041 | BV24: 0.38700418 | BW24: 0.010693215 | BX24: 0.0115219 | BY24: 0.0073139 | BZ24: 6.78 | CA24: 4.31 | CB24: 0.0449 | CC24: 58.907533 | CD24: 12.750299 | CE24: 19.759563 | CF24: 10.325177 | CG24: 0.68593419 | CH24: 22.33534 | CI24: 62.650829 | CJ24: 0.011681791 | CK24: 0.31457122 | CL24: 30.279221 | CM24: 26.843 | CN24: 6.4649026 | CO24: 0.09 | CP24: 0.506 | CQ24: 0.93853343 | CR24: 0.26815241 | CS24: 167.59526 | CT24: 0.004 | CU24: 0.21 | CV24: 15.09 | CW24: 0.69120538 | CX24: 3.4560269 | CY24: 2.7648215 | CZ24: 320.02809
A25: Putumayo | B25: 2019 | C25: 91.189349 | D25: 79.979075 | E25: 47.681429 | F25: 0.088545651 | G25: 0.00836182 | H25: 19.07 | I25: 91.03 | J25: 99.452041 | K25: 0.12615067 | L25: 45.952979 | M25: 1.4360306 | N25: 16.945161 | O25: 0.63531163 | P25: 334.87179 | Q25: 0.77570093 | R25: 0.48552531 | S25: 0.60278574 | T25: 0.64240196 | U25: 82.604396 | V25: 708.62722 | W25: 0.51493176 | X25: 147.31692 | Y25: 2.0612055 | Z25: 0.94218116 | AA25: 22.873095 | AB25: 0.32003215 | AC25: 0.40017579 | AD25: 492.35718 | AE25: 377.78693 | AF25: 34176 | AG25: 0 | AH25: 0.027410801 | AI25: 3.7434951 | AJ25: 0.20190179 | AK25: 0.44458164 | AL25: 754.055 | AM25: 225.047 | AN25: 0.5385 | AO25: 0.005485669 | AP25: 19.628 | AQ25: 0.12577708 | AR25: 0.28785972 | AS25: 0.93567251 | AT25: 6.2307692 | AU25: 0.91505043 | AV25: 0.9226597 | AW25: 83.382386 | AX25: 11.231006 | AY25: 44.043162 | AZ25: 73.83 | BA25: 21.28672 | BB25: 4.8421078 | BC25: 0.56561086 | BD25: 170.02602 | BE25: 0.4566 | BF25: 0.8071 | BG25: 0.7104 | BH25: 0.3659 | BI25: 0.0521 | BJ25: 242.76886 | BK25: 254 | BL25: 0.050427115 | BM25: 22.569751 | BN25: 3.527 | BO25: 6.75 | BP25: 8.705 | BQ25: 133.82814 | BR25: 0 | BS25: 8.9131423 | BT25: 2.5362319 | BU25: 7.6205288 | BV25: 0.43083276 | BW25: 0.0083194676 | BX25: 0.0212573 | BY25: 0.0566484 | BZ25: 5.66 | CA25: 3.21 | CB25: 0.0242 | CC25: 59.496235 | CD25: 13.181762 | CE25: 35.457374 | CF25: 3.2006897 | CG25: 0.41410057 | CH25: 16.195471 | CI25: 46.176145 | CJ25: 0.0026629937 | CK25: 0.16211352 | CL25: 28.697124 | CM25: 26.653 | CN25: 19.659587 | CO25: 0.349 | CP25: 1 | CQ25: 0 | CR25: 0 | CS25: 0 | CT25: 0.001 | CU25: 0 | CV25: 0 | CW25: 0 | CX25: 0 | CY25: 0 | CZ25: 52.824652
A26: Quindío | B26: 2019 | C26: 119.72882 | D26: 82.125734 | E26: 82.50875 | F26: 0.39692211 | G26: 0.015240856 | H26: 44.1 | I26: 47.095 | J26: 99.822784 | K26: 0.22895838 | L26: 39.26624 | M26: 0 | N26: 11.298305 | O26: 0.6347756 | P26: 511.25714 | Q26: 0.38842975 | R26: 0.96765105 | S26: 0.84398154 | T26: 0.85382407 | U26: 99.079541 | V26: 524.05442 | W26: 0.88712602 | X26: 35.932684 | Y26: 10.515014 | Z26: 0.65174206 | AA26: 44.026345 | AB26: 12.883469 | AC26: 0.42944889 | AD26: 451.13178 | AE26: 399.48844 | AF26: 387616 | AG26: 0.2414 | AH26: 0.1587122 | AI26: 5.7907821 | AJ26: 0.39758348 | AK26: 0.73075957 | AL26: 5724.24 | AM26: 646.025 | AN26: 1.15 | AO26: 0.00012860898 | AP26: 27.188 | AQ26: 0.40937646 | AR26: 0.17707016 | AS26: 3.3918129 | AT26: 16.5 | AU26: 0.97659144 | AV26: 0.93479718 | AW26: 93.233083 | AX26: 11.447121 | AY26: 34.170511 | AZ26: 75.16 | BA26: 28.371873 | BB26: 7.9053994 | BC26: 4.7896643 | BD26: 302.09074 | BE26: 0.6793 | BF26: 0.9526 | BG26: 0.8906 | BH26: 0.5466 | BI26: 0.0417 | BJ26: 259.66929 | BK26: 254 | BL26: 0.53673788 | BM26: 23.679393 | BN26: 35.724 | BO26: 53.374 | BP26: 24.404 | BQ26: 147.83433 | BR26: 6.3015312 | BS26: 50.292458 | BT26: 24.616457 | BU26: 71.582235 | BV26: 0.51088589 | BW26: 0.029547553 | BX26: 0.0394386 | BY26: 0.0616701 | BZ26: 8.71 | CA26: 5.27 | CB26: 0.0587 | CC26: 62.731802 | CD26: 13.659857 | CE26: 31.862864 | CF26: 11.482008 | CG26: 0.46690428 | CH26: 28.898069 | CI26: 77.550224 | CJ26: 0.018758208 | CK26: 0.35598293 | CL26: 29.586967 | CM26: 27.507 | CN26: 11.859113 | CO26: 0.295 | CP26: 0.982 | CQ26: 1.2965268 | CR26: 0 | CS26: 240.78355 | CT26: 0.003 | CU26: 0.88 | CV26: 16.67 | CW26: 13.109449 | CX26: 9.3638921 | CY26: 5.6183352 | CZ26: 569.32464
A27: Risaralda | B27: 2019 | C27: 130.25197 | D27: 74.700247 | E27: 73.806667 | F27: 0.40836343 | G27: 0.010639237 | H27: 64.77 | I27: 54.82 | J27: 92.255357 | K27: 0.2062096 | L27: 23.425881 | M27: 0.52999732 | N27: 11.977939 | O27: 0.52609857 | P27: 622.3617 | Q27: 0.68453378 | R27: 0.94042369 | S27: 0.77170322 | T27: n/a | U27: 99.675523 | V27: 466.38124 | W27: 0.8311866 | X27: 45.851022 | Y27: 10.448285 | Z27: 0.84456317 | AA27: 17.027118 | AB27: 3.8800483 | AC27: 0.20886612 | AD27: 419.65865 | AE27: 284.77545 | AF27: 1742190 | AG27: 0.2754 | AH27: 0.15578024 | AI27: 6.0568779 | AJ27: 0.45144131 | AK27: 0.77874369 | AL27: 10323.646 | AM27: 1269.485 | AN27: 1.6 | AO27: 9.419847e-05 | AP27: 21.768 | AQ27: 0.42783909 | AR27: 0.1743098 | AS27: 4.7953216 | AT27: 6.6857143 | AU27: 0.94202899 | AV27: 0.91289542 | AW27: 90.567113 | AX27: 11.078496 | AY27: 66.281602 | AZ27: 76.64 | BA27: 32.388063 | BB27: 9.6927386 | BC27: 6.3452186 | BD27: 235.53081 | BE27: 0.696 | BF27: 0.9623 | BG27: 0.8442 | BH27: 0.4919 | BI27: 0.0423 | BJ27: 259.38986 | BK27: 256 | BL27: 0.40294737 | BM27: 22.751489 | BN27: 42.592 | BO27: 223.383 | BP27: 19.88 | BQ27: 148.43533 | BR27: 7.7373974 | BS27: 48.159901 | BT27: 26.29784 | BU27: 44.890272 | BV27: 0.58367033 | BW27: 0.053558844 | BX27: 0.0247299 | BY27: 0.0395242 | BZ27: 7.31 | CA27: 7.05 | CB27: 0.0682 | CC27: 64.361578 | CD27: 7.8745848 | CE27: 34.441655 | CF27: 5.2056003 | CG27: 0.37900643 | CH27: 30.963336 | CI27: 81.828651 | CJ27: 0.026405993 | CK27: 0.39803017 | CL27: 30.329562 | CM27: 28.26 | CN27: 19.067224 | CO27: 0.186 | CP27: 0.572 | CQ27: 2.4379877 | CR27: 0.21199893 | CS27: 217.2989 | CT27: 0.004 | CU27: 1.07 | CV27: 18.62 | CW27: 4.2773246 | CX27: 6.4159869 | CY27: 16.039967 | CZ27: 982.71533
A28: Archipiélago de San Andrés | B28: 2019 | C28: 122.913 | D28: 39.860804 | E28: 71.24 | F28: 0.34498449 | G28: 0.035402096 | H28: 52.03 | I28: 55.95 | J28: 78.666169 | K28: 0.26731333 | L28: 42.428198 | M28: 0 | N28: 17.950392 | O28: 0.48422733 | P28: 259.29412 | Q28: 0.43181818 | R28: 0.50283231 | S28: - | T28: n/a | U28: 99.806392 | V28: 593.53487 | W28: 0.28434215 | X28: 74.654047 | Y28: 15.958075 | Z28: 0.86827839 | AA28: 35.80127 | AB28: 20.487505 | AC28: 0.75417646 | AD28: NA | AE28: - | AF28: 1983714 | AG28: 0.264 | AH28: 0.054051621 | AI28: 1.6827399 | AJ28: 0.36909532 | AK28: 0.77338454 | AL28: 6169.889 | AM28: 130.35 | AN28: 0.4444 | AO28: 0 | AP28: 2.249 | AQ28: 0.41256026 | AR28: 0.19504095 | AS28: 4.2105263 | AT28: 1.5 | AU28: 0.95060373 | AV28: 0.96528555 | AW28: 92.154567 | AX28: 25.761124 | AY28: 0 | AZ28: 74.67 | BA28: 53.684931 | BB28: 10.088334 | BC28: 2.0698197 | BD28: 279.047 | BE28: 0.6869 | BF28: 0.9296 | BG28: 0.8423 | BH28: 0.509 | BI28: 0.0197 | BJ28: 238 | BK28: 247 | BL28: 0.37075718 | BM28: 30.510811 | BN28: 1.441 | BO28: 16.311 | BP28: 26.589 | BQ28: 132.29815 | BR28: 40.740741 | BS28: 6.863418 | BT28: 26.618705 | BU28: 82.640145 | BV28: 0.73697917 | BW28: 0 | BX28: 0.243614 | BY28: 0.022234 | BZ28: 16.16 | CA28: 14.88 | CB28: 0.068 | CC28: 72.94158 | CD28: 7.3804738 | CE28: 58.619792 | CF28: 1.0646243 | CG28: 0.35211783 | CH28: 29.835345 | CI28: 105.43766 | CJ28: 0.0026334989 | CK28: 0.25532263 | CL28: 27.998685 | CM28: 0 | CN28: 0.93205029 | CO28: 1 | CP28: 1 | CQ28: 0 | CR28: 0 | CS28: 65.274151 | CT28: 0.006 | CU28: 0 | CV28: 0 | CW28: 16.310819 | CX28: 0 | CY28: 0 | CZ28: 1223.3114
A29: Santander | B29: 2019 | C29: 112.89371 | D29: 68.849706 | E29: 78.63375 | F29: 0.37421912 | G29: 0.0087799905 | H29: 42.46 | I29: 55.11 | J29: 94.428537 | K29: 0.084975319 | L29: 11.213651 | M29: 0.13731001 | N29: 9.794781 | O29: 0.50326567 | P29: 389.46349 | Q29: 0.51980485 | R29: 0.82458737 | S29: 0.83850277 | T29: 0.22516417 | U29: 99.520925 | V29: 461.45612 | W29: 0.76065828 | X29: 82.266915 | Y29: 5.8859678 | Z29: 0.81469627 | AA29: 24.098831 | AB29: 1.724204 | AC29: 0.2397777 | AD29: 270.00979 | AE29: 228.92022 | AF29: 1595907 | AG29: 0.2756 | AH29: 0.15785766 | AI29: 6.0327893 | AJ29: 0.39957684 | AK29: 0.73688093 | AL29: 6341.352 | AM29: 930.326 | AN29: 2.6341 | AO29: 0.00086613046 | AP29: 26.589 | AQ29: 0.45095195 | AR29: 0.18638076 | AS29: 0.70175439 | AT29: 8.2517241 | AU29: 0.89882184 | AV29: 0.89081445 | AW29: 92.149489 | AX29: 5.6549797 | AY29: 49.89688 | AZ29: 78.3 | BA29: 42.163179 | BB29: 8.8280217 | BC29: 4.2538659 | BD29: 257.54782 | BE29: 0.6751 | BF29: 0.9488 | BG29: 0.8383 | BH29: 0.4963 | BI29: 0.032 | BJ29: 270.72616 | BK29: 268 | BL29: 0.50265322 | BM29: 21.668793 | BN29: 37.68 | BO29: 330.958 | BP29: 23.143 | BQ29: 152.29188 | BR29: 7.3492083 | BS29: 36.703556 | BT29: 26.410486 | BU29: 50.103764 | BV29: 0.51153888 | BW29: 0.036775571 | BX29: 0.0123496 | BY29: 0.0040818 | BZ29: 8.25 | CA29: 8.05 | CB29: 0.057 | CC29: 67.330537 | CD29: 9.6036375 | CE29: 32.302158 | CF29: 7.8177406 | CG29: 0.51367453 | CH29: 37.948442 | CI29: 86.366228 | CJ29: 0.012671403 | CK29: 0.2759738 | CL29: 31.703195 | CM29: 28.266 | CN29: 6.2302181 | CO29: 0.233 | CP29: 0.281 | CQ29: 2.7919703 | CR29: 0.45770005 | CS29: 298.42043 | CT29: 0.008 | CU29: 0.99 | CV29: 21.78 | CW29: 8.8516354 | CX29: 4.6587555 | CY29: 6.5222577 | CZ29: 676.91717
A30: Sucre | B30: 2019 | C30: 92.030256 | D30: 76.325314 | E30: 43.035 | F30: 0.18697712 | G30: 0.01410738 | H30: 53.26 | I30: 44.185 | J30: 98.13895 | K30: 0.13624799 | L30: 16.356067 | M30: 0 | N30: 9.5042012 | O30: 0.50719397 | P30: 305.09091 | Q30: 0.52641879 | R30: 0.85833787 | S30: 0.89464363 | T30: n/a | U30: 97.644088 | V30: 426.51937 | W30: 0.59222139 | X30: 49.927779 | Y30: 4.1382981 | Z30: 1 | AA30: 9.8811629 | AB30: 0.81900693 | AC30: 0 | AD30: 292.94556 | AE30: 314.91685 | AF30: 93063 | AG30: 0.1116 | AH30: 0.054398817 | AI30: 4.8063447 | AJ30: 0.19657754 | AK30: 0.48424301 | AL30: 1567.517 | AM30: 317.425 | AN30: 1.1905 | AO30: 7.8780865e-05 | AP30: 1.496 | AQ30: 0.33312271 | AR30: 0.093757272 | AS30: 0.58479532 | AT30: 15.053846 | AU30: 0.93734909 | AV30: 0.92136067 | AW30: 87.889564 | AX30: 11.766988 | AY30: 77.584535 | AZ30: 76.14 | BA30: 19.487188 | BB30: 5.2302435 | BC30: 1.6526156 | BD30: 314.96481 | BE30: 0.7216 | BF30: 0.9533 | BG30: 0.7531 | BH30: 0.4167 | BI30: 0.0278 | BJ30: 237 | BK30: 241 | BL30: 0.30492333 | BM30: 25.270655 | BN30: 25.615 | BO30: 29.033 | BP30: 5.398 | BQ30: 140.9543 | BR30: 5.1899907 | BS30: 5.2638239 | BT30: 10.17316 | BU30: 32.900475 | BV30: 0.29774436 | BW30: 0.0075244545 | BX30: 0.019493 | BY30: 0.0500241 | BZ30: 4.46 | CA30: 2.76 | CB30: 0.0429 | CC30: 68.381111 | CD30: 8.8268112 | CE30: 14.973001 | CF30: 10.260391 | CG30: 0.67812322 | CH30: 23.945114 | CI30: 31.96698 | CJ30: 0.0049791056 | CK30: 0.20793924 | CL30: 29.305731 | CM30: 28.275 | CN30: 31.052817 | CO30: 0.338 | CP30: 0.98 | CQ30: 0.55256984 | CR30: 0 | CS30: 99.462571 | CT30: 0.001 | CU30: 0.61 | CV30: 18.19 | CW30: 0 | CX30: 0 | CY30: 0 | CZ30: 54.015246
A31: Tolima | B31: 2019 | C31: 122.21172 | D31: 67.077971 | E31: 59.125 | F31: 0.23045368 | G31: 0.010182753 | H31: 36.09 | I31: 92.31 | J31: 93.558366 | K31: 0.15838056 | L31: 20.673785 | M31: 0.2255322 | N31: 15.33619 | O31: 0.50714815 | P31: 341.41237 | Q31: 0.64402367 | R31: 0.8549436 | S31: 0.76207586 | T31: 0.081851574 | U31: 98.306345 | V31: 464.67532 | W31: 0.71978111 | X31: 73.134228 | Y31: 4.1287751 | Z31: 0.87467979 | AA31: 61.537212 | AB31: 3.4740684 | AC31: 0.30228694 | AD31: 244.36683 | AE31: 195.15172 | AF31: 125335 | AG31: 0.2258 | AH31: 0.10386379 | AI31: 5.4056544 | AJ31: 0.32645871 | AK31: 0.67995856 | AL31: 4721.137 | AM31: 1152.753 | AN31: 2 | AO31: 0.00011074535 | AP31: 11.22 | AQ31: 0.3762894 | AR31: 0.22538158 | AS31: 4.7953216 | AT31: 4.6106383 | AU31: 0.92524987 | AV31: 0.8886354 | AW31: 89.486539 | AX31: 7.9100514 | AY31: 79.100514 | AZ31: 76.55 | BA31: 24.922109 | BB31: 5.8013047 | BC31: 2.0440966 | BD31: 220.26978 | BE31: 0.7209 | BF31: 0.982 | BG31: 0.8351 | BH31: 0.4672 | BI31: 0.0302 | BJ31: 246.71335 | BK31: 247.97215 | BL31: 0.48032013 | BM31: 23.447957 | BN31: 25.974 | BO31: 68.24 | BP31: 18.638 | BQ31: 144.63853 | BR31: 7.892204 | BS31: 41.677307 | BT31: 14.597262 | BU31: 28.673394 | BV31: 0.41854637 | BW31: 0.0097765363 | BX31: 0.0193086 | BY31: 0.0520908 | BZ31: 6.41 | CA31: 4.4 | CB31: 0.0364 | CC31: 64.253284 | CD31: 14.130461 | CE31: 25.162402 | CF31: 11.676112 | CG31: 0.45585944 | CH31: 34.316315 | CI31: 74.919667 | CJ31: 0.0097594702 | CK31: 0.32652208 | CL31: 30.605402 | CM31: 26.849 | CN31: 2.7542179 | CO31: 0.25 | CP31: 0.542 | CQ31: 0.8269514 | CR31: 0 | CS31: 130.0569 | CT31: 0.004 | CU31: 0.97 | CV31: 25.61 | CW31: 1.5080648 | CX31: 1.5080648 | CY31: 2.2620971 | CZ31: 318.20166
A32: Valle del Cauca | B32: 2019 | C32: 164.37937 | D32: 74.622173 | E32: 68.97 | F32: 0.43711545 | G32: 0.0098118857 | H32: 56.58 | I32: 87.21 | J32: 98.214253 | K32: 0.2937399 | L32: 50.64919 | M32: 0.33512918 | N32: 15.304233 | O32: 0.55186344 | P32: 481.81905 | Q32: 0.47970564 | R32: 0.95725696 | S32: 1 | T32: 0.043203717 | U32: 99.272399 | V32: 457.2777 | W32: 0.89236648 | X32: 29.258967 | Y32: 5.9150768 | Z32: 0.76274968 | AA32: 18.351658 | AB32: 3.710024 | AC32: 0.45989721 | AD32: 289.85646 | AE32: 245.79219 | AF32: 4647659 | AG32: 0.373 | AH32: 0.15017325 | AI32: 5.8844799 | AJ32: 0.47339746 | AK32: 0.80063697 | AL32: 4343.63 | AM32: 648.206 | AN32: 2.0308 | AO32: 0.00014668495 | AP32: 23.142 | AQ32: 0.51330236 | AR32: 0.19939801 | AS32: 8.7719298 | AT32: 17.840476 | AU32: 0.94257355 | AV32: 0.92691051 | AW32: 91.086443 | AX32: 10.050349 | AY32: 42.602634 | AZ32: 75.53 | BA32: 38.91637 | BB32: 8.8982639 | BC32: 4.39454 | BD32: 232.4456 | BE32: 0.5398 | BF32: 0.7619 | BG32: 0.7145 | BH32: 0.402 | BI32: 0.0326 | BJ32: 256.30779 | BK32: 250 | BL32: 0.25354251 | BM32: 27.337256 | BN32: 30.116 | BO32: 115.802 | BP32: 15.7 | BQ32: 149.33876 | BR32: 11.083951 | BS32: 43.223657 | BT32: 26.40072 | BU32: 28.294518 | BV32: 0.57842513 | BW32: 0.056931998 | BX32: 0.011935 | BY32: 0.0069854 | BZ32: 10.33 | CA32: 8.75 | CB32: 0.0653 | CC32: 65.263278 | CD32: 12.11556 | CE32: 36.424201 | CF32: 11.408238 | CG32: 0.39352299 | CH32: 39.774143 | CI32: 81.014931 | CJ32: 0.022722992 | CK32: 0.43193301 | CL32: 32.184256 | CM32: 29.125 | CN32: 17.485041 | CO32: 0.102 | CP32: 0.036 | CQ32: 3.2395821 | CR32: 0.31278723 | CS32: 253.35766 | CT32: 0.006 | CU32: 1.07 | CV32: 23.22 | CW32: 5.1888879 | CX32: 6.0913032 | CY32: 13.761833 | CZ32: 1143.3602
A33: Vaupés | B33: 2019 | C33: 93.336924 | D33: 59.515174 | E33: 42.608571 | F33: 0.061523909 | G33: 0.029323731 | H33: 54.52 | I33: 93.02 | J33: 96.940973 | K33: 0.0012357121 | L33: 7.3534819 | M33: 0 | N33: 7.3534819 | O33: n/a | P33: n/a | Q33: 1 | R33: 0.40757993 | S33: - | T33: n/a | U33: 58.050665 | V33: 608.91108 | W33: 0.35686799 | X33: - | Y33: - | Z33: - | AA33: 62.043778 | AB33: 0.046757181 | AC33: 0 | AD33: NA | AE33: - | AF33: 29768 | AG33: 0.0198 | AH33: 0.0014606742 | AI33: 2.0644154 | AJ33: 0.11855972 | AK33: 0.19856341 | AL33: 0 | AM33: 0 | AN33: 0 | AO33: 0.00019716295 | AP33: 10.615 | AQ33: 0.36399552 | AR33: 0.070092901 | AS33: 1.1695906 | AT33: 6.7666667 | AU33: 0.86542923 | AV33: 0.83513839 | AW33: 37.943262 | AX33: 10.118044 | AY33: 0 | AZ33: 63.93 | BA33: 13.139892 | BB33: 1.7812427 | BC33: 0.41304179 | BD33: 49.023212 | BE33: 0.2282 | BF33: 0.5112 | BG33: 0.3054 | BH33: 0.1135 | BI33: 0.0388 | BJ33: 212 | BK33: 223 | BL33: 0.16111111 | BM33: 27.017647 | BN33: 1.007 | BO33: 0 | BP33: 4.338 | BQ33: 132.63913 | BR33: 0 | BS33: 15.853659 | BT33: 0 | BU33: 0 | BV33: 0.33 | BW33: 0.011695906 | BX33: 0.56299069 | BY33: 0.0581058 | BZ33: 2.94 | CA33: 0.98 | CB33: 0 | CC33: 49.090899 | CD33: 8.0178323 | CE33: 49.73976 | CF33: 1.8365504 | CG33: 0.45411235 | CH33: 14.521375 | CI33: 27.753253 | CJ33: 0.0092724848 | CK33: 0.024149309 | CL33: 26.294629 | CM33: 17.93 | CN33: 0.11150923 | CO33: 1 | CP33: 1 | CQ33: 0 | CR33: 0 | CS33: 24.511606 | CT33: 0.017 | CU33: 0 | CV33: 0 | CW33: 0 | CX33: 0 | CY33: 0 | CZ33: 25.118686
A34: Vichada | B34: 2019 | C34: 87.137365 | D34: 62.27916 | E34: 36.301429 | F34: 0.057098268 | G34: 0.013996767 | H34: 38.33 | I34: 51.28 | J34: 95.321603 | K34: 0.0042305658 | L34: 20.406649 | M34: 0 | N34: 15.768774 | O34: n/a | P34: n/a | Q34: 0.68421053 | R34: 0.63267664 | S34: - | T34: n/a | U34: 69.074038 | V34: 453.72959 | W34: 0.053125071 | X34: 89.176128 | Y34: 0.095906905 | Z34: 0.75862069 | AA34: 34.320273 | AB34: 0.036910676 | AC34: 1 | AD34: NA | AE34: - | AF34: 40482 | AG34: 0.0034 | AH34: 0.029376689 | AI34: 1.0560217 | AJ34: 0.067020843 | AK34: 0.1801922 | AL34: 494.176 | AM34: 52.947 | AN34: 1.25 | AO34: 0.00065471962 | AP34: 5.713 | AQ34: 0.34509736 | AR34: 0.089006412 | AS34: 0 | AT34: 8.775 | AU34: 0.88989845 | AV34: 0.60351455 | AW34: 48.415842 | AX34: 30.511811 | AY34: 320.46157 | AZ34: 65.35 | BA34: 25.997682 | BB34: 3.4384345 | BC34: 0.43832734 | BD34: 86.26447 | BE34: 0.3074 | BF34: 0.5668 | BG34: 0.2406 | BH34: 0.0936 | BI34: 0.0714 | BJ34: 225 | BK34: 237 | BL34: 0.2195122 | BM34: 31.807453 | BN34: 1.049 | BO34: 2.856 | BP34: 6.157 | BQ34: 135.00229 | BR34: 0 | BS34: 0 | BT34: 3.5714286 | BU34: 0 | BV34: 0.50666667 | BW34: 0.026315789 | BX34: 0.1869422 | BY34: 0.0385288 | BZ34: 1.39 | CA34: 1.09 | CB34: 0.0254 | CC34: 69.94931 | CD34: 18.593325 | CE34: 32.145618 | CF34: 14.427529 | CG34: 0.52424778 | CH34: 15.502495 | CI34: 22.223806 | CJ34: 0.0034745739 | CK34: 0.11640668 | CL34: 27.11762 | CM34: 0 | CN34: 0.33160104 | CO34: 1 | CP34: 1 | CQ34: 0 | CR34: 0 | CS34: 0 | CT34: 0.023 | CU34: 0 | CV34: 0 | CW34: 0 | CX34: 0 | CY34: 0 | CZ34: 0
A35: Amazonas | B35: 2020 | C35: 94.551979 | D35: 76.954873 | E35: 33.241429 | F35: 0.098366553 | G35: 0.017550039 | H35: 32.38 | I35: 45.35 | J35: 94.404236 | K35: 0 | L35: 10.288992 | M35: 0 | N35: 7.716744 | O35: n/a | P35: n/a | Q35: 0.3 | R35: 0.22533666 | S35: - | T35: n/a | U35: 85.479294 | V35: 611.11502 | W35: 0.18499224 | X35: 26.204807 | Y35: 0.01830119 | Z35: 0.88012048 | AA35: 12.153872 | AB35: 0.0086171522 | AC35: 0.28042328 | AD35: NA | AE35: - | AF35: 302957 | AG35: 0.232 | AH35: 0.012142736 | AI35: 1.7534643 | AJ35: 0.10872453 | AK35: 0.30864158 | AL35: 426.645 | AM35: 41.288 | AN35: 0.5556 | AO35: 6.9221614e-05 | AP35: 20.92077 | AQ35: 0.35748886 | AR35: 0.2009002 | AS35: 4.1176471 | AT35: 10.15 | AU35: 0.88018171 | AV35: 0.84058824 | AW35: 55.410312 | AX35: 25.380711 | AY35: 0 | AZ35: 72.32 | BA35: 37.267922 | BB35: 7.0741293 | BC35: 1.1248137 | BD35: 214.78271 | BE35: 0.4599 | BF35: 0.7833 | BG35: 0.6151 | BH35: 0.3151 | BI35: 0.0487 | BJ35: 224 | BK35: 230 | BL35: 0.17716535 | BM35: 28.015748 | BN35: 4.377 | BO35: 117.51 | BP35: 4.39 | BQ35: 137.18396 | BR35: 47.058824 | BS35: 16.787265 | BT35: 5.4545455 | BU35: 0 | BV35: 0.42741935 | BW35: 0.026490066 | BX35: 0.1582474 | BY35: 0.0180783 | BZ35: 6.17 | CA35: 3.4853961 | CB35: 0.0332 | CC35: 63.908395 | CD35: 7.2950281 | CE35: 36.771517 | CF35: 5.0220938 | CG35: 0.63496341 | CH35: 16.047631 | CI35: 46.170663 | CJ35: 0.0016453915 | CK35: 0.21842066 | CL35: 27.355509 | CM35: 0 | CN35: 0.00024221821 | CO35: 1 | CP35: 1 | CQ35: 5.144496 | CR35: 0 | CS35: 270.08604 | CT35: 0.014 | CU35: 1.22 | CV35: 63.64 | CW35: 0 | CX35: 0 | CY35: 0 | CZ35: 261.13411
A36: Antioquia | B36: 2020 | C36: 143.55973 | D36: 69.434146 | E36: 83.688889 | F36: 0.43598876 | G36: 0.0083705309 | H36: 52.65 | I36: 67.65 | J36: 95.935148 | K36: 0.021478217 | L36: 36.640069 | M36: 0.16793365 | N36: 21.861908 | O36: 0.60969312 | P36: 609.73628 | Q36: 0.52019544 | R36: 0.86388918 | S36: 0.63436048 | T36: 0.15532646 | U36: 99.330783 | V36: 506.28375 | W36: 0.77727684 | X36: 32.509393 | Y36: 3.2743979 | Z36: 0.8687714 | AA36: 23.376436 | AB36: 2.4071004 | AC36: 0.85592802 | AD36: 439.80992 | AE36: 361.59621 | AF36: 9941050 | AG36: 0.5446 | AH36: 0.18171944 | AI36: 9.926693 | AJ36: 0.42085284 | AK36: 0.71721344 | AL36: 5711.979 | AM36: 717.971 | AN36: 2.5395 | AO36: 0.0019680995 | AP36: 10.837968 | AQ36: 0.5039765 | AR36: 0.19010569 | AS36: 3.7254902 | AT36: 5.728 | AU36: 0.958507 | AV36: 0.94016493 | AW36: 90.137612 | AX36: 8.4810483 | AY36: 65.651085 | AZ36: 76.13 | BA36: 33.361068 | BB36: 8.4893498 | BC36: 6.0154763 | BD36: 146.94194 | BE36: 0.6798 | BF36: 0.9189 | BG36: 0.8129 | BH36: 0.4383 | BI36: 0.0397 | BJ36: 252.58375 | BK36: 251 | BL36: 0.39488621 | BM36: 29.908373 | BN36: 37.461 | BO36: 196.142 | BP36: 20.485 | BQ36: 153.14446 | BR36: 11.213383 | BS36: 37.469734 | BT36: 31.812491 | BU36: 54.298127 | BV36: 0.61464342 | BW36: 0.036311914 | BX36: 0.0064338 | BY36: 0.0269354 | BZ36: 13.8 | CA36: 10.364712 | CB36: 0.0741 | CC36: 61.279501 | CD36: 12.360859 | CE36: 45.202645 | CF36: 9.8289702 | CG36: 0.31252776 | CH36: 35.589027 | CI36: 93.770496 | CJ36: 0.029268049 | CK36: 0.57151132 | CL36: 32.641496 | CM36: 30.383 | CN36: 24.376251 | CO36: 0.103 | CP36: 0.111 | CQ36: 5.0532762 | CR36: 0.6717346 | CS36: 445.63484 | CT36: 0.009 | CU36: 1.25 | CV36: 19.54 | CW36: 17.636679 | CX36: 6.8673794 | CY36: 33.088282 | CZ36: 1972.0304
A37: Arauca | B37: 2020 | C37: 99.315437 | D37: 74.552247 | E37: 30.83625 | F37: 0.082135569 | G37: 0.0094809767 | H37: 44.83 | I37: 84.62 | J37: 94.906511 | K37: 0.060117411 | L37: 61.047664 | M37: 2.4990272 | N37: 50.337547 | O37: 0.4793915 | P37: 429.92857 | Q37: 0.70942408 | R37: 0.7182601 | S37: 0.068069745 | T37: n/a | U37: 95.114412 | V37: 579.94782 | W37: 0.53978742 | X37: 168.4492 | Y37: 1.8541859 | Z37: 0.49469736 | AA37: 60.47967 | AB37: 0.71126459 | AC37: 0 | AD37: 396.03334 | AE37: 445.39894 | AF37: 135799 | AG37: 0.1142 | AH37: 0.042994347 | AI37: 7.0562814 | AJ37: 0.16453447 | AK37: 0.60897068 | AL37: 556.646 | AM37: 164.19 | AN37: 0.375 | AO37: 0.0017308964 | AP37: 21.607065 | AQ37: 0.12551316 | AR37: 0.28891482 | AS37: 0.19607843 | AT37: 8.2714286 | AU37: 1 | AV37: 1 | AW37: 75.192508 | AX37: 10.830325 | AY37: 100.28079 | AZ37: 75.57 | BA37: 30.609404 | BB37: 6.490422 | BC37: 1.1834271 | BD37: 137.8035 | BE37: 0.6166 | BF37: 0.9381 | BG37: 0.7465 | BH37: 0.3666 | BI37: 0.0263 | BJ37: 248.89507 | BK37: 252 | BL37: 0.54151329 | BM37: 28.163599 | BN37: 6.756 | BO37: 18.69 | BP37: 3.015 | BQ37: 136.95221 | BR37: 45.454545 | BS37: 1.0582011 | BT37: 4.5454545 | BU37: 39.355051 | BV37: 0.44462541 | BW37: 0.031512605 | BX37: 0.0814861 | BY37: 0.50010912 | BZ37: 5.64 | CA37: 3.9484629 | CB37: 0.0262 | CC37: 63.230769 | CD37: 19.335204 | CE37: 26.142416 | CF37: 17.748485 | CG37: 0.51732804 | CH37: 32.340155 | CI37: 46.972749 | CJ37: 0.0001843595 | CK37: 0.12201723 | CL37: 29.108507 | CM37: 26.273 | CN37: 13.957577 | CO37: 0.503 | CP37: 0.987 | CQ37: 0 | CR37: 0 | CS37: 17.850194 | CT37: 0.001 | CU37: 0 | CV37: 0 | CW37: 0 | CX37: 0 | CY37: 0 | CZ37: 80.099476
A38: Atlántico | B38: 2020 | C38: 135.76416 | D38: 79.594878 | E38: 74.765 | F38: 0.4941258 | G38: 0.011030812 | H38: 68.81 | I38: 75.58 | J38: 96.298918 | K38: 0.18191705 | L38: 20.506787 | M38: 0.15162134 | N38: 7.9222152 | O38: 0.56215005 | P38: 519.70256 | Q38: 0.36936211 | R38: 0.98462606 | S38: 0.87907121 | T38: n/a | U38: 99.638348 | V38: 454.44247 | W38: 0.85891767 | X38: 14.652672 | Y38: 10.965791 | Z38: 1 | AA38: 3.5198895 | AB38: 2.7408501 | AC38: 0.27620073 | AD38: 217.74128 | AE38: 221.13105 | AF38: 2671774 | AG38: 0.3216 | AH38: 0.13678552 | AI38: 9.7801082 | AJ38: 0.42942046 | AK38: 0.76209119 | AL38: 5443.658 | AM38: 695.529 | AN38: 2.3784 | AO38: 0 | AP38: 1.6833264 | AQ38: 0.6960408 | AR38: 0.13184313 | AS38: 1.372549 | AT38: 20.530435 | AU38: 1 | AV38: 0.9949302 | AW38: 87.712144 | AX38: 14.354744 | AY38: 91.92693 | AZ38: 77.49 | BA38: 42.661738 | BB38: 9.4406946 | BC38: 3.4642936 | BD38: 272.0466 | BE38: 0.6154 | BF38: 0.8902 | BG38: 0.7655 | BH38: 0.4927 | BI38: 0.0155 | BJ38: 248.4899 | BK38: 241 | BL38: 0.51804311 | BM38: 30.910148 | BN38: 39.243 | BO38: 206.072 | BP38: 17.395 | BQ38: 146.77191 | BR38: 13.395079 | BS38: 53.32355 | BT38: 29.000071 | BU38: 61.687883 | BV38: 0.46802622 | BW38: 0.014423077 | BX38: 0.0250715 | BY38: 0.0672318 | BZ38: 16.76 | CA38: 10.85 | CB38: 0.0597 | CC38: 63.233252 | CD38: 7.2567438 | CE38: 31.297966 | CF38: 13.247555 | CG38: 0.5037019 | CH38: 31.649641 | CI38: 63.016142 | CJ38: 0.024633221 | CK38: 0.57294457 | CL38: 31.493615 | CM38: 29.144 | CN38: 28.542946 | CO38: 0.133 | CP38: 0.051 | CQ38: 4.8897883 | CR38: 0.9476334 | CS38: 490.49505 | CT38: 0.005 | CU38: 1.52 | CV38: 21.6 | CW38: 8.2823345 | CX38: 2.7607782 | CY38: 2.3663813 | CZ38: 798.65369
A39: Bogotá, D.C. | B39: 2020 | C39: 161.39709 | D39: 79.6 | E39: 91.9025 | F39: 0.51387492 | G39: 0.035307409 | H39: 68.09 | I39: 48.215 | J39: 98.6 | K39: 0.31486151 | L39: 14.039485 | M39: 0.11853224 | N39: 12.063948 | O39: 0.53365908 | P39: 703.16257 | Q39: 0.45205923 | R39: 0.99570168 | S39: 0.9648626 | T39: n/a | U39: 99.894262 | V39: 483.89172 | W39: 0.99460532 | X39: - | Y39: - | Z39: - | AA39: - | AB39: - | AC39: - | AD39: 418.24549 | AE39: 326.48867 | AF39: 27874054 | AG39: 1 | AH39: 0.25312031 | AI39: 12.107394 | AJ39: 0.63750727 | AK39: 0.87104408 | AL39: 10166.292 | AM39: 1601.455 | AN39: 2.7656 | AO39: 6.7894537e-05 | AP39: 36.426847 | AQ39: 0.60757249 | AR39: 0.17004523 | AS39: 1.1111111 | AT39: 5.1 | AU39: 0.89949711 | AV39: 0.8604496 | AW39: 87.819285 | AX39: 9.2440734 | AY39: 56.198461 | AZ39: 79.54 | BA39: 55.171692 | BB39: 13.942219 | BC39: 7.0441761 | BD39: 183.85667 | BE39: 0.7065 | BF39: 0.9781 | BG39: 0.8597 | BH39: 0.5601 | BI39: 0.0165 | BJ39: 272.38782 | BK39: 257 | BL39: 0.37160875 | BM39: 40.983516 | BN39: 82.817 | BO39: 410.77212 | BP39: 31.188 | BQ39: 155.68934 | BR39: 8.2291743 | BS39: 33.25359 | BT39: 37.870642 | BU39: 34.338201 | BV39: 0.69742311 | BW39: 0.077423018 | BX39: 0.0052625 | BY39: 0.0067017 | BZ39: 17.164 | CA39: 15.8388 | CB39: 0.0723 | CC39: 71.002874 | CD39: 10.868966 | CE39: 51.279573 | CF39: 10.463362 | CG39: 0.32939126 | CH39: 77.202355 | CI39: 121.98248 | CJ39: 0.033769623 | CK39: 0.69614756 | CL39: 33.412116 | CM39: 29.731 | CN39: 33.675727 | CO39: 0.144 | CP39: 0.017 | CQ39: 7.6519145 | CR39: 1.1104788 | CS39: 707.63747 | CT39: 0.01 | CU39: 1.79 | CV39: 18.8 | CW39: 18.112989 | CX39: 9.8922426 | CY39: 33.30268 | CZ39: 2026.145
A40: Bolívar | B40: 2020 | C40: 111.78606 | D40: 71.624394 | E40: 52.02 | F40: 0.28973369 | G40: 0.0089621507 | H40: 48.95 | I40: 97.67 | J40: 95.231565 | K40: 0.18785311 | L40: 18.587081 | M40: 0.1877483 | N40: 9.4343519 | O40: 0.53163882 | P40: 445.02874 | Q40: 0.43725156 | R40: 0.80527502 | S40: 0.90558108 | T40: 0.30489472 | U40: 95.802788 | V40: 455.12106 | W40: 0.46285066 | X40: 40.529537 | Y40: 3.229679 | Z40: 0.90760402 | AA40: 7.603806 | AB40: 0.62360459 | AC40: 0.87962963 | AD40: 243.40499 | AE40: 248.19198 | AF40: 5529945 | AG40: 0.4744 | AH40: 0.090317423 | AI40: 8.9243863 | AJ40: 0.23990779 | AK40: 0.57425134 | AL40: 2573.871 | AM40: 484.638 | AN40: 1.4419 | AO40: 0.0010610434 | AP40: 0.15673878 | AQ40: 0.53481883 | AR40: 0.14695004 | AS40: 2.2875817 | AT40: 6.0630435 | AU40: 0.94533979 | AV40: 0.89236469 | AW40: 86.569756 | AX40: 12.294508 | AY40: 75.615426 | AZ40: 76.48 | BA40: 30.44893 | BB40: 7.0993189 | BC40: 2.6656599 | BD40: 192.06651 | BE40: 0.6974 | BF40: 0.9725 | BG40: 0.7938 | BH40: 0.4417 | BI40: 0.0275 | BJ40: 232.90635 | BK40: 228 | BL40: 0.15661889 | BM40: 26.412205 | BN40: 22.051 | BO40: 101.057 | BP40: 16.95 | BQ40: 144.54002 | BR40: 5.9440559 | BS40: 42.394084 | BT40: 22.72029 | BU40: 31.219042 | BV40: 0.38765143 | BW40: 0.061779242 | BX40: 0.3013539 | BY40: 0.012989 | BZ40: 10.95 | CA40: 6.73 | CB40: 0.0592 | CC40: 68.830323 | CD40: 4.3729456 | CE40: 22.422699 | CF40: 9.6946338 | CG40: 0.60861936 | CH40: 22.222062 | CI40: 49.614346 | CJ40: 0.010544898 | CK40: 0.24118265 | CL40: 31.201539 | CM40: 29.476 | CN40: 34.591214 | CO40: 0.124 | CP40: 0.07 | CQ40: 2.3937908 | CR40: 0.093874149 | CS40: 213.09432 | CT40: 0.004 | CU40: 1.54 | CV40: 23.88 | CW40: 0.96613223 | CX40: 0.48306612 | CY40: 3.8645289 | CZ40: 296.11953
A41: Boyacá | B41: 2020 | C41: 113.55077 | D41: 68.072861 | E41: 76.728889 | F41: 0.2363125 | G41: 0.010924673 | H41: 43.59 | I41: 47.675 | J41: 90.99082 | K41: 0.08329369 | L41: 7.4741451 | M41: 0 | N41: 14.785809 | O41: 0.6591722 | P41: 200.18504 | Q41: 0.61412935 | R41: 0.84987168 | S41: 0.92318164 | T41: 0.43564948 | U41: 98.538834 | V41: 498.00316 | W41: 0.630598 | X41: 105.65405 | Y41: 5.5466256 | Z41: 0.54337826 | AA41: 58.268029 | AB41: 3.0929622 | AC41: 0.43492507 | AD41: 197.51383 | AE41: 194.52683 | AF41: - | AG41: - | AH41: 0.095388771 | AI41: 7.1210524 | AJ41: 0.3320431 | AK41: 0.63096509 | AL41: 5677.143 | AM41: 729.528 | AN41: 2.5238 | AO41: 0.00023965025 | AP41: 16.473274 | AQ41: 0.53781341 | AR41: 0.23245789 | AS41: 2.2875817 | AT41: 21.530435 | AU41: 0.96755762 | AV41: 1 | AW41: 89.613684 | AX41: 9.2022317 | AY41: 86.950221 | AZ41: 77.49 | BA41: 24.096275 | BB41: 7.5501384 | BC41: 2.0142036 | BD41: 127.95412 | BE41: 0.7066 | BF41: 0.9285 | BG41: 0.8925 | BH41: 0.5796 | BI41: 0.0207 | BJ41: 262.60908 | BK41: 260 | BL41: 0.68732394 | BM41: 21.214755 | BN41: 45.491 | BO41: 355.026 | BP41: 16.972 | BQ41: 151.55607 | BR41: 9.257175 | BS41: 56.644877 | BT41: 17.291372 | BU41: 11.409396 | BV41: 0.56995305 | BW41: 0.025118544 | BX41: 0.2732924 | BY41: 0.0104808 | BZ41: 8.39 | CA41: 5.16 | CB41: 0.0258 | CC41: 56.278972 | CD41: 9.3954115 | CE41: 28.444558 | CF41: 6.294019 | CG41: 0.50826737 | CH41: 50.151453 | CI41: 67.643536 | CJ41: 0.0065797786 | CK41: 0.17345715 | CL41: 30.887732 | CM41: 27.83 | CN41: 6.3662675 | CO41: 0.298 | CP41: 0.498 | CQ41: 2.518462 | CR41: 0.73116637 | CS41: 376.95689 | CT41: 0.003 | CU41: 1.07 | CV41: 17.22 | CW41: 0.8214389 | CX41: 1.6428778 | CY41: 6.5715112 | CZ41: 211.1098
A42: Caldas | B42: 2020 | C42: 131.8794 | D42: 73.765719 | E42: 81.273333 | F42: 0.31890368 | G42: 0.012940006 | H42: 47.78 | I42: 46.8 | J42: 93.857373 | K42: 0.065826071 | L42: 16.165118 | M42: 0 | N42: 10.512285 | O42: 0.54948436 | P42: 445.80882 | Q42: 0.53281943 | R42: 0.8906426 | S42: 0.89948824 | T42: n/a | U42: 99.708547 | V42: 465.05406 | W42: 0.80029131 | X42: 42.728261 | Y42: 5.4074163 | Z42: 0.8905522 | AA42: 49.038423 | AB42: 6.268712 | AC42: 0.32440199 | AD42: 317.06533 | AE42: 288.76382 | AF42: 241602 | AG42: 0.1332 | AH42: 0.12328714 | AI42: 8.7314952 | AJ42: 0.41098517 | AK42: 0.70654343 | AL42: 6579.506 | AM42: 998.882 | AN42: 3.0588 | AO42: 0.00037414637 | AP42: 4.7647224 | AQ42: 0.45891527 | AR42: 0.14363374 | AS42: 2.875817 | AT42: 8.6185185 | AU42: 0.96737973 | AV42: 0.96786241 | AW42: 93.497914 | AX42: 8.1037277 | AY42: 92.614031 | AZ42: 78.2 | BA42: 30.132271 | BB42: 8.8410416 | BC42: 4.4215337 | BD42: 206.47715 | BE42: 0.6568 | BF42: 0.8301 | BG42: 0.7781 | BH42: 0.4519 | BI42: 0.0296 | BJ42: 256.123 | BK42: 255.65906 | BL42: 0.41828669 | BM42: 22.375774 | BN42: 40.845 | BO42: 337.489 | BP42: 16.999 | BQ42: 150.78923 | BR42: 17.084363 | BS42: 66.337046 | BT42: 23.759847 | BU42: 51.750863 | BV42: 0.5646082 | BW42: 0.03531218 | BX42: 0.05482 | BY42: 0.0405993 | BZ42: 7.05 | CA42: 5.53 | CB42: 0.0627 | CC42: 57.124776 | CD42: 11.420233 | CE42: 41.198783 | CF42: 5.7023986 | CG42: 0.30521204 | CH42: 29.756326 | CI42: 69.338707 | CJ42: 0.018768509 | CK42: 0.32189267 | CL42: 30.282802 | CM42: 28.678 | CN42: 22.056445 | CO42: 0.126 | CP42: 0.363 | CQ42: 7.4379378 | CR42: 1.0908976 | CS42: 503.79632 | CT42: 0.008 | CU42: 0.92 | CV42: 22.49 | CW42: 9.0157325 | CX42: 7.0122364 | CY42: 6.0104883 | CZ42: 789.37746
A43: Caquetá | B43: 2020 | C43: 94.699524 | D43: 70.913518 | E43: 42.105714 | F43: 0.19570516 | G43: 0.015846845 | H43: 47.6 | I43: 88.37 | J43: 97.465875 | K43: 0.12252461 | L43: 45.058132 | M43: 0.2462193 | N43: 37.179115 | O43: 0.39683138 | P43: 567.98 | Q43: 0.39417476 | R43: 0.68155708 | S43: 0.90022276 | T43: 0.35298782 | U43: 90.558367 | V43: 592.80318 | W43: 0.59367835 | X43: 148.94027 | Y43: 0.67275333 | Z43: 0.54356459 | AA43: 27.950815 | AB43: 0.12760074 | AC43: 0.36442918 | AD43: 569.68126 | AE43: 415.91045 | AF43: 129321 | AG43: 0.1272 | AH43: 0.056227588 | AI43: 5.9704042 | AJ43: 0.24430547 | AK43: 0.58371176 | AL43: 2023.8 | AM43: 234.835 | AN43: 2.25 | AO43: 0.0052399242 | AP43: 39.064078 | AQ43: 0.17649581 | AR43: 0.15370235 | AS43: 4.1830065 | AT43: 19.56875 | AU43: 0.93074968 | AV43: 0.86586294 | AW43: 79.715199 | AX43: 9.5400826 | AY43: 27.880004 | AZ43: 73.35 | BA43: 14.58812 | BB43: 4.7001998 | BC43: 0.69252943 | BD43: 161.02742 | BE43: 0.5917 | BF43: 0.9089 | BG43: 0.6946 | BH43: 0.3222 | BI43: 0.055 | BJ43: 244 | BK43: 246 | BL43: 0.36436856 | BM43: 20.19491 | BN43: 25.072 | BO43: 103.024 | BP43: 3.755 | BQ43: 137.25656 | BR43: 3.9577836 | BS43: 0.57923403 | BT43: 10.126582 | BU43: 23.980978 | BV43: 0.34706398 | BW43: 0.028820961 | BX43: 0.044557 | BY43: 0.0787038 | BZ43: 4.19 | CA43: 2.94 | CB43: 0.0276 | CC43: 57.46772 | CD43: 11.003994 | CE43: 20.099939 | CF43: 10.011609 | CG43: 0.42885249 | CH43: 39.125323 | CI43: 50.000983 | CJ43: 0.0056836805 | CK43: 0.29944319 | CL43: 29.035502 | CM43: 18.893 | CN43: 0.056649609 | CO43: 0.596 | CP43: 0.596 | CQ43: 0.49243861 | CR43: 0 | CS43: 100.94991 | CT43: 0.009 | CU43: 1.4 | CV43: 15.16 | CW43: 2.4884969 | CX43: 0 | CY43: 0 | CZ43: 166.72929
A44: Casanare | B44: 2020 | C44: 119.77925 | D44: 75.583265 | E44: 73.7125 | F44: 0.17174574 | G44: 0.0064975776 | H44: 47.85 | I44: 51.36 | J44: 94.693843 | K44: 0.17021647 | L44: 14.466951 | M44: 0 | N44: 32.200633 | O44: 0.53642769 | P44: 288.78431 | Q44: 0.45500562 | R44: 0.86065757 | S44: 0.78805936 | T44: n/a | U44: 97.581804 | V44: 498.73609 | W44: 0.74504389 | X44: 117.65855 | Y44: 1.1295721 | Z44: 0.64193197 | AA44: 70.629401 | AB44: 1.0959229 | AC44: 0.76572912 | AD44: 284.6673 | AE44: 239.10489 | AF44: 313945 | AG44: 0.2536 | AH44: 0.080168084 | AI44: 7.7867614 | AJ44: 0.3459189 | AK44: 0.68286184 | AL44: 2228.75 | AM44: 154.595 | AN44: 1 | AO44: 0.00041995405 | AP44: 2.927976 | AQ44: 0.4162912 | AR44: 0.29886258 | AS44: 1.6993464 | AT44: 10.394737 | AU44: 0.9222777 | AV44: 0.88902573 | AW44: 79.321434 | AX44: 8.5470085 | AY44: 142.45014 | AZ44: 77.05 | BA44: 30.439545 | BB44: 6.903661 | BC44: 1.2538595 | BD44: 131.60259 | BE44: 0.7143 | BF44: 0.9101 | BG44: 0.7886 | BH44: 0.4409 | BI44: 0.0269 | BJ44: 256.54004 | BK44: 257 | BL44: 0.39276808 | BM44: 24.038238 | BN44: 18.518 | BO44: 46.135 | BP44: 5.658 | BQ44: 142.7206 | BR44: 1.6574586 | BS44: 10.600744 | BT44: 7.754734 | BU44: 0 | BV44: 0.59959211 | BW44: 0.031607263 | BX44: 0.0281223 | BY44: 0.3033634 | BZ44: 10.71 | CA44: 8.12 | CB44: 0.0371 | CC44: 72.370171 | CD44: 10.006644 | CE44: 38.24237 | CF44: 7.2665735 | CG44: 0.4031241 | CH44: 52.270523 | CI44: 70.003637 | CJ44: 0.0030537298 | CK44: 0.11137656 | CL44: 30.039509 | CM44: 29.252 | CN44: 28.385182 | CO44: 0.449 | CP44: 1 | CQ44: 0 | CR44: 0 | CS44: 30.33393 | CT44: 0.002 | CU44: 0.08 | CV44: 0 | CW44: 0 | CX44: 2.3780987 | CY44: 0 | CZ44: 128.41733
A45: Cauca | B45: 2020 | C45: 79.987688 | D45: 76.299137 | E45: 59.20875 | F45: 0.1433294 | G45: 0.0058823262 | H45: 47.8 | I45: 46.22 | J45: 95.568468 | K45: 0.11841672 | L45: 54.044658 | M45: 0.87932484 | N45: 28.950079 | O45: 0.52506951 | P45: 363.34848 | Q45: 0.60496381 | R45: 0.76631045 | S45: 0.68113896 | T45: 0.83493523 | U45: 96.265853 | V45: 480.38606 | W45: 0.45466039 | X45: 103.87323 | Y45: 5.1904292 | Z45: 0.5460979 | AA45: 13.808241 | AB45: 0.69654019 | AC45: 0 | AD45: 370.11807 | AE45: 293.58232 | AF45: 119624 | AG45: 0.1352 | AH45: 0.051812647 | AI45: 7.9823514 | AJ45: 0.22426921 | AK45: 0.5454322 | AL45: 3739.885 | AM45: 421.076 | AN45: 1.5556 | AO45: 0.00043182666 | AP45: 8.9653712 | AQ45: 0.2147228 | AR45: 0.10957621 | AS45: 2.0915033 | AT45: 14.414286 | AU45: 0.93641084 | AV45: 0.92935004 | AW45: 85.320434 | AX45: 13.382402 | AY45: 55.760009 | AZ45: 76.06 | BA45: 19.27642 | BB45: 5.3667226 | BC45: 1.3998933 | BD45: 115.39448 | BE45: 0.5516 | BF45: 0.8455 | BG45: 0.6621 | BH45: 0.3358 | BI45: 0.0258 | BJ45: 235.91948 | BK45: 243 | BL45: 0.34196375 | BM45: 24.14519 | BN45: 23.276 | BO45: 82.076 | BP45: 10.733 | BQ45: 144.46388 | BR45: 8.2398619 | BS45: 38.444478 | BT45: 13.199283 | BU45: 37.759148 | BV45: 0.36056087 | BW45: 0.035407725 | BX45: 0.5597757 | BY45: 0.240367 | BZ45: 3.94 | CA45: 2.24 | CB45: 0.0532 | CC45: 61.993183 | CD45: 11.36302 | CE45: 20.549603 | CF45: 13.733364 | CG45: 0.66672972 | CH45: 22.431778 | CI45: 38.601539 | CJ45: 0.0085818084 | CK45: 0.14462029 | CL45: 30.508182 | CM45: 27.283 | CN45: 9.9111429 | CO45: 0.111 | CP45: 0.227 | CQ45: 1.6233689 | CR45: 0.13528074 | CS45: 153.54365 | CT45: 0.004 | CU45: 1.55 | CV45: 20.85 | CW45: 4.096995 | CX45: 0.6828325 | CY45: 0.6828325 | CZ45: 200.75275
A46: Cesar | B46: 2020 | C46: 106.64053 | D46: 69.578485 | E46: 40.0925 | F46: 0.19769464 | G46: 0.0067106668 | H46: 47.84 | I46: 88.37 | J46: 95.842515 | K46: 0.072043937 | L46: 18.923697 | M46: 0.23954047 | N46: 11.897176 | O46: 0.51871639 | P46: 583.10989 | Q46: 0.48324873 | R46: 0.8530805 | S46: 0.88858553 | T46: 0.12190666 | U46: 95.440166 | V46: 461.21567 | W46: 0.73088433 | X46: 55.631223 | Y46: 2.915931 | Z46: 0.68971234 | AA46: 28.364785 | AB46: 1.5509277 | AC46: 0.5911215 | AD46: 295.60032 | AE46: 273.7518 | AF46: 446615 | AG46: 0.2418 | AH46: 0.074038751 | AI46: 7.6530018 | AJ46: 0.25003847 | AK46: 0.65990108 | AL46: 2927.427 | AM46: 395.428 | AN46: 1.1579 | AO46: 0.00014879789 | AP46: 0.78617288 | AQ46: 0.4051021 | AR46: 0.39575277 | AS46: 3.0718954 | AT46: 12.98 | AU46: 1 | AV46: 0.97330976 | AW46: 85.772487 | AX46: 13.448565 | AY46: 97.006041 | AZ46: 75.76 | BA46: 31.489071 | BB46: 7.4461035 | BC46: 1.4899247 | BD46: 279.78326 | BE46: 0.5881 | BF46: 0.878 | BG46: 0.7127 | BH46: 0.3994 | BI46: 0.0398 | BJ46: 244.37976 | BK46: 243 | BL46: 0.3082431 | BM46: 31.993888 | BN46: 23.115 | BO46: 91.789 | BP46: 9.641 | BQ46: 140.56353 | BR46: 5.9563758 | BS46: 1.3627734 | BT46: 10.641201 | BU46: 51.788951 | BV46: 0.35757139 | BW46: 0.015972618 | BX46: 0.0639779 | BY46: 0.0083807 | BZ46: 6.54 | CA46: 3.59 | CB46: 0.0433 | CC46: 63.924252 | CD46: 12.634144 | CE46: 20.465204 | CF46: 8.1823464 | CG46: 0.59214328 | CH46: 23.496872 | CI46: 44.859456 | CJ46: 0.0025784049 | CK46: 0.16033624 | CL46: 29.999461 | CM46: 29.904 | CN46: 50.031362 | CO46: 0.084 | CP46: 0.978 | CQ46: 0.7186214 | CR46: 0 | CS46: 71.86214 | CT46: 0.001 | CU46: 1.22 | CV46: 41.79 | CW46: 0 | CX46: 0 | CY46: 0.83293491 | CZ46: 95.787515
A47: Chocó | B47: 2020 | C47: 77.355501 | D47: 67.081743 | E47: 50.434286 | F47: 0.15405328 | G47: 0.017560155 | H47: 8.31 | I47: 48.255 | J47: 89.030192 | K47: 0.22572766 | L47: 42.042253 | M47: 0.55562449 | N47: 27.410808 | O47: 0.55587333 | P47: 226.54545 | Q47: 0.53794266 | R47: 0.35023394 | S47: 0.10309032 | T47: 0.77276995 | U47: 84.901817 | V47: 650.48549 | W47: 0.21905762 | X47: 52.152102 | Y47: 0.59944767 | Z47: 0.67873085 | AA47: 5.4771611 | AB47: 0.063556845 | AC47: 0.12278092 | AD47: 548.26486 | AE47: 489.06167 | AF47: 345882 | AG47: 0.1178 | AH47: 0.039934483 | AI47: 4.979703 | AJ47: 0.12942524 | AK47: 0.41009819 | AL47: 1226.619 | AM47: 76.787 | AN47: 1 | AO47: 0.0010349102 | AP47: 8.4916658 | AQ47: 0.08031328 | AR47: 0.14747424 | AS47: 6.6666667 | AT47: 3.6633333 | AU47: 0.95072541 | AV47: 0.85270671 | AW47: 66.046086 | AX47: 24.304194 | AY47: 156.80125 | AZ47: 71.4 | BA47: 14.055427 | BB47: 3.1530158 | BC47: 0.42258902 | BD47: 137.23925 | BE47: 0.5599 | BF47: 0.8174 | BG47: 0.5112 | BH47: 0.2321 | BI47: 0.0316 | BJ47: 209 | BK47: 216 | BL47: 0.18309859 | BM47: 26.032617 | BN47: 23.205 | BO47: 60.206 | BP47: 1.737 | BQ47: 125.31766 | BR47: 3.248731 | BS47: 1.0039083 | BT47: 3.2358432 | BU47: 0 | BV47: 0.26269841 | BW47: 0.0046480744 | BX47: 0.0514227 | BY47: 0.0338902 | BZ47: 3.43 | CA47: 2.33 | CB47: 0.0175 | CC47: 47.709675 | CD47: 11.547434 | CE47: 18.876439 | CF47: 2.684032 | CG47: 0.67299663 | CH47: 19.857204 | CI47: 28.777574 | CJ47: 0.0028603115 | CK47: 0.14134383 | CL47: 28.900509 | CM47: 26.177 | CN47: 6.0200387 | CO47: 0.459 | CP47: 0.936 | CQ47: 0.37041633 | CR47: 0 | CS47: 66.674939 | CT47: 0.003 | CU47: 1.5 | CV47: 33.33 | CW47: 0 | CX47: 0 | CY47: 0 | CZ47: 69.181379
A48: Córdoba | B48: 2020 | C48: 82.444697 | D48: 63.659973 | E48: 30.57 | F48: 0.17500966 | G48: 0.012280638 | H48: 40.75 | I48: 45.545 | J48: 92.165109 | K48: 0.083404367 | L48: 22.61619 | M48: 0.055296308 | N48: 13.437003 | O48: 0.48984797 | P48: 486.88889 | Q48: 0.57731649 | R48: 0.7432796 | S48: 0.87446859 | T48: n/a | U48: 97.942677 | V48: 434.85464 | W48: 0.37236573 | X48: 49.420462 | Y48: 3.5253717 | Z48: 0.84592624 | AA48: 11.356381 | AB48: 0.82083624 | AC48: 0 | AD48: 287.04287 | AE48: 276.56107 | AF48: 1029318 | AG48: 0.2524 | AH48: 0.055604519 | AI48: 6.157004 | AJ48: 0.17345443 | AK48: 0.47804867 | AL48: 2193.125 | AM48: 270.307 | AN48: 1.3043 | AO48: 0.00055677171 | AP48: 25.392653 | AQ48: 0.2880449 | AR48: 0.11826131 | AS48: 4.9019608 | AT48: 16.526667 | AU48: 0.90289359 | AV48: 0.8702087 | AW48: 87.146451 | AX48: 15.968596 | AY48: 95.278021 | AZ48: 76.63 | BA48: 16.541742 | BB48: 5.0055783 | BC48: 1.1322892 | BD48: 194.42182 | BE48: 0.5831 | BF48: 0.9071 | BG48: 0.7821 | BH48: 0.4356 | BI48: 0.0223 | BJ48: 237.14631 | BK48: 240 | BL48: 0.42439744 | BM48: 25.011018 | BN48: 22.763 | BO48: 65.834 | BP48: 2.805 | BQ48: 139.6503 | BR48: 8.5295657 | BS48: 72.890981 | BT48: 11.194969 | BU48: 43.458393 | BV48: 0.3094564 | BW48: 0.017821782 | BX48: 0.0834352 | BY48: 0.4388173 | BZ48: 3.87 | CA48: 2.56 | CB48: 0.0547 | CC48: 68.583674 | CD48: 11.456251 | CE48: 17.048823 | CF48: 15.111231 | CG48: 0.55333663 | CH48: 18.017314 | CI48: 32.84204 | CJ48: 0.0059955825 | CK48: 0.23685167 | CL48: 30.339435 | CM48: 28.494 | CN48: 12.390495 | CO48: 0.338 | CP48: 0.641 | CQ48: 1.2718151 | CR48: 0.055296308 | CS48: 138.79373 | CT48: 0.003 | CU48: 1.36 | CV48: 26.23 | CW48: 0.5602922 | CX48: 0.5602922 | CY48: 0 | CZ48: 84.043831
A49: Cundinamarca | B49: 2020 | C49: 144.18284 | D49: 61.706289 | E49: 84.7875 | F49: 0.5013498 | G49: 0.017547343 | H49: 60.96 | I49: 55.4 | J49: 90.713432 | K49: 0.020422388 | L49: 12.412811 | M49: 0.097228281 | N49: 10.111741 | O49: 0.48984797 | P49: 377.96795 | Q49: 0.69278403 | R49: 0.89980724 | S49: 0.70411251 | T49: 0.61940299 | U49: 99.419599 | V49: 502.35982 | W49: 0.74068375 | X49: 40.389989 | Y49: 5.2092431 | Z49: 0.88789607 | AA49: 66.425389 | AB49: 9.0556709 | AC49: 0.73542987 | AD49: 405.81059 | AE49: 327.40525 | AF49: - | AG49: - | AH49: 0.13393113 | AI49: 8.5077352 | AJ49: 0.40159293 | AK49: 0.73188396 | AL49: 3060.362 | AM49: 388.078 | AN49: 1.6129 | AO49: 0.00013032052 | AP49: 13.094701 | AQ49: 0.57465482 | AR49: 0.25298119 | AS49: 6.7633987 | AT49: 7.9818966 | AU49: 0.98367256 | AV49: 0.96565465 | AW49: 88.019504 | AX49: 9.4358563 | AY49: 77.437118 | AZ49: 78.69 | BA49: 14.097635 | BB49: 2.8845327 | BC49: 1.0893353 | BD49: 97.195872 | BE49: 0.67 | BF49: 0.9858 | BG49: 0.864 | BH49: 0.5034 | BI49: 0.0289 | BJ49: 264.56589 | BK49: 255 | BL49: 0.38465078 | BM49: 29.415754 | BN49: 16.04 | BO49: 87.014 | BP49: 14.393 | BQ49: 150.12262 | BR49: 8.6237981 | BS49: 25.010079 | BT49: 22.352592 | BU49: 21.684131 | BV49: 0.59029011 | BW49: 0.040355424 | BX49: 0.0644177 | BY49: 0.004294 | BZ49: 9.76 | CA49: 7.18 | CB49: 0.0759 | CC49: 69.444005 | CD49: 12.018106 | CE49: 40.820215 | CF49: 9.9579237 | CG49: 0.36377428 | CH49: 55.047913 | CI49: 59.07278 | CJ49: 0.0041558815 | CK49: 0.1623103 | CL49: 31.7787 | CM49: 29.536 | CN49: 27.091003 | CO49: 0.15 | CP49: 0.064 | CQ49: 1.0371017 | CR49: 0.12963771 | CS49: 97.552375 | CT49: 0.006 | CU49: 1.17 | CV49: 24.01 | CW49: 4.7960645 | CX49: 3.7683364 | CY49: 10.277281 | CZ49: 646.78355
A50: Guainía | B50: 2020 | C50: 99.162656 | D50: 74.790565 | E50: 45.51375 | F50: 0.082933061 | G50: 0.036534177 | H50: 51.16 | I50: 41.86 | J50: 100 | K50: 0.0011648224 | L50: 6.0639136 | M50: 0 | N50: 16.170436 | O50: n/a | P50: n/a | Q50: 0.6 | R50: 0.15504416 | S50: - | T50: n/a | U50: 65.588954 | V50: 817.535 | W50: 0.21133375 | X50: - | Y50: - | Z50: - | AA50: 37.587971 | AB50: 0.02706055 | AC50: 0 | AD50: NA | AE50: - | AF50: 49999 | AG50: 0.0122 | AH50: 0.017874215 | AI50: 1.1097715 | AJ50: 0.13831799 | AK50: 0.29481309 | AL50: 2086.923 | AM50: 172.315 | AN50: 2.6667 | AO50: 0.00031676615 | AP50: 15.178024 | AQ50: 0.044989444 | AR50: 0.19709339 | AS50: 1.2418301 | AT50: 0 | AU50: 1 | AV50: 1 | AW50: 30.985915 | AX50: 19.396552 | AY50: 323.27586 | AZ50: 72.4 | BA50: 28.017531 | BB50: 4.4273512 | BC50: 0.58136935 | BD50: 95.001314 | BE50: 0.464 | BF50: 0.6195 | BG50: 0.2893 | BH50: 0.0679 | BI50: 0.0714 | BJ50: 225 | BK50: 246 | BL50: 0.19072165 | BM50: 31.347938 | BN50: 2.412 | BO50: 31.176 | BP50: 6.912 | BQ50: 130.84524 | BR50: 0 | BS50: 0 | BT50: 4.1666667 | BU50: 0 | BV50: 0.45762712 | BW50: 0 | BX50: 0.2112118 | BY50: 0.0284206 | BZ50: 4.24 | CA50: 1.94 | CB50: 0.0104 | CC50: 51.662005 | CD50: 14.24531 | CE50: 31.234543 | CF50: 3.8924867 | CG50: 0.59719245 | CH50: 12.734667 | CI50: 70.940311 | CJ50: 0 | CK50: 0.061040749 | CL50: 26.619297 | CM50: 12.003 | CN50: 0.057579578 | CO50: 1 | CP50: 1 | CQ50: 0 | CR50: 0 | CS50: 20.213045 | CT50: 0.003 | CU50: 0 | CV50: 0 | CW50: 0 | CX50: 0 | CY50: 0 | CZ50: 0
A51: Guaviare | B51: 2020 | C51: 132.91686 | D51: 75.671267 | E51: 65.67875 | F51: 0.15933194 | G51: 0.032998204 | H51: 52.43 | I51: 49.36 | J51: 95.850461 | K51: 0.00038729667 | L51: 40.134095 | M51: 0 | N51: 33.051608 | O51: 0.5698686 | P51: n/a | Q51: 1 | R51: 0.45135703 | S51: 0.38298903 | T51: n/a | U51: 83.954403 | V51: 676.072 | W51: 0.42074713 | X51: 173.71658 | Y51: 0.26894875 | Z51: 0.13702848 | AA51: 0 | AB51: 0 | AC51: 0 | AD51: 362.02719 | AE51: 362.61115 | AF51: 31114 | AG51: 0.0246 | AH51: 0.029444102 | AI51: 6.757379 | AJ51: 0.24444291 | AK51: 0.5164703 | AL51: 4937.816 | AM51: 209.334 | AN51: 1.4 | AO51: 0.0064015139 | AP51: 36.641761 | AQ51: 0.1663327 | AR51: 0.17243223 | AS51: 1.8954248 | AT51: 8.425 | AU51: 1 | AV51: 0.99347353 | AW51: 62.57716 | AX51: 16.884114 | AY51: 76.745971 | AZ51: 75.46 | BA51: 24.988578 | BB51: 6.8150668 | BC51: 0.30458399 | BD51: 136.92809 | BE51: 0.4244 | BF51: 0.821 | BG51: 0.665 | BH51: 0.3114 | BI51: 0.0336 | BJ51: 237 | BK51: 237 | BL51: 0.41796875 | BM51: 29.108073 | BN51: 7.918 | BO51: 24.164 | BP51: 18.877 | BQ51: 137.8162 | BR51: 0 | BS51: 0 | BT51: 3.6764706 | BU51: 0 | BV51: 0.31666667 | BW51: 0.070886076 | BX51: 0.1950994 | BY51: 0.0403202 | BZ51: 2.48 | CA51: 3.2 | CB51: 0.0111 | CC51: 85.569336 | CD51: 12.053883 | CE51: 28.824789 | CF51: 13.288827 | CG51: 0.44469101 | CH51: 35.460993 | CI51: 57.027187 | CJ51: 0 | CK51: 0.20690452 | CL51: 27.386816 | CM51: 22.272 | CN51: 6.0393786e-06 | CO51: 0.837 | CP51: 0.836 | CQ51: 1.1804146 | CR51: 0 | CS51: 0 | CT51: 0.02 | CU51: 0 | CV51: 0 | CW51: 0 | CX51: 0 | CY51: 0 | CZ51: 12.08211
A52: Huila | B52: 2020 | C52: 113.84122 | D52: 68.986949 | E52: 57.535 | F52: 0.24366079 | G52: 0.0099786751 | H52: 39.94 | I52: 48.835 | J52: 97.665056 | K52: 0.088508876 | L52: 23.654398 | M52: 0.17988135 | N52: 17.808254 | O52: 0.34202899 | P52: 517.4186 | Q52: 0.63177454 | R52: 0.82767957 | S52: 0.91334349 | T52: 0.86102174 | U52: 98.754414 | V52: 482.78664 | W52: 0.64989598 | X52: 89.678713 | Y52: 4.9613474 | Z52: 0.77121097 | AA52: 52.759175 | AB52: 2.9492193 | AC52: 0.6714068 | AD52: 262.05191 | AE52: 215.93645 | AF52: 297393 | AG52: 0.246 | AH52: 0.095738223 | AI52: 6.2773917 | AJ52: 0.30518504 | AK52: 0.6537008 | AL52: 3910.413 | AM52: 633.732 | AN52: 1.1852 | AO52: 0.00024278618 | AP52: 22.01487 | AQ52: 0.34708006 | AR52: 0.17610775 | AS52: 3.7908497 | AT52: 11.981081 | AU52: 0.95400449 | AV52: 0.92202496 | AW52: 92.559845 | AX52: 10.065669 | AY52: 21.530843 | AZ52: 75.45 | BA52: 26.955553 | BB52: 8.5434987 | BC52: 3.3037966 | BD52: 163.69203 | BE52: 0.7097 | BF52: 0.924 | BG52: 0.8128 | BH52: 0.4475 | BI52: 0.0421 | BJ52: 256.7725 | BK52: 261 | BL52: 0.53112033 | BM52: 25.52213 | BN52: 26.378 | BO52: 79.427 | BP52: 13.307 | BQ52: 141.84482 | BR52: 4.2132982 | BS52: 40.684351 | BT52: 10.671937 | BU52: 19.487525 | BV52: 0.38275096 | BW52: 0.0093879084 | BX52: 0.0217237 | BY52: 0.0206157 | BZ52: 7.88 | CA52: 4.96 | CB52: 0.0319 | CC52: 62.824527 | CD52: 9.4005154 | CE52: 22.537445 | CF52: 10.062773 | CG52: 0.65201653 | CH52: 44.724778 | CI52: 101.30891 | CJ52: 0.012028902 | CK52: 0.31259388 | CL52: 30.31531 | CM52: 28.079 | CN52: 9.2088614 | CO52: 0.2 | CP52: 0.724 | CQ52: 1.1692288 | CR52: 0 | CS52: 117.82228 | CT52: 0.002 | CU52: 1.38 | CV52: 16.29 | CW52: 6.3614041 | CX52: 0.90877201 | CY52: 0 | CZ52: 257.18248
A53: La Guajira | B53: 2020 | C53: 76.709381 | D53: 65.232035 | E53: 53.98625 | F53: 0.12226339 | G53: 0.0057432535 | H53: 24.71 | I53: 47.095 | J53: 92.364475 | K53: 0.040539112 | L53: 24.582051 | M53: 0.64689608 | N53: 14.986426 | O53: 0.44902323 | P53: 217.84615 | Q53: 0.49372385 | R53: 0.55438784 | S53: 0.80362536 | T53: n/a | U53: 68.453627 | V53: 458.62363 | W53: 0.38246283 | X53: 42.692718 | Y53: 1.8032185 | Z53: 0.73369701 | AA53: 26.041988 | AB53: 1.1585812 | AC53: 0.19679061 | AD53: 142.33313 | AE53: 168.10701 | AF53: 258693 | AG53: 0.227 | AH53: 0.049314073 | AI53: 5.0916183 | AJ53: 0.11015511 | AK53: 0.40610938 | AL53: 1585.219 | AM53: 126.729 | AN53: 1.3636 | AO53: 0.00028213702 | AP53: 13.791321 | AQ53: 0.27407621 | AR53: 0.17060759 | AS53: 2.4183007 | AT53: 12.92 | AU53: 0.97251321 | AV53: 0.90596831 | AW53: 65.42024 | AX53: 19.506233 | AY53: 122.21951 | AZ53: 70.01 | BA53: 22.3119 | BB53: 5.9888173 | BC53: 0.61626352 | BD53: 164.31161 | BE53: 0.6637 | BF53: 0.9009 | BG53: 0.5654 | BH53: 0.2325 | BI53: 0.0277 | BJ53: 229.45375 | BK53: 232.9507 | BL53: 0.21560011 | BM53: 26.31365 | BN53: 16.73 | BO53: 18.738 | BP53: 7.119 | BQ53: 134.03579 | BR53: 6.2845304 | BS53: 2.786617 | BT53: 4.9955397 | BU53: 0 | BV53: 0.33392937 | BW53: 0.015907448 | BX53: 0.0556425 | BY53: 0.0077778 | BZ53: 2.56 | CA53: 2.09 | CB53: 0.0222 | CC53: 73.72918 | CD53: 6.2748917 | CE53: 17.810859 | CF53: 16.547056 | CG53: 0.73162228 | CH53: 16.489851 | CI53: 34.103376 | CJ53: 0.0029629191 | CK53: 0.086548764 | CL53: 28.994848 | CM53: 29.293 | CN53: 70.161032 | CO53: 0.177 | CP53: 0.991 | CQ53: 1.4016082 | CR53: 0 | CS53: 152.02058 | CT53: 0.002 | CU53: 1.43 | CV53: 13.64 | CW53: 0 | CX53: 0 | CY53: 0 | CZ53: 57.917689
A54: Magdalena | B54: 2020 | C54: 100.34918 | D54: 72.174371 | E54: 85.067778 | F54: 0.26425454 | G54: 0.014552297 | H54: 48.65 | I54: 61.96 | J54: 95.051949 | K54: 0.058553387 | L54: 19.152784 | M54: 0.072002949 | N54: 12.816525 | O54: 0.50594487 | P54: 304.15517 | Q54: 0.54465776 | R54: 0.7937076 | S54: 0.81912804 | T54: n/a | U54: 94.98991 | V54: 438.20263 | W54: 0.50282141 | X54: 48.054401 | Y54: 2.7806107 | Z54: 0.90745006 | AA54: 10.127274 | AB54: 0.60656729 | AC54: 0.74879587 | AD54: 196.59414 | AE54: 246.2748 | AF54: 2316304 | AG54: 0.2764 | AH54: 0.066701149 | AI54: 8.7382496 | AJ54: 0.24077879 | AK54: 0.56539173 | AL54: 2732.049 | AM54: 449.495 | AN54: 1.8125 | AO54: 0.00021760428 | AP54: 14.419975 | AQ54: 0.44902351 | AR54: 0.084476198 | AS54: 0.71895425 | AT54: 10.45 | AU54: 0.94002954 | AV54: 0.91412523 | AW54: 82.451618 | AX54: 12.84489 | AY54: 114.0829 | AZ54: 75.48 | BA54: 20.32759 | BB54: 5.8922127 | BC54: 1.1386744 | BD54: 203.26433 | BE54: 0.6236 | BF54: 0.917 | BG54: 0.7392 | BH54: 0.4066 | BI54: 0.0326 | BJ54: 229.55982 | BK54: 228 | BL54: 0.17241379 | BM54: 28.531008 | BN54: 20.661 | BO54: 76.468 | BP54: 7.252 | BQ54: 141.61802 | BR54: 7.7883175 | BS54: 63.50553 | BT54: 15.776224 | BU54: 55.167668 | BV54: 0.39484056 | BW54: 0.027138158 | BX54: 0.0680279 | BY54: 0.0347208 | BZ54: 7.32 | CA54: 4.37 | CB54: 0.058 | CC54: 63.183238 | CD54: 8.5170425 | CE54: 22.669975 | CF54: 10.160171 | CG54: 0.63750984 | CH54: 25.010263 | CI54: 39.454006 | CJ54: 0.0059423038 | CK54: 0.29552275 | CL54: 30.11497 | CM54: 28.463 | CN54: 23.985073 | CO54: 0.135 | CP54: 0.298 | CQ54: 2.1600885 | CR54: 0.2880118 | CS54: 172.08705 | CT54: 0.004 | CU54: 1.36 | CV54: 27.23 | CW54: 0.74529755 | CX54: 0.74529755 | CY54: 0.74529755 | CZ54: 113.28523
A55: Meta | B55: 2020 | C55: 108.80451 | D55: 74.514372 | E55: 77.167778 | F55: 0.28600068 | G55: 0.007431539 | H55: 51.6 | I55: 55.98 | J55: 97.236611 | K55: 0.08732341 | L55: 21.86052 | M55: 0 | N55: 41.439943 | O55: 0.56031483 | P55: 441.56522 | Q55: 0.60212474 | R55: 0.79842132 | S55: 0.8229992 | T55: 0.068193649 | U55: 97.409934 | V55: 497.11844 | W55: 0.79127854 | X55: 117.84208 | Y55: 1.4307585 | Z55: 0.80013597 | AA55: 4.8434359 | AB55: 0.059507211 | AC55: 0.21005122 | AD55: 328.94069 | AE55: 271.29712 | AF55: 286413 | AG55: 0.2898 | AH55: 0.11485859 | AI55: 8.3454235 | AJ55: 0.35936299 | AK55: 0.76909465 | AL55: 2079.993 | AM55: 414.277 | AN55: 1.24 | AO55: 0.0052980927 | AP55: 14.734927 | AQ55: 0.5588326 | AR55: 0.22080058 | AS55: 3.2679739 | AT55: 10.013793 | AU55: 0.9440731 | AV55: 0.9015625 | AW55: 83.06209 | AX55: 9.4415428 | AY55: 66.961296 | AZ55: 75.76 | BA55: 25.129575 | BB55: 6.2440712 | BC55: 1.6772294 | BD55: 195.50909 | BE55: 0.6524 | BF55: 0.9104 | BG55: 0.7831 | BH55: 0.4329 | BI55: 0.0447 | BJ55: 254.73524 | BK55: 254 | BL55: 0.3992674 | BM55: 30.975406 | BN55: 25.573 | BO55: 77.328 | BP55: 6.661 | BQ55: 143.46681 | BR55: 4.9056604 | BS55: 15.45029 | BT55: 11.537618 | BU55: 42.370145 | BV55: 0.53686067 | BW55: 0.036977492 | BX55: 0.010947 | BY55: 0.0504832 | BZ55: 10.97 | CA55: 7 | CB55: 0.0395 | CC55: 64.480367 | CD55: 13.336932 | CE55: 30.598723 | CF55: 8.7730261 | CG55: 0.39696197 | CH55: 49.543206 | CI55: 68.304668 | CJ55: 0.004179403 | CK55: 0.13949031 | CL55: 31.107271 | CM55: 28.697 | CN55: 8.7895696 | CO55: 0.325 | CP55: 0.963 | CQ55: 0.38018296 | CR55: 0 | CS55: 118.80718 | CT55: 0.003 | CU55: 1.47 | CV55: 7 | CW55: 2.8853867 | CX55: 1.9235911 | CY55: 0.96179556 | CZ55: 191.39732
A56: Nariño | B56: 2020 | C56: 93.264191 | D56: 71.544247 | E56: 57.18 | F56: 0.21914249 | G56: 0.015826373 | H56: 50.54 | I56: 45.64 | J56: 94.25715 | K56: 0.032227976 | L56: 35.605081 | M56: 0.24555228 | N56: 16.329227 | O56: 0.57826561 | P56: 331.52071 | Q56: 0.5504027 | R56: 0.76249138 | S56: 0.25640565 | T56: 0.12319201 | U56: 97.647431 | V56: 543.19062 | W56: 0.43500682 | X56: 57.649246 | Y56: 2.8256102 | Z56: 0.77704976 | AA56: 12.761352 | AB56: 0.62486473 | AC56: 0.68149894 | AD56: 250.49874 | AE56: 248.05031 | AF56: 326092 | AG56: 0.2372 | AH56: 0.060732544 | AI56: 7.3460591 | AJ56: 0.26298032 | AK56: 0.53005205 | AL56: 2271.115 | AM56: 332.022 | AN56: 1.36 | AO56: 0.00081572655 | AP56: 5.9298921 | AQ56: 0.11027569 | AR56: 0.35725764 | AS56: 2.6797386 | AT56: 12.245313 | AU56: 0.90128854 | AV56: 0.85658642 | AW56: 85.091518 | AX56: 10.702678 | AY56: 100.86294 | AZ56: 76.7 | BA56: 21.399125 | BB56: 6.1685874 | BC56: 1.3591069 | BD56: 154.75933 | BE56: 0.4904 | BF56: 0.8182 | BG56: 0.6966 | BH56: 0.356 | BI56: 0.0134 | BJ56: 252.10576 | BK56: 255 | BL56: 0.54721579 | BM56: 19.381991 | BN56: 23.476 | BO56: 73.47 | BP56: 3.683 | BQ56: 146.57964 | BR56: 6.8456376 | BS56: 34.601889 | BT56: 11.785029 | BU56: 27.6561 | BV56: 0.35430267 | BW56: 0.036423841 | BX56: 0.0606729 | BY56: 0.490331 | BZ56: 8.62 | CA56: 2.58 | CB56: 0.0476 | CC56: 67.262165 | CD56: 6.4971513 | CE56: 16.313045 | CF56: 8.1914084 | CG56: 0.68726981 | CH56: 25.796083 | CI56: 43.430879 | CJ56: 0.010528612 | CK56: 0.29386514 | CL56: 30.341429 | CM56: 26.757 | CN56: 5.6902532 | CO56: 0.194 | CP56: 0.244 | CQ56: 0.49110456 | CR56: 0.18416421 | CS56: 144.26196 | CT56: 0.007 | CU56: 0.66 | CV56: 19.16 | CW56: 0 | CX56: 0 | CY56: 7.9725646 | CZ56: 121.42829
A57: Norte de Santander | B57: 2020 | C57: 110.93117 | D57: 71.745998 | E57: 52.9725 | F57: 0.24830338 | G57: 0.014444794 | H57: 50.95 | I57: 59.43 | J57: 95.905705 | K57: 0.074770124 | L57: 34.43293 | M57: 1.2776597 | N57: 24.020003 | O57: 0.58573394 | P57: 530.35915 | Q57: 0.57911803 | R57: 0.85052791 | S57: 0.74600635 | T57: 0.69418561 | U57: 98.141035 | V57: 495.58653 | W57: 0.78384818 | X57: 81.432859 | Y57: 5.6086665 | Z57: 0.57994532 | AA57: 20.832791 | AB57: 1.5057189 | AC57: 0.097357428 | AD57: 193.20201 | AE57: 201.16231 | AF57: 1057441 | AG57: 0.2604 | AH57: 0.096055545 | AI57: 8.2143077 | AJ57: 0.32110199 | AK57: 0.67936757 | AL57: 5643.528 | AM57: 686.011 | AN57: 2 | AO57: 0.0032918259 | AP57: 13.778171 | AQ57: 0.32668316 | AR57: 0.38659239 | AS57: 3.6601307 | AT57: 10.0325 | AU57: 0.92698465 | AV57: 0.92873979 | AW57: 83.902439 | AX57: 11.018424 | AY57: 84.757104 | AZ57: 75.56 | BA57: 23.253725 | BB57: 4.7769415 | BC57: 1.3925143 | BD57: 129.68246 | BE57: 0.6588 | BF57: 0.9176 | BG57: 0.745 | BH57: 0.4056 | BI57: 0.0395 | BJ57: 258.12363 | BK57: 261 | BL57: 0.5274216 | BM57: 26.530975 | BN57: 40.472 | BO57: 121.473 | BP57: 10.425 | BQ57: 145.30846 | BR57: 6.7981791 | BS57: 9.5214851 | BT57: 10.641007 | BU57: 51.189427 | BV57: 0.36257982 | BW57: 0.010693215 | BX57: 0.0115219 | BY57: 0.0073139 | BZ57: 4.17 | CA57: 4.67 | CB57: 0.0427 | CC57: 58.334092 | CD57: 14.386834 | CE57: 19.175299 | CF57: 10.520983 | CG57: 0.69041786 | CH57: 31.711396 | CI57: 61.1499 | CJ57: 0.011880448 | CK57: 0.30779089 | CL57: 30.326354 | CM57: 27.93 | CN57: 7.792244 | CO57: 0.085 | CP57: 0.313 | CQ57: 1.8526066 | CR57: 0.38329792 | CS57: 240.83886 | CT57: 0.003 | CU57: 0.6 | CV57: 29.79 | CW57: 2.0111431 | CX57: 3.3519051 | CY57: 2.6815241 | CZ57: 376.08375
A58: Putumayo | B58: 2020 | C58: 91.189349 | D58: 79.979075 | E58: 47.681429 | F58: 0.11017882 | G58: 0.0084362125 | H58: 23.67 | I58: 91.03 | J58: 99.452041 | K58: 0.12615067 | L58: 47.772636 | M58: 0 | N58: 25.441049 | O58: 0.64473779 | P58: 371.20513 | Q58: 0.80461165 | R58: 0.48552531 | S58: 0.63017883 | T58: 0.82426471 | U58: 82.604396 | V58: 651.12232 | W58: 0.51493176 | X58: 147.31692 | Y58: 2.0612055 | Z58: 0.94551425 | AA58: 22.512501 | AB58: 0.32003215 | AC58: 0.40017579 | AD58: 400.14437 | AE58: 390.42375 | AF58: 30712 | AG58: 0.0072 | AH58: 0.044669167 | AI58: 4.0494439 | AJ58: 0.20190179 | AK58: 0.44458164 | AL58: 754.055 | AM58: 225.047 | AN58: 0.5385 | AO58: 0.005485669 | AP58: 19.627824 | AQ58: 0.11475563 | AR58: 0.29298458 | AS58: 5.8169935 | AT58: 6.0615385 | AU58: 0.97360587 | AV58: 0.95198541 | AW58: 81.265707 | AX58: 12.197877 | AY58: 135.53196 | AZ58: 73.97 | BA58: 21.28672 | BB58: 4.8421078 | BC58: 0.56561086 | BD58: 140.20845 | BE58: 0.4566 | BF58: 0.8071 | BG58: 0.7104 | BH58: 0.3659 | BI58: 0.0521 | BJ58: 242.76886 | BK58: 254 | BL58: 0.54941278 | BM58: 22.569751 | BN58: 3.989 | BO58: 54.856 | BP58: 8.625 | BQ58: 134.87352 | BR58: 0 | BS58: 8.9131423 | BT58: 2.2857143 | BU58: 5.7270694 | BV58: 0.37043581 | BW58: 0.0083194676 | BX58: 0.0212573 | BY58: 0.0566484 | BZ58: 7.04 | CA58: 3.53 | CB58: 0.0248 | CC58: 59.655093 | CD58: 16.899082 | CE58: 36.006233 | CF58: 6.0158862 | CG58: 0.43863563 | CH58: 16.912743 | CI58: 49.564003 | CJ58: 0.0029536027 | CK58: 0.15576744 | CL58: 27.215851 | CM58: 27.77 | CN58: 83.899027 | CO58: 0.629 | CP58: 1 | CQ58: 0 | CR58: 0 | CS58: 0 | CT58: 0.002 | CU58: 0 | CV58: 0 | CW58: 0 | CX58: 0 | CY58: 0 | CZ58: 66.057407
A59: Quindío | B59: 2020 | C59: 119.72882 | D59: 82.125734 | E59: 82.50875 | F59: 0.39579166 | G59: 0.014956024 | H59: 44.63 | I59: 47.095 | J59: 99.822784 | K59: 0.22895838 | L59: 35.228299 | M59: 0 | N59: 11.864453 | O59: 0.62928595 | P59: 512.14286 | Q59: 0.46627165 | R59: 0.96765105 | S59: 1 | T59: 0.87106836 | U59: 99.079541 | V59: 522.22403 | W59: 0.88712602 | X59: 35.932684 | Y59: 10.515014 | Z59: 0.6450704 | AA59: 43.387393 | AB59: 12.883469 | AC59: 0.42944889 | AD59: 431.47125 | AE59: 358.23588 | AF59: 443476 | AG59: 0.2514 | AH59: 0.18108219 | AI59: 8.101656 | AJ59: 0.39758348 | AK59: 0.73075957 | AL59: 5724.24 | AM59: 646.025 | AN59: 1.15 | AO59: 0.00012860898 | AP59: 27.187604 | AQ59: 0.41244992 | AR59: 0.18028675 | AS59: 2.2222222 | AT59: 14.725 | AU59: 0.99949101 | AV59: 0.96103896 | AW59: 93.175339 | AX59: 11.211959 | AY59: 35.593522 | AZ59: 75.26 | BA59: 28.371873 | BB59: 7.9053994 | BC59: 4.7896643 | BD59: 206.25896 | BE59: 0.6793 | BF59: 0.9526 | BG59: 0.8906 | BH59: 0.5466 | BI59: 0.0417 | BJ59: 259.66929 | BK59: 254 | BL59: 0.56485356 | BM59: 23.679393 | BN59: 40.933 | BO59: 101.314 | BP59: 25.811 | BQ59: 148.22676 | BR59: 6.3015312 | BS59: 50.292458 | BT59: 25.136612 | BU59: 72.329492 | BV59: 0.53127506 | BW59: 0.029547553 | BX59: 0.0394386 | BY59: 0.0616701 | BZ59: 8.31 | CA59: 5.57 | CB59: 0.0557 | CC59: 62.086643 | CD59: 15.139792 | CE59: 31.642932 | CF59: 11.327461 | CG59: 0.46613457 | CH59: 30.142112 | CI59: 76.619808 | CJ59: 0.019064611 | CK59: 0.36125868 | CL59: 29.627641 | CM59: 27.53 | CN59: 12.235942 | CO59: 0.204 | CP59: 0.85 | CQ59: 1.0951803 | CR59: 0.18253005 | CS59: 288.39748 | CT59: 0.002 | CU59: 1.57 | CV59: 25 | CW59: 12.965268 | CX59: 9.2609056 | CY59: 9.2609056 | CZ59: 559.3587
A60: Risaralda | B60: 2020 | C60: 130.25197 | D60: 74.700247 | E60: 73.806667 | F60: 0.390634 | G60: 0.0099473875 | H60: 43.66 | I60: 54.82 | J60: 92.255357 | K60: 0.2062096 | L60: 23.936731 | M60: 0 | N60: 15.74785 | O60: 0.5104228 | P60: 636.30851 | Q60: 0.65079877 | R60: 0.94042369 | S60: 0.85764122 | T60: n/a | U60: 99.675523 | V60: 493.27656 | W60: 0.8311866 | X60: 45.851022 | Y60: 10.448285 | Z60: 0.8414347 | AA60: 16.864267 | AB60: 3.8800483 | AC60: 0.20886612 | AD60: 466.63694 | AE60: 390.26548 | AF60: 1818632 | AG60: 0.2732 | AH60: 0.17866104 | AI60: 9.199618 | AJ60: 0.45144131 | AK60: 0.77874369 | AL60: 10323.646 | AM60: 1269.485 | AN60: 1.6 | AO60: 9.419847e-05 | AP60: 21.767824 | AQ60: 0.4309227 | AR60: 0.1791485 | AS60: 3.2679739 | AT60: 6.7142857 | AU60: 0.96804068 | AV60: 0.94501845 | AW60: 90.182287 | AX60: 11.252591 | AY60: 98.706939 | AZ60: 76.74 | BA60: 32.388063 | BB60: 9.6927386 | BC60: 6.3452186 | BD60: 166.40228 | BE60: 0.696 | BF60: 0.9623 | BG60: 0.8442 | BH60: 0.4919 | BI60: 0.0423 | BJ60: 259.38986 | BK60: 256 | BL60: 0.43914894 | BM60: 22.751489 | BN60: 43.548 | BO60: 221.539 | BP60: 19.579 | BQ60: 148.47722 | BR60: 7.7373974 | BS60: 48.159901 | BT60: 24.603015 | BU60: 37.854967 | BV60: 0.58110937 | BW60: 0.053558844 | BX60: 0.0247299 | BY60: 0.0395242 | BZ60: 8.52 | CA60: 7.51 | CB60: 0.0672 | CC60: 61.602161 | CD60: 7.6137981 | CE60: 37.076605 | CF60: 5.1194903 | CG60: 0.34866971 | CH60: 28.83856 | CI60: 78.910199 | CJ60: 0.022414806 | CK60: 0.41287489 | CL60: 30.413481 | CM60: 27.992 | CN60: 17.19809 | CO60: 0.112 | CP60: 0.255 | CQ60: 5.4592545 | CR60: 0.20997133 | CS60: 340.15355 | CT60: 0.004 | CU60: 1.29 | CV60: 30.19 | CW60: 14.839925 | CX60: 9.5399517 | CY60: 13.77993 | CZ60: 1061.0546
A61: Archipiélago de San Andrés | B61: 2020 | C61: 122.913 | D61: 39.860804 | E61: 71.24 | F61: 0.35424211 | G61: 0.031603754 | H61: 44.09 | I61: 55.95 | J61: 78.666169 | K61: 0.26731333 | L61: 40.011523 | M61: 2.527103 | N61: 9.6027656 | O61: 0.46253765 | P61: 254.94118 | Q61: 0.63106796 | R61: 0.50283231 | S61: - | T61: n/a | U61: 99.806392 | V61: 551.7299 | W61: 0.28434215 | X61: 74.654047 | Y61: 15.958075 | Z61: 0.89039958 | AA61: 35.80127 | AB61: 20.117746 | AC61: 0.75417646 | AD61: NA | AE61: - | AF61: 2235218 | AG61: 0.2704 | AH61: 0.067248695 | AI61: 1.6802988 | AJ61: 0.36909532 | AK61: 0.77338454 | AL61: 6169.889 | AM61: 130.35 | AN61: 0.4444 | AO61: 0 | AP61: 2.2490909 | AQ61: 0.39931111 | AR61: 0.19929796 | AS61: 3.1372549 | AT61: 9.4 | AU61: 0.89519651 | AV61: 0.92067039 | AW61: 91.176471 | AX61: 15.345269 | AY61: 127.87724 | AZ61: 74.66 | BA61: 53.684931 | BB61: 10.088334 | BC61: 2.0698197 | BD61: 185.65347 | BE61: 0.6869 | BF61: 0.9296 | BG61: 0.8423 | BH61: 0.509 | BI61: 0.0197 | BJ61: 238 | BK61: 247 | BL61: 0.45945946 | BM61: 30.510811 | BN61: 1.76 | BO61: 70.17 | BP61: 29.437 | BQ61: 133.4419 | BR61: 40.740741 | BS61: 6.863418 | BT61: 42.857143 | BU61: 86.428571 | BV61: 0.73262032 | BW61: 0 | BX61: 0.243614 | BY61: 0.022234 | BZ61: 16.48 | CA61: 15.44 | CB61: 0.0725 | CC61: 69.528396 | CD61: 7.6688047 | CE61: 60.06795 | CF61: 1.1271335 | CG61: 0.33618965 | CH61: 42.247854 | CI61: 105.73811 | CJ61: 0.0023329914 | CK61: 0.24699447 | CL61: 28.060187 | CM61: 16.788 | CN61: 0.79226686 | CO61: 0.256 | CP61: 0.256 | CQ61: 0 | CR61: 0 | CS61: 96.027656 | CT61: 0.008 | CU61: 0 | CV61: 0 | CW61: 16.318538 | CX61: 0 | CY61: 0 | CZ61: 1615.5352
A62: Santander | B62: 2020 | C62: 112.89371 | D62: 68.849706 | E62: 78.63375 | F62: 0.33949816 | G62: 0.0084349818 | H62: 35.37 | I62: 55.11 | J62: 94.428537 | K62: 0.084975319 | L62: 13.541373 | M62: 0.178764 | N62: 8.8041269 | O62: 0.50030955 | P62: 420.73968 | Q62: 0.488335 | R62: 0.82458737 | S62: 0.88457919 | T62: 0.34347626 | U62: 99.520925 | V62: 468.97608 | W62: 0.76065828 | X62: 82.266915 | Y62: 5.8859678 | Z62: 0.51864481 | AA62: 23.530713 | AB62: 1.724204 | AC62: 0.2397777 | AD62: 347.88167 | AE62: 333.42898 | AF62: 1844269 | AG62: 0.2806 | AH62: 0.1464306 | AI62: 8.8127318 | AJ62: 0.39957684 | AK62: 0.73688093 | AL62: 6341.352 | AM62: 930.326 | AN62: 2.6341 | AO62: 0.00086613046 | AP62: 26.588852 | AQ62: 0.45522196 | AR62: 0.19120655 | AS62: 3.8562092 | AT62: 12.726437 | AU62: 0.90270057 | AV62: 0.88250821 | AW62: 90.338365 | AX62: 7.9056865 | AY62: 79.750347 | AZ62: 78.37 | BA62: 42.163179 | BB62: 8.8280217 | BC62: 4.2538659 | BD62: 194.31647 | BE62: 0.6751 | BF62: 0.9488 | BG62: 0.8383 | BH62: 0.4963 | BI62: 0.032 | BJ62: 270.72616 | BK62: 268 | BL62: 0.52565125 | BM62: 21.668793 | BN62: 37.859 | BO62: 403.188 | BP62: 21.935 | BQ62: 151.8345 | BR62: 7.3492083 | BS62: 36.703556 | BT62: 26.741064 | BU62: 53.906156 | BV62: 0.54772505 | BW62: 0.036775571 | BX62: 0.0123496 | BY62: 0.0040818 | BZ62: 8.84 | CA62: 8.33 | CB62: 0.0547 | CC62: 65.139508 | CD62: 11.314391 | CE62: 31.918918 | CF62: 9.583369 | CG62: 0.44894348 | CH62: 46.000133 | CI62: 84.772025 | CJ62: 0.012631575 | CK62: 0.25794908 | CL62: 31.770853 | CM62: 28.751 | CN62: 6.8117441 | CO62: 0.131 | CP62: 0.341 | CQ62: 3.843426 | CR62: 0.357528 | CS62: 387.91788 | CT62: 0.005 | CU62: 1.3 | CV62: 22.6 | CW62: 7.7809008 | CX62: 5.0347005 | CY62: 8.2386009 | CZ62: 657.71497
A63: Sucre | B63: 2020 | C63: 92.030256 | D63: 76.325314 | E63: 43.035 | F63: 0.19270852 | G63: 0.012230847 | H63: 44.9 | I63: 44.185 | J63: 98.13895 | K63: 0.13624799 | L63: 17.761339 | M63: 0.10764448 | N63: 9.1497808 | O63: 0.49614327 | P63: 379.35227 | Q63: 0.54227213 | R63: 0.85833787 | S63: 0.90190236 | T63: n/a | U63: 97.644088 | V63: 443.98725 | W63: 0.59222139 | X63: 49.927779 | Y63: 4.1382981 | Z63: 0.866141 | AA63: 9.6245992 | AB63: 0.81900693 | AC63: 0 | AD63: 337.16083 | AE63: 336.84541 | AF63: 87341 | AG63: 0.1252 | AH63: 0.059285218 | AI63: 6.275218 | AJ63: 0.19657754 | AK63: 0.48424301 | AL63: 1567.517 | AM63: 317.425 | AN63: 1.1905 | AO63: 7.8780865e-05 | AP63: 1.4964908 | AQ63: 0.32677461 | AR63: 0.099338691 | AS63: 1.9607843 | AT63: 12.003846 | AU63: 1 | AV63: 1 | AW63: 84.321036 | AX63: 9.9752249 | AY63: 84.756813 | AZ63: 76.24 | BA63: 19.487188 | BB63: 5.2302435 | BC63: 1.6526156 | BD63: 236.27963 | BE63: 0.7216 | BF63: 0.9533 | BG63: 0.7531 | BH63: 0.4167 | BI63: 0.0278 | BJ63: 237 | BK63: 241 | BL63: 0.30703314 | BM63: 25.270655 | BN63: 24.507 | BO63: 25.639 | BP63: 4.294 | BQ63: 139.77895 | BR63: 5.1899907 | BS63: 5.2638239 | BT63: 9.7603334 | BU63: 45.9375 | BV63: 0.29482072 | BW63: 0.0075244545 | BX63: 0.019493 | BY63: 0.0500241 | BZ63: 3.88 | CA63: 2.8 | CB63: 0.0434 | CC63: 67.130118 | CD63: 10.956025 | CE63: 15.730002 | CF63: 11.089655 | CG63: 0.65902894 | CH63: 21.259576 | CI63: 33.238828 | CJ63: 0.0048689883 | CK63: 0.21203271 | CL63: 29.037253 | CM63: 29.102 | CN63: 50.55405 | CO63: 0.27 | CP63: 0.994 | CQ63: 1.2917338 | CR63: 0 | CS63: 177.61339 | CT63: 0.001 | CU63: 0.87 | CV63: 16.67 | CW63: 1.1051397 | CX63: 0 | CY63: 0 | CZ63: 79.570056
A64: Tolima | B64: 2020 | C64: 122.21172 | D64: 67.077971 | E64: 59.125 | F64: 0.25456572 | G64: 0.010121556 | H64: 34.57 | I64: 92.31 | J64: 93.558366 | K64: 0.15838056 | L64: 19.995312 | M64: 0.074888809 | N64: 19.545979 | O64: 0.4917594 | P64: 349.43814 | Q64: 0.78947368 | R64: 0.8549436 | S64: 0.76835453 | T64: 0.08304844 | U64: 98.306345 | V64: 510.62818 | W64: 0.71978111 | X64: 73.134228 | Y64: 4.1287751 | Z64: 0.89798673 | AA64: 61.300983 | AB64: 3.4740684 | AC64: 0.30228694 | AD64: 334.47409 | AE64: 313.24411 | AF64: 139838 | AG64: 0.2378 | AH64: 0.11575816 | AI64: 7.6555649 | AJ64: 0.32645871 | AK64: 0.67995856 | AL64: 4721.137 | AM64: 1152.753 | AN64: 2 | AO64: 0.00011074535 | AP64: 11.219591 | AQ64: 0.35568864 | AR64: 0.22603581 | AS64: 3.3986928 | AT64: 4.5021277 | AU64: 0.99089968 | AV64: 0.94897736 | AW64: 89.626728 | AX64: 9.2738408 | AY64: 69.991251 | AZ64: 76.64 | BA64: 24.922109 | BB64: 5.8013047 | BC64: 2.0440966 | BD64: 153.74672 | BE64: 0.7209 | BF64: 0.982 | BG64: 0.8351 | BH64: 0.4672 | BI64: 0.0302 | BJ64: 246.71335 | BK64: 247.97215 | BL64: 0.4917339 | BM64: 23.447957 | BN64: 24.115 | BO64: 106.226 | BP64: 19.11 | BQ64: 143.13153 | BR64: 7.892204 | BS64: 41.677307 | BT64: 13.292761 | BU64: 50.314527 | BV64: 0.41275225 | BW64: 0.0097765363 | BX64: 0.0193086 | BY64: 0.0520908 | BZ64: 7.32 | CA64: 4.66 | CB64: 0.0354 | CC64: 61.202997 | CD64: 17.1226 | CE64: 25.273369 | CF64: 13.549465 | CG64: 0.40883642 | CH64: 43.207043 | CI64: 73.920137 | CJ64: 0.0090702121 | CK64: 0.31407137 | CL64: 30.665354 | CM64: 26.395 | CN64: 1.8964766 | CO64: 0.261 | CP64: 0.37 | CQ64: 1.0484433 | CR64: 0 | CS64: 167.75093 | CT64: 0.002 | CU64: 1.53 | CV64: 24.9 | CW64: 3.75887 | CX64: 2.255322 | CY64: 6.014192 | CZ64: 360.85152
A65: Valle del Cauca | B65: 2020 | C65: 164.37937 | D65: 74.622173 | E65: 68.97 | F65: 0.43768872 | G65: 0.0099175058 | H65: 60.52 | I65: 87.21 | J65: 98.214253 | K65: 0.2937399 | L65: 50.390879 | M65: 0.3550216 | N65: 23.875203 | O65: 0.53507529 | P65: 482.69524 | Q65: 0.47581296 | R65: 0.95725696 | S65: 0.78748994 | T65: 0.048502174 | U65: 99.272399 | V65: 452.9909 | W65: 0.89236648 | X65: 29.258967 | Y65: 5.9150768 | Z65: 0.76599184 | AA65: 21.617012 | AB65: 4.4003098 | AC65: 0.49216745 | AD65: 342.95618 | AE65: 313.30147 | AF65: 5294580 | AG65: 0.4004 | AH65: 0.16756168 | AI65: 9.1483404 | AJ65: 0.47339746 | AK65: 0.80063697 | AL65: 4343.63 | AM65: 648.206 | AN65: 2.0308 | AO65: 0.00014668495 | AP65: 23.141933 | AQ65: 0.51872707 | AR65: 0.20620332 | AS65: 5.751634 | AT65: 18.564286 | AU65: 0.989443 | AV65: 0.99263613 | AW65: 90.864896 | AX65: 10.044938 | AY65: 52.868094 | AZ65: 75.64 | BA65: 38.91637 | BB65: 8.8982639 | BC65: 4.39454 | BD65: 171.29792 | BE65: 0.5398 | BF65: 0.7619 | BG65: 0.7145 | BH65: 0.402 | BI65: 0.0326 | BJ65: 256.30779 | BK65: 250 | BL65: 0.33379477 | BM65: 27.337256 | BN65: 30.197 | BO65: 146.295 | BP65: 14.901 | BQ65: 149.83099 | BR65: 11.083951 | BS65: 43.223657 | BT65: 26.562585 | BU65: 44.192237 | BV65: 0.58476821 | BW65: 0.056931998 | BX65: 0.011935 | BY65: 0.0069854 | BZ65: 10.95 | CA65: 9.23 | CB65: 0.0665 | CC65: 65.284621 | CD65: 12.55947 | CE65: 35.58521 | CF65: 11.597387 | CG65: 0.40029166 | CH65: 42.01929 | CI65: 78.314218 | CJ65: 0.022322952 | CK65: 0.42469588 | CL65: 32.24992 | CM65: 29.449 | CN65: 17.289159 | CO65: 0.11 | CP65: 0.026 | CQ65: 3.7499157 | CR65: 0.37721045 | CS65: 292.00527 | CT65: 0.007 | CU65: 1.37 | CV65: 22.98 | CW65: 10.277295 | CX65: 5.8089058 | CY65: 6.926003 | CZ65: 1193.5067
A66: Vaupés | B66: 2020 | C66: 93.336924 | D66: 59.515174 | E66: 42.608571 | F66: 0.070548466 | G66: 0.034447973 | H66: 62.69 | I66: 93.02 | J66: 96.940973 | K66: 0.0012357121 | L66: 9.3630767 | M66: 2.3407692 | N66: 2.3407692 | O66: n/a | P66: n/a | Q66: 0 | R66: 0.40757993 | S66: - | T66: n/a | U66: 58.050665 | V66: 655.68848 | W66: 0.35686799 | X66: - | Y66: - | Z66: - | AA66: 59.249549 | AB66: 0.046757181 | AC66: 0 | AD66: NA | AE66: - | AF66: 30736 | AG66: 0.0304 | AH66: 0.0015442312 | AI66: 2.2445703 | AJ66: 0.11855972 | AK66: 0.19856341 | AL66: 0 | AM66: 0 | AN66: 0 | AO66: 0.00019716295 | AP66: 10.615297 | AQ66: 0.36806949 | AR66: 0.067727527 | AS66: 1.2418301 | AT66: 6.4333333 | AU66: 0.83972125 | AV66: 0.77415459 | AW66: 33.841463 | AX66: 16.200295 | AY66: 147.27541 | AZ66: 64.15 | BA66: 13.139892 | BB66: 1.7812427 | BC66: 0.41304179 | BD66: 63.200768 | BE66: 0.2282 | BF66: 0.5112 | BG66: 0.3054 | BH66: 0.1135 | BI66: 0.0388 | BJ66: 212 | BK66: 223 | BL66: 0.17647059 | BM66: 27.017647 | BN66: 0.86 | BO66: 2.451 | BP66: 2.976 | BQ66: 129.19384 | BR66: 0 | BS66: 15.853659 | BT66: 0 | BU66: 0 | BV66: 0.375 | BW66: 0.011695906 | BX66: 0.56299069 | BY66: 0.0581058 | BZ66: 2.57 | CA66: 1.15 | CB66: 0 | CC66: 55.383409 | CD66: 11.282959 | CE66: 44.083506 | CF66: 4.6790466 | CG66: 0.49174733 | CH66: 13.816735 | CI66: 27.987178 | CJ66: 0.0095719526 | CK66: 0.024498648 | CL66: 26.362841 | CM66: 17.731 | CN66: 0.021753722 | CO66: 0.208 | CP66: 0.179 | CQ66: 0 | CR66: 0 | CS66: 0 | CT66: 0.02036 | CU66: 0 | CV66: 0 | CW66: 0 | CX66: 0 | CY66: 0 | CZ66: 24.511606
A67: Vichada | B67: 2020 | C67: 87.137365 | D67: 62.27916 | E67: 36.301429 | F67: 0.082692995 | G67: 0.020194992 | H67: 57.27 | I67: 51.28 | J67: 95.321603 | K67: 0.0042305658 | L67: 18.083346 | M67: 0 | N67: 19.891681 | O67: n/a | P67: n/a | Q67: 0.57142857 | R67: 0.63267664 | S67: - | T67: n/a | U67: 69.074038 | V67: 549.73582 | W67: 0.053125071 | X67: 89.176128 | Y67: 0.095906905 | Z67: 0.75862069 | AA67: 33.45419 | AB67: 0.036910676 | AC67: 1 | AD67: NA | AE67: - | AF67: 47919 | AG67: 0.013 | AH67: 0.0086821015 | AI67: 1.1479289 | AJ67: 0.067020843 | AK67: 0.1801922 | AL67: 494.176 | AM67: 52.947 | AN67: 1.25 | AO67: 0.00065471962 | AP67: 5.7130037 | AQ67: 0.37234277 | AR67: 0.1019933 | AS67: 0 | AT67: 8.925 | AU67: 0.95883905 | AV67: 0.69147203 | AW67: 33.846154 | AX67: 25.019547 | AY67: 335.36437 | AZ67: 65.69 | BA67: 25.997682 | BB67: 3.4384345 | BC67: 0.43832734 | BD67: 69.620883 | BE67: 0.3074 | BF67: 0.5668 | BG67: 0.2406 | BH67: 0.0936 | BI67: 0.0714 | BJ67: 225 | BK67: 237 | BL67: 0.23913043 | BM67: 31.807453 | BN67: 0.882 | BO67: 40.813 | BP67: 4.289 | BQ67: 130.16685 | BR67: 0 | BS67: 0 | BT67: 3.2258065 | BU67: 0 | BV67: 0.47810219 | BW67: 0.026315789 | BX67: 0.1869422 | BY67: 0.0385288 | BZ67: 3.62 | CA67: 1.42 | CB67: 0.0318 | CC67: 71.104687 | CD67: 18.879504 | CE67: 28.897689 | CF67: 13.779771 | CG67: 0.46738299 | CH67: 15.579257 | CI67: 26.046464 | CJ67: 0.0040754959 | CK67: 0.10277602 | CL67: 27.179794 | CM67: 19.45 | CN67: 0.30781109 | CO67: 1 | CP67: 1 | CQ67: 0 | CR67: 0 | CS67: 9.0416731 | CT67: 0.019 | CU67: 0 | CV67: 0 | CW67: 0 | CX67: 0 | CY67: 0 | CZ67: 0
A68: Amazonas | B68: 2021 | C68: 94.551979 | D68: 76.954873 | E68: 33.241429 | F68: 0.082517313 | G68: 0.020947293 | H68: 37.19 | I68: 45.35 | J68: 94.404236 | K68: 0 | L68: 9.9413461 | M68: 0 | N68: 6.2133413 | O68: n/a | P68: n/a | Q68: 0 | R68: 0.34188321 | S68: - | T68: n/a | U68: 84.71246 | V68: 616.71496 | W68: 0.20157031 | X68: 25.812509 | Y68: 0.01830119 | Z68: 0.33333333 | AA68: 11.743215 | AB68: 0.0086171522 | AC68: 0.28042328 | AD68: NA | AE68: - | AF68: 102831 | AG68: 0.1334 | AH68: 0.017123288 | AI68: 2.0736777 | AJ68: 0.10872453 | AK68: 0.30864158 | AL68: 451.947 | AM68: 39.878 | AN68: 0.6364 | AO68: 0.00010386176 | AP68: 20.598744 | AQ68: 0.36463366 | AR68: 0.17841879 | AS68: 3.1427324 | AT68: 9.15 | AU68: 0.92625899 | AV68: 0.91061453 | AW68: 56.05 | AX68: 16.115352 | AY68: 169.63528 | AZ68: 72.46 | BA68: 38.240307 | BB68: 7.2832339 | BC68: 1.1717086 | BD68: 200.06959 | BE68: 0.5319 | BF68: 0.789 | BG68: 0.6064 | BH68: 0.2973 | BI68: 0.0417 | BJ68: 224 | BK68: 230 | BL68: 0.18577075 | BM68: 28.387352 | BN68: 4.785 | BO68: 66.878 | BP68: 5.57 | BQ68: 134.34188 | BR68: 52.631579 | BS68: 7.0695553 | BT68: 10.25641 | BU68: 0 | BV68: 0.35555556 | BW68: 0.026490066 | BX68: 0.1582474 | BY68: 0.0180783 | BZ68: 4.43 | CA68: 3.3915464 | CB68: 0.037313433 | CC68: 53.016056 | CD68: 11.150418 | CE68: 35.132534 | CF68: 2.7984735 | CG68: 0.62157859 | CH68: 21.566402 | CI68: 47.307605 | CJ68: 0.0022203777 | CK68: 0.25526299 | CL68: 27.414578 | CM68: 0 | CN68: 8.8079976e-05 | CO68: 1 | CP68: 1 | CQ68: 4.970673 | CR68: 0 | CS68: 260.96033 | CT68: 0.009 | CU68: 0.33 | CV68: 42.87 | CW68: 0 | CX68: 0 | CY68: 0 | CZ68: 244.36356
A69: Antioquia | B69: 2021 | C69: 143.55973 | D69: 69.434146 | E69: 83.688889 | F69: 0.45138833 | G69: 0.0088160982 | H69: 55.71 | I69: 67.65 | J69: 95.935148 | K69: 0.021478217 | L69: 31.130624 | M69: 0.39101266 | N69: 20.633438 | O69: 0.61326655 | P69: 589.83448 | Q69: 0.5818155 | R69: 0.91305821 | S69: 0.65265007 | T69: 0.25839725 | U69: 99.770068 | V69: 506.43712 | W69: 0.83634358 | X69: 26.657482 | Y69: 2.7449538 | Z69: 0.83579035 | AA69: 31.577942 | AB69: 3.3008615 | AC69: 0.82367803 | AD69: 445.28507 | AE69: 429.07875 | AF69: 3353270 | AG69: 0.5638 | AH69: 0.18819286 | AI69: 15.802929 | AJ69: 0.42085284 | AK69: 0.71721344 | AL69: 5769.414 | AM69: 724.773 | AN69: 2.3902 | AO69: 0.0018237125 | AP69: 12.247752 | AQ69: 0.49262229 | AR69: 0.15978432 | AS69: 4.7140986 | AT69: 7.688 | AU69: 0.95114787 | AV69: 0.95106277 | AW69: 90.23 | AX69: 8.7492298 | AY69: 61.614295 | AZ69: 76.23 | BA69: 34.515868 | BB69: 8.7473993 | BC69: 6.1117928 | BD69: 180.03125 | BE69: 0.6786 | BF69: 0.9024 | BG69: 0.826 | BH69: 0.4504 | BI69: 0.0402 | BJ69: 252.58375 | BK69: 251 | BL69: 0.4164725 | BM69: 29.244378 | BN69: 36.948 | BO69: 217.886 | BP69: 19.494 | BQ69: 149.8897 | BR69: 11.995516 | BS69: 37.448873 | BT69: 32.905338 | BU69: 64.34741 | BV69: 0.60560316 | BW69: 0.036311914 | BX69: 0.0064338 | BY69: 0.0269354 | BZ69: 12.78 | CA69: 10.684299 | CB69: 0.079160184 | CC69: 59.2298 | CD69: 17.886663 | CE69: 45.0037 | CF69: 9.3625911 | CG69: 0.3214302 | CH69: 38.1215 | CI69: 93.160992 | CJ69: 0.032446764 | CK69: 0.5961055 | CL69: 32.719083 | CM69: 30.681 | CN69: 25.689798 | CO69: 0.135 | CP69: 0.201 | CQ69: 4.977892 | CR69: 0.66171374 | CS69: 438.98691 | CT69: 0.01 | CU69: 0.99 | CV69: 21.61 | CW69: 24.426713 | CX69: 7.0226799 | CY69: 31.134937 | CZ69: 2162.5274
A70: Arauca | B70: 2021 | C70: 99.315437 | D70: 74.552247 | E70: 30.83625 | F70: 0.10305101 | G70: 0.010525537 | H70: 44.83 | I70: 84.62 | J70: 94.906511 | K70: 0.060117411 | L70: 33.304492 | M70: 1.4360043 | N70: 36.3946 | O70: 0.50829914 | P70: 312.5 | Q70: 0.73160173 | R70: 0.72656346 | S70: 0.094828709 | T70: n/a | U70: 97.950245 | V70: 659.39291 | W70: 0.59364776 | X70: 157.66362 | Y70: 1.8541859 | Z70: 0.13262501 | AA70: 56.974716 | AB70: 0.69669997 | AC70: 0.15698445 | AD70: 347.14688 | AE70: 325.44255 | AF70: 42157 | AG70: 0.0144 | AH70: 0.051858384 | AI70: 8.1552153 | AJ70: 0.16453447 | AK70: 0.60897068 | AL70: 369.825 | AM70: 196.234 | AN70: 0.2857 | AO70: 0.001449324 | AP70: 20.473947 | AQ70: 0.14440526 | AR70: 0.35308546 | AS70: 0.13094718 | AT70: 9.7142857 | AU70: 1 | AV70: 1 | AW70: 76.75 | AX70: 11.957484 | AY70: 66.430469 | AZ70: 75.68 | BA70: 31.257235 | BB70: 6.7464531 | BC70: 1.2095712 | BD70: 144.89171 | BE70: 0.5817 | BF70: 0.9177 | BG70: 0.7322 | BH70: 0.3731 | BI70: 0.0402 | BJ70: 248.89507 | BK70: 252 | BL70: 0.53892944 | BM70: 27.845499 | BN70: 6.287 | BO70: 13.923 | BP70: 2.774 | BQ70: 134.23172 | BR70: 54.545455 | BS70: 0.81665986 | BT70: 6.557377 | BU70: 63.030303 | BV70: 0.39962121 | BW70: 0.031512605 | BX70: 0.0814861 | BY70: 0.50010912 | BZ70: 8.74 | CA70: 4.2691176 | CB70: 0.02388535 | CC70: 52.046907 | CD70: 37.695513 | CE70: 23.679688 | CF70: 15.929808 | CG70: 0.48012484 | CH70: 49.436229 | CI70: 47.442869 | CJ70: 0.00024541221 | CK70: 0.12678812 | CL70: 29.318955 | CM70: 26.799 | CN70: 4.5563346 | CO70: 0.532 | CP70: 0.99 | CQ70: 0 | CR70: 0 | CS70: 17.167264 | CT70: 0.001 | CU70: 0 | CV70: 0 | CW70: 0 | CX70: 0 | CY70: 0 | CZ70: 85.680931
A71: Atlántico | B71: 2021 | C71: 135.76416 | D71: 79.594878 | E71: 74.765 | F71: 0.51958932 | G71: 0.010549285 | H71: 68.16 | I71: 75.58 | J71: 96.298918 | K71: 0.18191705 | L71: 20.121285 | M71: 0.18562071 | N71: 7.0535868 | O71: 0.48201675 | P71: 549.61579 | Q71: 0.46138614 | R71: 0.97805316 | S71: 0.87984783 | T71: n/a | U71: 99.658033 | V71: 477.34913 | W71: 0.8466629 | X71: 13.621699 | Y71: 10.606877 | Z71: 0.99162293 | AA71: 14.939497 | AB71: 11.877804 | AC71: 0.78246608 | AD71: 323.57246 | AE71: 326.08958 | AF71: 963544 | AG71: 0.3174 | AH71: 0.13444075 | AI71: 20.770104 | AJ71: 0.42942046 | AK71: 0.76209119 | AL71: 5248.848 | AM71: 793.138 | AN71: 2.0976 | AO71: 5.3128689e-05 | AP71: 1.8087886 | AQ71: 0.6812873 | AR71: 0.10017383 | AS71: 2.7498909 | AT71: 19.6 | AU71: 0.98804111 | AV71: 0.98447954 | AW71: 84.34 | AX71: 15.120243 | AY71: 104.35751 | AZ71: 77.57 | BA71: 43.601821 | BB71: 9.7843608 | BC71: 3.5488159 | BD71: 261.46533 | BE71: 0.6269 | BF71: 0.8936 | BG71: 0.7694 | BH71: 0.4895 | BI71: 0.0126 | BJ71: 248.4899 | BK71: 241 | BL71: 0.54314721 | BM71: 32.006526 | BN71: 38.762 | BO71: 190.361 | BP71: 14.829 | BQ71: 143.82837 | BR71: 12.004245 | BS71: 55.438505 | BT71: 31.198415 | BU71: 70.363951 | BV71: 0.4670724 | BW71: 0.014423077 | BX71: 0.0250715 | BY71: 0.0672318 | BZ71: 16 | CA71: 10.44 | CB71: 0.064169805 | CC71: 58.578789 | CD71: 10.735426 | CE71: 28.705435 | CF71: 13.722748 | CG71: 0.5471997 | CH71: 35.869075 | CI71: 70.593617 | CJ71: 0.024306631 | CK71: 0.61056578 | CL71: 31.547823 | CM71: 29.132 | CN71: 26.79826 | CO71: 0.124 | CP71: 0.055 | CQ71: 4.7890142 | CR71: 0.92810353 | CS71: 480.38639 | CT71: 0.004 | CU71: 1.09 | CV71: 21.06 | CW71: 13.266868 | CX71: 2.6533735 | CY71: 2.6533735 | CZ71: 855.90249
A72: Bogotá, D.C. | B72: 2021 | C72: 161.39709 | D72: 79.6 | E72: 91.9025 | F72: 0.50352826 | G72: 0.034694197 | H72: 66.45 | I72: 48.215 | J72: 98.6 | K72: 0.31486151 | L72: 13.605511 | M72: 0.2586599 | N72: 19.709884 | O72: 0.55725439 | P72: 728.0397 | Q72: 0.44639896 | R72: 0.99905674 | S72: 0.96349274 | T72: n/a | U72: 99.996899 | V72: 524.93746 | W72: 0.99705731 | X72: - | Y72: - | Z72: - | AA72: - | AB72: - | AC72: - | AD72: 533.718 | AE72: 402.65837 | AF72: 8545032 | AG72: 1 | AH72: 0.25246182 | AI72: 25.772077 | AJ72: 0.63750727 | AK72: 0.87104408 | AL72: 9825.395 | AM72: 1638.182 | AN72: 2.814 | AO72: 0 | AP72: 32.129723 | AQ72: 0.56048938 | AR72: 0.12211519 | AS72: 2.1824531 | AT72: 4.1 | AU72: 0.92568644 | AV72: 0.89323048 | AW72: 85.36 | AX72: 9.5797825 | AY72: 48.192771 | AZ72: 79.6 | BA72: 57.264453 | BB72: 14.505586 | BC72: 7.0441761 | BD72: 185.36862 | BE72: 0.6911 | BF72: 0.9622 | BG72: 0.8752 | BH72: 0.5549 | BI72: 0.016 | BJ72: 272.38782 | BK72: 257 | BL72: 0.39982475 | BM72: 41.065782 | BN72: 82.39 | BO72: 426.04384 | BP72: 28.895 | BQ72: 152.57052 | BR72: 8.8106305 | BS72: 34.39278 | BT72: 38.23509 | BU72: 36.260435 | BV72: 0.65643911 | BW72: 0.077423018 | BX72: 0.0052625 | BY72: 0.0067017 | BZ72: 23.48 | CA72: 15.5712 | CB72: 0.075613823 | CC72: 67.301903 | CD72: 18.962479 | CE72: 48.395877 | CF72: 10.806866 | CG72: 0.34273043 | CH72: 81.495309 | CI72: 120.28446 | CJ72: 0.036143615 | CK72: 0.70283626 | CL72: 33.508812 | CM72: 29.779 | CN72: 36.238555 | CO72: 0.168 | CP72: 0.029 | CQ72: 7.5140701 | CR72: 1.095918 | CS72: 694.88982 | CT72: 0.015 | CU72: 1.72 | CV72: 19.85 | CW72: 36.218184 | CX72: 12.758129 | CY72: 30.950085 | CZ72: 2218.9446
A73: Bolívar | B73: 2021 | C73: 111.78606 | D73: 71.624394 | E73: 52.02 | F73: 0.28114993 | G73: 0.008369483 | H73: 46.27 | I73: 97.67 | J73: 95.231565 | K73: 0.18785311 | L73: 20.467489 | M73: 0.13829384 | N73: 10.003255 | O73: 0.53963461 | P73: 429.93889 | Q73: 0.47871116 | R73: 0.81329463 | S73: 0.92576902 | T73: 0.62865737 | U73: 98.324821 | V73: 482.9994 | W73: 0.4525401 | X73: 28.653488 | Y73: 2.3499346 | Z73: 0.83856842 | AA73: 3.5380174 | AB73: 0.2954423 | AC73: 0.42996743 | AD73: 304.85847 | AE73: 304.81534 | AF73: 1814492 | AG73: 0.4678 | AH73: 0.087203452 | AI73: 21.393904 | AJ73: 0.23990779 | AK73: 0.57425134 | AL73: 2473.778 | AM73: 427.984 | AN73: 1.4524 | AO73: 0.001183309 | AP73: 0.2361781 | AQ73: 0.55817392 | AR73: 0.11748978 | AS73: 4.3212571 | AT73: 4.5478261 | AU73: 0.90150006 | AV73: 0.87301791 | AW73: 85.94 | AX73: 12.786062 | AY73: 76.775432 | AZ73: 76.56 | BA73: 31.352191 | BB73: 7.471591 | BC73: 2.7400746 | BD73: 171.25387 | BE73: 0.6767 | BF73: 0.9781 | BG73: 0.8064 | BH73: 0.4543 | BI73: 0.0299 | BJ73: 232.90635 | BK73: 228 | BL73: 0.18738739 | BM73: 26.804028 | BN73: 22.151 | BO73: 106.735 | BP73: 14.939 | BQ73: 139.72154 | BR73: 6.9120763 | BS73: 42.225837 | BT73: 23.508772 | BU73: 46.36472 | BV73: 0.37079386 | BW73: 0.061779242 | BX73: 0.3013539 | BY73: 0.012989 | BZ73: 10.3 | CA73: 6.43 | CB73: 0.062321734 | CC73: 65.659352 | CD73: 9.3635397 | CE73: 20.337804 | CF73: 10.892302 | CG73: 0.63923671 | CH73: 29.643159 | CI73: 50.385487 | CJ73: 0.01019422 | CK73: 0.24524415 | CL73: 31.281948 | CM73: 29.376 | CN73: 33.452166 | CO73: 0.113 | CP73: 0.069 | CQ73: 2.3509953 | CR73: 0.092195894 | CS73: 209.28468 | CT73: 0.004 | CU73: 1.16 | CV73: 29.32 | CW73: 1.4081122 | CX73: 0.46937074 | CY73: 4.2243367 | CZ73: 333.25323
A74: Boyacá | B74: 2021 | C74: 113.55077 | D74: 68.072861 | E74: 76.728889 | F74: 0.2441342 | G74: 0.01160564 | H74: 46.51 | I74: 47.675 | J74: 90.99082 | K74: 0.08329369 | L74: 6.2833605 | M74: 0 | N74: 17.577502 | O74: 0.53927554 | P74: 197.37692 | Q74: 0.61246986 | R74: 0.85392296 | S74: 0.94967327 | T74: 0.46973063 | U74: 98.363818 | V74: 537.65122 | W74: 0.61727127 | X74: 103.86868 | Y74: 5.5135193 | Z74: 0.50047735 | AA74: 55.566302 | AB74: 3.0127604 | AC74: 0.44478543 | AD74: 203.90762 | AE74: 174.56448 | AF74: - | AG74: - | AH74: 0.094522751 | AI74: 11.538655 | AJ74: 0.3320431 | AK74: 0.63096509 | AL74: 6044.713 | AM74: 684.46 | AN74: 2.4783 | AO74: 0.00015093363 | AP74: 16.726195 | AQ74: 0.45739459 | AR74: 0.20087186 | AS74: 3.9284155 | AT74: 20.6 | AU74: 0.9310838 | AV74: 0.97966688 | AW74: 86.8 | AX74: 9.2753186 | AY74: 37.704547 | AZ74: 77.58 | BA74: 24.992858 | BB74: 7.8780125 | BC74: 2.0676264 | BD74: 137.43857 | BE74: 0.6907 | BF74: 0.9204 | BG74: 0.9011 | BH74: 0.5933 | BI74: 0.0205 | BJ74: 262.60908 | BK74: 260 | BL74: 0.70354629 | BM74: 21.463143 | BN74: 45.985 | BO74: 349.416 | BP74: 16.938 | BQ74: 148.67097 | BR74: 9.3714609 | BS74: 56.084143 | BT74: 18.224163 | BU74: 11.089165 | BV74: 0.51751775 | BW74: 0.025118544 | BX74: 0.2732924 | BY74: 0.0104808 | BZ74: 8.8 | CA74: 5.33 | CB74: 0.02627605 | CC74: 50.606214 | CD74: 12.859545 | CE74: 30.345451 | CF74: 7.6776486 | CG74: 0.4994927 | CH74: 63.511881 | CI74: 69.263687 | CJ74: 0.007245977 | CK74: 0.19108271 | CL74: 30.960934 | CM74: 27.673 | CN74: 5.7931086 | CO74: 0.318 | CP74: 0.71 | CQ74: 2.4656225 | CR74: 0.71582588 | CS74: 369.04801 | CT74: 0.003 | CU74: 0.75 | CV74: 26.14 | CW74: 6.4992566 | CX74: 0.81240708 | CY74: 7.3116637 | CZ74: 255.09582
A75: Caldas | B75: 2021 | C75: 131.8794 | D75: 73.765719 | E75: 81.273333 | F75: 0.31147216 | G75: 0.013485369 | H75: 51.34 | I75: 46.8 | J75: 93.857373 | K75: 0.065826071 | L75: 14.978927 | M75: 0 | N75: 9.3985422 | O75: 0.66543558 | P75: 440.28873 | Q75: 0.58469171 | R75: 0.8872149 | S75: 0.64917697 | T75: n/a | U75: 99.801879 | V75: 539.92187 | W75: 0.81276657 | X75: 42.602227 | Y75: 5.4459559 | Z75: 0.89421865 | AA75: 58.393339 | AB75: 7.5614858 | AC75: 0.68592506 | AD75: 541.69642 | AE75: 550.08979 | AF75: 67681 | AG75: 0.0136 | AH75: 0.12069889 | AI75: 12.911491 | AJ75: 0.41098517 | AK75: 0.70654343 | AL75: 6575.649 | AM75: 1039.217 | AN75: 2.7368 | AO75: 0.00039173428 | AP75: 5.1654433 | AQ75: 0.49844036 | AR75: 0.12040141 | AS75: 1.9205587 | AT75: 7.8666667 | AU75: 0.96515365 | AV75: 0.96240034 | AW75: 93.89 | AX75: 11.186232 | AY75: 24.585126 | AZ75: 78.29 | BA75: 31.587824 | BB75: 9.2630046 | BC75: 4.5835885 | BD75: 186.79603 | BE75: 0.6461 | BF75: 0.8079 | BG75: 0.7745 | BH75: 0.4642 | BI75: 0.0331 | BJ75: 256.123 | BK75: 255.65906 | BL75: 0.42783726 | BM75: 21.697859 | BN75: 41.282 | BO75: 294.741 | BP75: 16.607 | BQ75: 146.8669 | BR75: 17.90378 | BS75: 65.643105 | BT75: 25.284698 | BU75: 41.191904 | BV75: 0.51780586 | BW75: 0.03531218 | BX75: 0.05482 | BY75: 0.0405993 | BZ75: 7.02 | CA75: 5.67 | CB75: 0.064739484 | CC75: 58.372336 | CD75: 16.411094 | CE75: 38.576078 | CF75: 6.0505188 | CG75: 0.31381228 | CH75: 33.363917 | CI75: 70.517115 | CJ75: 0.01765073 | CK75: 0.35065125 | CL75: 30.355484 | CM75: 28.878 | CN75: 22.291513 | CO75: 0.112 | CP75: 0.403 | CQ75: 7.3426111 | CR75: 1.0769163 | CS75: 497.33953 | CT75: 0.007 | CU75: 0.6 | CV75: 32.67 | CW75: 19.834501 | CX75: 7.9338004 | CY75: 5.9503503 | CZ75: 788.42141
A76: Caquetá | B76: 2021 | C76: 94.699524 | D76: 70.913518 | E76: 42.105714 | F76: 0.19651639 | G76: 0.014835652 | H76: 39.34 | I76: 88.37 | J76: 97.465875 | K76: 0.12252461 | L76: 34.567113 | M76: 0.24172807 | N76: 15.470596 | O76: 0.57845552 | P76: 591.48148 | Q76: 0.52860412 | R76: 0.71690502 | S76: 0.90800582 | T76: 0.59840728 | U76: 92.189937 | V76: 597.31051 | W76: 0.60395899 | X76: 128.10667 | Y76: 0.58483111 | Z76: 0.48273196 | AA76: 35.461507 | AB76: 0.16489631 | AC76: 0.072256305 | AD76: 449.93267 | AE76: 403.59448 | AF76: 42882 | AG76: 0.0148 | AH76: 0.06630932 | AI76: 9.0112583 | AJ76: 0.24430547 | AK76: 0.58371176 | AL76: 2233.717 | AM76: 143.689 | AN76: 1.5 | AO76: 0.0034077446 | AP76: 37.836708 | AQ76: 0.16917976 | AR76: 0.13147692 | AS76: 3.4919249 | AT76: 18.36875 | AU76: 0.93835891 | AV76: 0.90837452 | AW76: 79.37 | AX76: 8.1668368 | AY76: 72.918186 | AZ76: 73.48 | BA76: 15.317914 | BB76: 4.9738344 | BC76: 0.73049297 | BD76: 133.67562 | BE76: 0.578 | BF76: 0.892 | BG76: 0.6856 | BH76: 0.3358 | BI76: 0.0532 | BJ76: 244 | BK76: 246 | BL76: 0.38127632 | BM76: 19.417557 | BN76: 26.995 | BO76: 134.928 | BP76: 4.154 | BQ76: 135.76607 | BR76: 4.6767538 | BS76: 0.047672017 | BT76: 8.6206897 | BU76: 17.730802 | BV76: 0.28453608 | BW76: 0.028820961 | BX76: 0.044557 | BY76: 0.0787038 | BZ76: 5.82 | CA76: 3.18 | CB76: 0.026819923 | CC76: 56.356368 | CD76: 18.539725 | CE76: 17.867306 | CF76: 12.148661 | CG76: 0.42969399 | CH76: 53.77071 | CI76: 51.347551 | CJ76: 0.0063313744 | CK76: 0.3417025 | CL76: 29.090226 | CM76: 22.067 | CN76: 0.049312649 | CO76: 0.616 | CP76: 0.324 | CQ76: 0.48345613 | CR76: 0 | CS76: 99.108507 | CT76: 0.005 | CU76: 0.9 | CV76: 13.51 | CW76: 2.462193 | CX76: 0 | CY76: 0 | CZ76: 172.35351
A77: Casanare | B77: 2021 | C77: 119.77925 | D77: 75.583265 | E77: 73.7125 | F77: 0.18189506 | G77: 0.0072027674 | H77: 52.58 | I77: 51.36 | J77: 94.693843 | K77: 0.17021647 | L77: 19.61527 | M77: 1.3527773 | N77: 22.320825 | O77: 0.43380118 | P77: 317.09259 | Q77: 0.51434426 | R77: 0.8244569 | S77: 0.81816065 | T77: n/a | U77: 96.522139 | V77: 536.42406 | W77: 0.69163024 | X77: 117.65855 | Y77: 1.1295721 | Z77: 0.66705144 | AA77: 70.629401 | AB77: 1.2232139 | AC77: 0.6854332 | AD77: 303.36004 | AE77: 241.39866 | AF77: 85770 | AG77: 0.0388 | AH77: 0.088990417 | AI77: 11.748275 | AJ77: 0.3459189 | AK77: 0.68286184 | AL77: 2299.115 | AM77: 224.553 | AN77: 0.9474 | AO77: 0.00036469534 | AP77: 3.455088 | AQ77: 0.47487237 | AR77: 0.26580221 | AS77: 1.1348756 | AT77: 7.1526316 | AU77: 0.96982435 | AV77: 0.96545371 | AW77: 81.14 | AX77: 7.9432145 | AY77: 118.30319 | AZ77: 77.16 | BA77: 31.116947 | BB77: 7.0904913 | BC77: 1.2644223 | BD77: 158.72586 | BE77: 0.6921 | BF77: 0.9144 | BG77: 0.809 | BH77: 0.4498 | BI77: 0.0301 | BJ77: 256.54004 | BK77: 257 | BL77: 0.41142384 | BM77: 23.982202 | BN77: 19.319 | BO77: 48.534 | BP77: 6.864 | BQ77: 138.67027 | BR77: 1.8181818 | BS77: 16.981681 | BT77: 7.6923077 | BU77: 24.369231 | BV77: 0.50711864 | BW77: 0.031607263 | BX77: 0.0281223 | BY77: 0.3033634 | BZ77: 11.83 | CA77: 8.81 | CB77: 0.034950443 | CC77: 66.075559 | CD77: 14.822453 | CE77: 35.208684 | CF77: 6.9562443 | CG77: 0.44071159 | CH77: 63.860072 | CI77: 73.151625 | CJ77: 0.0034999612 | CK77: 0.11089898 | CL77: 30.070506 | CM77: 28.265 | CN77: 30.234565 | CO77: 0.588 | CP77: 0.991 | CQ77: 0 | CR77: 0 | CS77: 29.310174 | CT77: 0.001 | CU77: 0 | CV77: 0 | CW77: 0 | CX77: 0 | CY77: 2.3333792 | CZ77: 168.0033
A78: Cauca | B78: 2021 | C78: 79.987688 | D78: 76.299137 | E78: 59.20875 | F78: 0.1428533 | G78: 0.0065088036 | H78: 45.18 | I78: 46.22 | J78: 95.568468 | K78: 0.11841672 | L78: 54.374458 | M78: 1.1272754 | N78: 22.015025 | O78: 0.52944371 | P78: 334.43066 | Q78: 0.44408946 | R78: 0.78736 | S78: 0.6853884 | T78: 0.84245717 | U78: 98.049454 | V78: 565.80022 | W78: 0.41518599 | X78: 97.296685 | Y78: 4.9080149 | Z78: 0.54529711 | AA78: 21.921465 | AB78: 1.1279824 | AC78: 0.63190212 | AD78: 373.85611 | AE78: 328.3981 | AF78: 29415 | AG78: 0.0126 | AH78: 0.051085391 | AI78: 13.609509 | AJ78: 0.22426921 | AK78: 0.5454322 | AL78: 4142.121 | AM78: 418.999 | AN78: 1.5185 | AO78: 0.00061177835 | AP78: 8.8110941 | AQ78: 0.19976173 | AR78: 0.099614133 | AS78: 1.9642078 | AT78: 13.392857 | AU78: 0.90503453 | AV78: 0.90302542 | AW78: 84.06 | AX78: 10.287461 | AY78: 82.299688 | AZ78: 76.16 | BA78: 20.109923 | BB78: 5.6286525 | BC78: 1.4549601 | BD78: 106.29543 | BE78: 0.5449 | BF78: 0.8523 | BG78: 0.6878 | BH78: 0.3642 | BI78: 0.0278 | BJ78: 235.91948 | BK78: 243 | BL78: 0.37467675 | BM78: 23.938035 | BN78: 25.256 | BO78: 100.175 | BP78: 10.322 | BQ78: 141.98859 | BR78: 8.8003321 | BS78: 39.459965 | BT78: 13.547904 | BU78: 38.099507 | BV78: 0.3694668 | BW78: 0.035407725 | BX78: 0.5597757 | BY78: 0.240367 | BZ78: 3.15 | CA78: 2.19 | CB78: 0.055708601 | CC78: 58.333399 | CD78: 15.449987 | CE78: 19.050851 | CF78: 12.813086 | CG78: 0.67888383 | CH78: 30.868945 | CI78: 39.451982 | CJ78: 0.0088950708 | CK78: 0.15937808 | CL78: 30.584006 | CM78: 27.229 | CN78: 9.7086899 | CO78: 0.126 | CP78: 0.169 | CQ78: 1.5914476 | CR78: 0.13262063 | CS78: 150.52442 | CT78: 0.003 | CU78: 1.06 | CV78: 21.7 | CW78: 6.7640372 | CX78: 0 | CY78: 0 | CZ78: 215.77279
A79: Cesar | B79: 2021 | C79: 106.64053 | D79: 69.578485 | E79: 40.0925 | F79: 0.18939663 | G79: 0.0069558852 | H79: 48.49 | I79: 88.37 | J79: 95.842515 | K79: 0.072043937 | L79: 16.887194 | M79: 0.54224936 | N79: 13.091449 | O79: 0.53613647 | P79: 593.45745 | Q79: 0.60746004 | R79: 0.86422663 | S79: 0.89245026 | T79: 0.10308149 | U79: 96.486323 | V79: 503.36848 | W79: 0.72921074 | X79: 58.810378 | Y79: 3.2156298 | Z79: 0.69779723 | AA79: 16.308537 | AB79: 0.91914429 | AC79: 0.73276968 | AD79: 315.23804 | AE79: 283.2154 | AF79: 131132 | AG79: 0.138 | AH79: 0.081733602 | AI79: 13.829708 | AJ79: 0.25003847 | AK79: 0.65990108 | AL79: 2835.442 | AM79: 306.581 | AN79: 1.3333 | AO79: 0.00019384414 | AP79: 0.78307182 | AQ79: 0.47213188 | AR79: 0.41195146 | AS79: 2.7498909 | AT79: 13.12 | AU79: 0.98796074 | AV79: 1 | AW79: 83.89 | AX79: 12.152332 | AY79: 77.021823 | AZ79: 75.86 | BA79: 32.356774 | BB79: 7.8526172 | BC79: 1.51667 | BD79: 217.75185 | BE79: 0.56 | BF79: 0.8823 | BG79: 0.714 | BH79: 0.4008 | BI79: 0.0411 | BJ79: 244.37976 | BK79: 243 | BL79: 0.31715437 | BM79: 33.085159 | BN79: 22.753 | BO79: 131.907 | BP79: 8.832 | BQ79: 137.27105 | BR79: 10.15953 | BS79: 1.1890638 | BT79: 10.411311 | BU79: 66.943258 | BV79: 0.33266444 | BW79: 0.015972618 | BX79: 0.0639779 | BY79: 0.0083807 | BZ79: 7.87 | CA79: 3.97 | CB79: 0.040295893 | CC79: 57.363581 | CD79: 14.616221 | CE79: 19.267758 | CF79: 6.3408956 | CG79: 0.64349769 | CH79: 32.79299 | CI79: 45.58511 | CJ79: 0.0048910107 | CK79: 0.1932665 | CL79: 30.023797 | CM79: 29.87 | CN79: 47.729076 | CO79: 0.094 | CP79: 0.958 | CQ79: 0.69717775 | CR79: 0 | CS79: 69.717775 | CT79: 0.002 | CU79: 0.56 | CV79: 10 | CW79: 0 | CX79: 0 | CY79: 0.79846822 | CZ79: 100.607
A80: Chocó | B80: 2021 | C80: 77.355501 | D80: 67.081743 | E80: 50.434286 | F80: 0.13979124 | G80: 0.016543708 | H80: 13.69 | I80: 48.255 | J80: 89.030192 | K80: 0.22572766 | L80: 49.965593 | M80: 0.1778135 | N80: 16.181028 | O80: 0.51968855 | P80: 207.54795 | Q80: 0.68510638 | R80: 0.35057536 | S80: 0.10309032 | T80: 0.8056338 | U80: 95.862765 | V80: 548.36328 | W80: 0.21369849 | X80: 51.658817 | Y80: 0.59944767 | Z80: 0.61296939 | AA80: 7.5392923 | AB80: 0.091124006 | AC80: 0.61509434 | AD80: 545.18435 | AE80: 583.31768 | AF80: 130275 | AG80: 0.1254 | AH80: 0.043686902 | AI80: 6.6405561 | AJ80: 0.12942524 | AK80: 0.41009819 | AL80: 1293.746 | AM80: 129.762 | AN80: 0.8571 | AO80: 0.0024622824 | AP80: 8.6815985 | AQ80: 0.081433786 | AR80: 0.14461706 | AS80: 5.5434308 | AT80: 4.2633333 | AU80: 0.86150454 | AV80: 0.8285687 | AW80: 69.03 | AX80: 27.358222 | AY80: 170.98889 | AZ80: 71.62 | BA80: 14.581847 | BB80: 3.2834303 | BC80: 0.45740271 | BD80: 150.25241 | BE80: 0.5313 | BF80: 0.8413 | BG80: 0.5338 | BH80: 0.2392 | BI80: 0.028 | BJ80: 209 | BK80: 216 | BL80: 0.19478938 | BM80: 27.03701 | BN80: 25.716 | BO80: 59.637 | BP80: 1.956 | BQ80: 120.69095 | BR80: 2.6708562 | BS80: 1.3188625 | BT80: 3.4427542 | BU80: 0 | BV80: 0.25747348 | BW80: 0.0046480744 | BX80: 0.0514227 | BY80: 0.0338902 | BZ80: 5.1 | CA80: 2.56 | CB80: 0.014316392 | CC80: 42.552154 | CD80: 9.6131945 | CE80: 19.451406 | CF80: 2.1077427 | CG80: 0.5941127 | CH80: 30.520386 | CI80: 29.667602 | CJ80: 0.0028612325 | CK80: 0.14305738 | CL80: 29.012855 | CM80: 26.716 | CN80: 5.0208234 | CO80: 0.364 | CP80: 0.951 | CQ80: 0.355627 | CR80: 0 | CS80: 64.012859 | CT80: 0.005 | CU80: 0.14 | CV80: 40 | CW80: 0 | CX80: 0 | CY80: 0 | CZ80: 74.083266
A81: Córdoba | B81: 2021 | C81: 82.444697 | D81: 63.659973 | E81: 30.57 | F81: 0.16358302 | G81: 0.011387497 | H81: 41.27 | I81: 45.545 | J81: 92.165109 | K81: 0.083404367 | L81: 16.661375 | M81: 0.05427158 | N81: 6.1326886 | O81: 0.58549366 | P81: 508.39 | Q81: 0.62759924 | R81: 0.68141451 | S81: 0.88751656 | T81: 0.510216 | U81: 98.437115 | V81: 459.15583 | W81: 0.40086342 | X81: 41.190386 | Y81: 2.9772302 | Z81: 0.81732304 | AA81: 12.240412 | AB81: 0.90143885 | AC81: 0.50270462 | AD81: 314.4843 | AE81: 313.77731 | AF81: 412501 | AG81: 0.1566 | AH81: 0.057074084 | AI81: 11.636231 | AJ81: 0.17345443 | AK81: 0.47804867 | AL81: 2249.287 | AM81: 296.679 | AN81: 1.3846 | AO81: 0.00070423661 | AP81: 25.440372 | AQ81: 0.30268868 | AR81: 0.099473004 | AS81: 3.9284155 | AT81: 14.06 | AU81: 0.88589245 | AV81: 0.87035325 | AW81: 87.55 | AX81: 14.837626 | AY81: 83.986562 | AZ81: 76.73 | BA81: 17.030685 | BB81: 5.2896878 | BC81: 1.151979 | BD81: 154.02275 | BE81: 0.549 | BF81: 0.8917 | BG81: 0.7923 | BH81: 0.4526 | BI81: 0.0264 | BJ81: 237.14631 | BK81: 240 | BL81: 0.44503441 | BM81: 25.469715 | BN81: 22.629 | BO81: 53.361 | BP81: 2.594 | BQ81: 136.37963 | BR81: 8.3713851 | BS81: 73.335288 | BT81: 12.171053 | BU81: 55.203709 | BV81: 0.20733054 | BW81: 0.017821782 | BX81: 0.0834352 | BY81: 0.4388173 | BZ81: 4.13 | CA81: 2.54 | CB81: 0.055184307 | CC81: 62.546224 | CD81: 16.252656 | CE81: 14.187274 | CF81: 10.395211 | CG81: 0.6145203 | CH81: 26.262301 | CI81: 32.876873 | CJ81: 0.0070954235 | CK81: 0.25399185 | CL81: 30.411689 | CM81: 28.406 | CN81: 12.855872 | CO81: 0.237 | CP81: 0.529 | CQ81: 1.2482463 | CR81: 0.05427158 | CS81: 136.22167 | CT81: 0.003 | CU81: 0.92 | CV81: 22.6 | CW81: 0.55296308 | CX81: 0 | CY81: 0 | CZ81: 93.450761
A82: Cundinamarca | B82: 2021 | C82: 144.18284 | D82: 61.706289 | E82: 84.7875 | F82: 0.52982696 | G82: 0.017680607 | H82: 64.08 | I82: 55.4 | J82: 90.713432 | K82: 0.020422388 | L82: 10.864199 | M82: 0.031766665 | N82: 9.6252995 | O82: 0.51897376 | P82: 359.55271 | Q82: 0.66270077 | R82: 0.89603117 | S82: 0.73735073 | T82: 0.73464789 | U82: 99.661271 | V82: 514.97576 | W82: 0.74300593 | X82: 38.805038 | Y82: 5.2902311 | Z82: 0.88929647 | AA82: 65.108003 | AB82: 9.0556709 | AC82: 0.73542987 | AD82: 424.08372 | AE82: 404.77896 | AF82: - | AG82: - | AH82: 0.13489776 | AI82: 15.50506 | AJ82: 0.40159293 | AK82: 0.73188396 | AL82: 3108.324 | AM82: 304.005 | AN82: 1.5556 | AO82: 0.00010648169 | AP82: 12.495828 | AQ82: 0.55015133 | AR82: 0.21863505 | AS82: 6.9943256 | AT82: 14.122414 | AU82: 0.96677974 | AV82: 0.97099953 | AW82: 85.94 | AX82: 7.5861282 | AY82: 68.44627 | AZ82: 78.77 | BA82: 14.255657 | BB82: 2.9906771 | BC82: 1.0795861 | BD82: 97.460128 | BE82: 0.6593 | BF82: 0.9463 | BG82: 0.8596 | BH82: 0.497 | BI82: 0.0302 | BJ82: 264.56589 | BK82: 255 | BL82: 0.40852626 | BM82: 28.392904 | BN82: 15.832 | BO82: 82.223 | BP82: 13.767 | BQ82: 147.07197 | BR82: 9.3494705 | BS82: 25.60029 | BT82: 22.572003 | BU82: 48.390104 | BV82: 0.55663522 | BW82: 0.040355424 | BX82: 0.0644177 | BY82: 0.004294 | BZ82: 9.37 | CA82: 7.18 | CB82: 0.075575404 | CC82: 66.794099 | CD82: 17.091974 | CE82: 32.87456 | CF82: 10.141812 | CG82: 0.35490301 | CH82: 50.865183 | CI82: 58.59049 | CJ82: 0.0041558815 | CK82: 0.1805692 | CL82: 31.847206 | CM82: 29.426 | CN82: 28.043807 | CO82: 0.142 | CP82: 0.049 | CQ82: 1.0165333 | CR82: 0.12706666 | CS82: 95.617662 | CT82: 0.004 | CU82: 1.07 | CV82: 21.06 | CW82: 5.8336969 | CX82: 3.8891312 | CY82: 13.287865 | CZ82: 690.96898
A83: Guainía | B83: 2021 | C83: 99.162656 | D83: 74.790565 | E83: 45.51375 | F83: 0.10299954 | G83: 0.046059043 | H83: 62.24 | I83: 41.86 | J83: 100 | K83: 0.0011648224 | L83: 7.6914202 | M83: 0 | N83: 13.459985 | O83: n/a | P83: n/a | Q83: 0.31111111 | R83: 0.21151678 | S83: - | T83: n/a | U83: 70.18638 | V83: 804.58124 | W83: 0.25386125 | X83: - | Y83: - | Z83: - | AA83: 37.587971 | AB83: 0.02706055 | AC83: 0 | AD83: NA | AE83: - | AF83: 19112 | AG83: 0.0132 | AH83: 0.02908869 | AI83: 1.2847425 | AJ83: 0.13831799 | AK83: 0.29481309 | AL83: 3448.276 | AM83: 273.673 | AN83: 1.8 | AO83: 0.00019837205 | AP83: 15.290287 | AQ83: 0.044696032 | AR83: 0.28382504 | AS83: 0.91663029 | AT83: 1.7 | AU83: 0.98350515 | AV83: 1 | AW83: 29.1 | AX83: 21.875 | AY83: 312.5 | AZ83: 72.74 | BA83: 29.556757 | BB83: 5.0162162 | BC83: 0.60540541 | BD83: 88.451333 | BE83: 0.4864 | BF83: 0.6719 | BG83: 0.3146 | BH83: 0.0869 | BI83: 0.057 | BJ83: 225 | BK83: 246 | BL83: 0.18489583 | BM83: 33.307292 | BN83: 3.211 | BO83: 68.724 | BP83: 8.648 | BQ83: 134.15152 | BR83: 0 | BS83: 1.3927577 | BT83: 0 | BU83: 0 | BV83: 0.36437247 | BW83: 0 | BX83: 0.2112118 | BY83: 0.0284206 | BZ83: 3.75 | CA83: 2.07 | CB83: 0.019047619 | CC83: 49.133605 | CD83: 21.235639 | CE83: 27.954872 | CF83: 6.1525156 | CG83: 0.59707075 | CH83: 22.188485 | CI83: 66.744521 | CJ83: 0.00073364138 | CK83: 0.075317457 | CL83: 26.74022 | CM83: 18.532 | CN83: 0.095470643 | CO83: 0.499 | CP83: 0.471 | CQ83: 0 | CR83: 0 | CS83: 19.228551 | CT83: 0.018 | CU83: 0 | CV83: 0 | CW83: 0 | CX83: 0 | CY83: 0 | CZ83: 60.639136
A84: Guaviare | B84: 2021 | C84: 132.91686 | D84: 75.671267 | E84: 65.67875 | F84: 0.15999104 | G84: 0.034335637 | H84: 44.32 | I84: 49.36 | J84: 95.850461 | K84: 0.00038729667 | L84: 26.951151 | M84: 0 | N84: 38.180797 | O84: 0 | P84: n/a | Q84: 1 | R84: 0.39826765 | S84: 0.39385768 | T84: n/a | U84: 85.704827 | V84: 675.02822 | W84: 0.40637712 | X84: 169.72001 | Y84: 0.26894875 | Z84: 0.34949962 | AA84: 0 | AB84: 0 | AC84: 0 | AD84: 546.46904 | AE84: 596.12728 | AF84: 9868 | AG84: 0.0298 | AH84: 0.030856037 | AI84: 8.4922445 | AJ84: 0.24444291 | AK84: 0.5164703 | AL84: 5187.943 | AM84: 324.246 | AN84: 1 | AO84: 0.0045304901 | AP84: 37.86516 | AQ84: 0.16747282 | AR84: 0.16983662 | AS84: 1.39677 | AT84: 7.925 | AU84: 1 | AV84: 1 | AW84: 67.57 | AX84: 15.055468 | AY84: 158.47861 | AZ84: 75.59 | BA84: 26.184059 | BB84: 7.0552871 | BC84: 0.33537456 | BD84: 176.30545 | BE84: 0.4211 | BF84: 0.7969 | BG84: 0.6844 | BH84: 0.3038 | BI84: 0.0447 | BJ84: 237 | BK84: 237 | BL84: 0.42392718 | BM84: 28.162549 | BN84: 7.794 | BO84: 10.624 | BP84: 17.593 | BQ84: 133.86556 | BR84: 0 | BS84: 0 | BT84: 2.2099448 | BU84: 0 | BV84: 0.34937238 | BW84: 0.070886076 | BX84: 0.1950994 | BY84: 0.0403202 | BZ84: 12.46 | CA84: 3.91 | CB84: 0.01179941 | CC84: 83.03031 | CD84: 16.973053 | CE84: 28.424467 | CF84: 10.331233 | CG84: 0.44760113 | CH84: 44.647116 | CI84: 60.884166 | CJ84: 0.0015155143 | CK84: 0.28758453 | CL84: 27.44058 | CM84: 18.15 | CN84: 0.56601887 | CO84: 1 | CP84: 0.507 | CQ84: 1.1229646 | CR84: 0 | CS84: 0 | CT84: 0.011 | CU84: 0 | CV84: 0 | CW84: 0 | CX84: 0 | CY84: 0 | CZ84: 11.804146
A85: Huila | B85: 2021 | C85: 113.84122 | D85: 68.986949 | E85: 57.535 | F85: 0.24903954 | G85: 0.010244605 | H85: 53.27 | I85: 48.835 | J85: 97.665056 | K85: 0.088508876 | L85: 21.54962 | M85: 0.087957633 | N85: 16.71195 | O85: 0.59264612 | P85: 507.2963 | Q85: 0.73129437 | R85: 0.8634792 | S85: 0.91271231 | T85: 0.88221089 | U85: 99.034718 | V85: 515.53888 | W85: 0.66268291 | X85: 88.554869 | Y85: 4.950186 | Z85: 0.76742358 | AA85: 43.688556 | AB85: 2.4972348 | AC85: 0.991363 | AD85: 285.05395 | AE85: 197.8102 | AF85: 75641 | AG85: 0.236 | AH85: 0.096523433 | AI85: 11.265526 | AJ85: 0.30518504 | AK85: 0.6537008 | AL85: 3849.794 | AM85: 674.897 | AN85: 1.2 | AO85: 9.4017094e-05 | AP85: 24.571541 | AQ85: 0.35698021 | AR85: 0.14986879 | AS85: 3.4046268 | AT85: 12.764865 | AU85: 0.93059777 | AV85: 0.92301654 | AW85: 91.9 | AX85: 8.320242 | AY85: 40.728458 | AZ85: 75.56 | BA85: 27.851552 | BB85: 8.8307778 | BC85: 3.4086287 | BD85: 204.14967 | BE85: 0.6848 | BF85: 0.9218 | BG85: 0.8135 | BH85: 0.4583 | BI85: 0.0448 | BJ85: 256.7725 | BK85: 261 | BL85: 0.56589415 | BM85: 25.033034 | BN85: 26.969 | BO85: 83.735 | BP85: 13.634 | BQ85: 137.78864 | BR85: 34.48966 | BS85: 38.247899 | BT85: 10.558273 | BU85: 23.792183 | BV85: 0.36463224 | BW85: 0.0093879084 | BX85: 0.0217237 | BY85: 0.0206157 | BZ85: 6.48 | CA85: 4.92 | CB85: 0.033502354 | CC85: 59.377427 | CD85: 16.121111 | CE85: 21.236246 | CF85: 9.3732453 | CG85: 0.67218792 | CH85: 59.758659 | CI85: 105.60573 | CJ85: 0.012185061 | CK85: 0.33831176 | CL85: 30.396796 | CM85: 28.353 | CN85: 9.5504842 | CO85: 0.185 | CP85: 0.738 | CQ85: 1.1434492 | CR85: 0 | CS85: 115.2245 | CT85: 0.002 | CU85: 1.03 | CV85: 29.62 | CW85: 9.8934743 | CX85: 0 | CY85: 0 | CZ85: 291.40779
A86: La Guajira | B86: 2021 | C86: 76.709381 | D86: 65.232035 | E86: 53.98625 | F86: 0.18212456 | G86: 0.0086105491 | H86: 51 | I86: 47.095 | J86: 92.364475 | K86: 0.040539112 | L86: 19.811901 | M86: 0.31118169 | N86: 10.683905 | O86: 0.40290284 | P86: 301.81818 | Q86: 0.4025974 | R86: 0.50628284 | S86: 0.8110542 | T86: n/a | U86: 65.518797 | V86: 531.32428 | W86: 0.40809428 | X86: 36.42122 | Y86: 1.6203425 | Z86: 0.58415632 | AA86: 32.722829 | AB86: 1.5131907 | AC86: 0.42187847 | AD86: 160.42192 | AE86: 177.06376 | AF86: 78523 | AG86: 0.124 | AH86: 0.051173793 | AI86: 8.8129958 | AJ86: 0.11015511 | AK86: 0.40610938 | AL86: 1452.859 | AM86: 151.097 | AN86: 1.6923 | AO86: 0.00026381427 | AP86: 15.904798 | AQ86: 0.28040225 | AR86: 0.19541095 | AS86: 2.0515059 | AT86: 14.253333 | AU86: 0.99037463 | AV86: 0.95729484 | AW86: 61.33 | AX86: 23.508709 | AY86: 189.51358 | AZ86: 70.24 | BA86: 22.600152 | BB86: 6.1890375 | BC86: 0.61583051 | BD86: 144.80321 | BE86: 0.7201 | BF86: 0.9302 | BG86: 0.5799 | BH86: 0.2508 | BI86: 0.0251 | BJ86: 229.45375 | BK86: 232.9507 | BL86: 0.21635389 | BM86: 26.083914 | BN86: 15.592 | BO86: 29.11 | BP86: 6.129 | BQ86: 131.37649 | BR86: 8.0405405 | BS86: 3.2811114 | BT86: 5.066345 | BU86: 0 | BV86: 0.22133832 | BW86: 0.015907448 | BX86: 0.0556425 | BY86: 0.0077778 | BZ86: 4.17 | CA86: 2.1 | CB86: 0.026600985 | CC86: 67.823295 | CD86: 10.177335 | CE86: 14.320994 | CF86: 15.450898 | CG86: 0.7740416 | CH86: 26.858823 | CI86: 36.285146 | CJ86: 0.0036658291 | CK86: 0.10739874 | CL86: 29.471144 | CM86: 28.706 | CN86: 46.374291 | CO86: 0.187 | CP86: 0.984 | CQ86: 1.348454 | CR86: 0 | CS86: 146.2554 | CT86: 0.001 | CU86: 0.45 | CV86: 19.05 | CW86: 0 | CX86: 2.1563203 | CY86: 2.1563203 | CZ86: 65.767769
A87: Magdalena | B87: 2021 | C87: 100.34918 | D87: 72.174371 | E87: 85.067778 | F87: 0.25248884 | G87: 0.014535569 | H87: 49.67 | I87: 61.96 | J87: 95.051949 | K87: 0.058553387 | L87: 20.616778 | M87: 0.21037529 | N87: 10.86939 | O87: 0.4969862 | P87: 355.91667 | Q87: 0.61639598 | R87: 0.78573294 | S87: 0.81740764 | T87: n/a | U87: 97.984561 | V87: 479.72031 | W87: 0.47244495 | X87: 39.374669 | Y87: 2.3583233 | Z87: 0.89586083 | AA87: 13.458872 | AB87: 0.82769801 | AC87: 0.19153466 | AD87: 197.3694 | AE87: 236.39481 | AF87: 772983 | AG87: 0.1714 | AH87: 0.071679656 | AI87: 16.660881 | AJ87: 0.24077879 | AK87: 0.56539173 | AL87: 2669.151 | AM87: 324.701 | AN87: 1.9412 | AO87: 0.00025056063 | AP87: 12.590627 | AQ87: 0.44727536 | AR87: 0.071207543 | AS87: 2.0078568 | AT87: 10.186667 | AU87: 0.93858873 | AV87: 0.94781784 | AW87: 78.77 | AX87: 12.424378 | AY87: 109.62686 | AZ87: 75.59 | BA87: 20.793441 | BB87: 6.0415854 | BC87: 1.160962 | BD87: 190.52989 | BE87: 0.6186 | BF87: 0.9183 | BG87: 0.7384 | BH87: 0.4103 | BI87: 0.035 | BJ87: 229.55982 | BK87: 228 | BL87: 0.21687541 | BM87: 28.319842 | BN87: 20.946 | BO87: 70.059 | BP87: 7.346 | BQ87: 140.55843 | BR87: 9.4238281 | BS87: 61.889051 | BT87: 15.682608 | BU87: 54.661363 | BV87: 0.30769231 | BW87: 0.027138158 | BX87: 0.0680279 | BY87: 0.0347208 | BZ87: 7.34 | CA87: 4.31 | CB87: 0.060103964 | CC87: 56.082261 | CD87: 11.857215 | CE87: 21.042336 | CF87: 9.7397044 | CG87: 0.65895511 | CH87: 31.668801 | CI87: 43.214742 | CJ87: 0.0073067081 | CK87: 0.32447999 | CL87: 30.182047 | CM87: 28.6 | CN87: 23.287887 | CO87: 0.109 | CP87: 0.315 | CQ87: 2.1037529 | CR87: 0.28050038 | CS87: 167.59898 | CT87: 0.003 | CU87: 0.81 | CV87: 32.48 | CW87: 1.440059 | CX87: 0.72002949 | CY87: 1.440059 | CZ87: 138.96569
A88: Meta | B88: 2021 | C88: 108.80451 | D88: 74.514372 | E88: 77.167778 | F88: 0.26738611 | G88: 0.007590115 | H88: 52.14 | I88: 55.98 | J88: 97.236611 | K88: 0.08732341 | L88: 26.431751 | M88: 0.36967483 | N88: 34.657016 | O88: 0.52722361 | P88: 453.14685 | Q88: 0.62304793 | R88: 0.78391397 | S88: 0.84550101 | T88: 0.09925829 | U88: 96.141482 | V88: 529.46491 | W88: 0.74379994 | X88: 89.543638 | Y88: 1.1001471 | Z88: 0.90009902 | AA88: 12.19927 | AB88: 0.15414258 | AC88: 0.63636364 | AD88: 416.58789 | AE88: 275.37219 | AF88: 48471 | AG88: 0.1788 | AH88: 0.11955329 | AI88: 18.40836 | AJ88: 0.35936299 | AK88: 0.76909465 | AL88: 2091.017 | AM88: 421.654 | AN88: 1.1724 | AO88: 0.0035095707 | AP88: 14.800551 | AQ88: 0.57979981 | AR88: 0.18062726 | AS88: 2.6189437 | AT88: 17.413793 | AU88: 0.95671851 | AV88: 0.92036613 | AW88: 79.88 | AX88: 11.402431 | AY88: 54.622423 | AZ88: 75.86 | BA88: 25.692235 | BB88: 6.3692398 | BC88: 1.702639 | BD88: 151.47426 | BE88: 0.6464 | BF88: 0.9163 | BG88: 0.7983 | BH88: 0.4499 | BI88: 0.0397 | BJ88: 254.73524 | BK88: 254 | BL88: 0.42527244 | BM88: 30.917748 | BN88: 26.261 | BO88: 78.793 | BP88: 7.126 | BQ88: 141.02145 | BR88: 5.9925094 | BS88: 17.023654 | BT88: 11.871426 | BU88: 54.198417 | BV88: 0.46508779 | BW88: 0.036977492 | BX88: 0.010947 | BY88: 0.0504832 | BZ88: 14.13 | CA88: 7.68 | CB88: 0.036746693 | CC88: 58.363291 | CD88: 20.291228 | CE88: 28.049368 | CF88: 6.4399266 | CG88: 0.43321181 | CH88: 57.393504 | CI88: 72.197976 | CJ88: 0.0050828445 | CK88: 0.14887947 | CL88: 31.197918 | CM88: 27.983 | CN88: 7.9454087 | CO88: 0.77 | CP88: 0.946 | CQ88: 0.36967483 | CR88: 0 | CS88: 115.52339 | CT88: 0.001 | CU88: 0.59 | CV88: 16.21 | CW88: 3.8018296 | CX88: 1.9009148 | CY88: 0.95045741 | CZ88: 210.05109
A89: Nariño | B89: 2021 | C89: 93.264191 | D89: 71.544247 | E89: 57.18 | F89: 0.23287036 | G89: 0.013590407 | H89: 52.44 | I89: 45.64 | J89: 94.25715 | K89: 0.032227976 | L89: 35.125557 | M89: 0.54039319 | N89: 13.930136 | O89: 0.58371801 | P89: 343.22286 | Q89: 0.58059914 | R89: 0.72935894 | S89: 0.30777449 | T89: 0.13601677 | U89: 98.593436 | V89: 522.06252 | W89: 0.42231554 | X89: 57.703742 | Y89: 2.825487 | Z89: 0.77432151 | AA89: 6.838976 | AB89: 0.34237105 | AC89: 0 | AD89: 277.18776 | AE89: 300.90599 | AF89: 113696 | AG89: 0.2362 | AH89: 0.058788285 | AI89: 13.921462 | AJ89: 0.26298032 | AK89: 0.53005205 | AL89: 2343.789 | AM89: 274.58 | AN89: 1.3333 | AO89: 0.0010403391 | AP89: 6.6795735 | AQ89: 0.10834985 | AR89: 0.34683493 | AS89: 2.6189437 | AT89: 11.635938 | AU89: 0.8855227 | AV89: 0.86026768 | AW89: 86.67 | AX89: 11.259205 | AY89: 103.46297 | AZ89: 76.8 | BA89: 22.521184 | BB89: 6.5980922 | BC89: 1.4001371 | BD89: 162.29809 | BE89: 0.5302 | BF89: 0.7987 | BG89: 0.6944 | BH89: 0.38 | BI89: 0.0145 | BJ89: 252.10576 | BK89: 255 | BL89: 0.56931114 | BM89: 18.741465 | BN89: 24.202 | BO89: 69.369 | BP89: 3.87 | BQ89: 139.88539 | BR89: 7.037203 | BS89: 36.065337 | BT89: 11.330049 | BU89: 39.161893 | BV89: 0.34518748 | BW89: 0.036423841 | BX89: 0.0606729 | BY89: 0.490331 | BZ89: 4.06 | CA89: 2.68 | CB89: 0.050206327 | CC89: 64.255156 | CD89: 8.9652749 | CE89: 13.926189 | CF89: 8.7804792 | CG89: 0.72083369 | CH89: 32.136314 | CI89: 45.381317 | CJ89: 0.011208025 | CK89: 0.31739728 | CL89: 30.408409 | CM89: 26.634 | CN89: 5.6049285 | CO89: 0.131 | CP89: 0.211 | CQ89: 0.4803495 | CR89: 0.18013106 | CS89: 141.10267 | CT89: 0.004 | CU89: 0.58 | CV89: 18.39 | CW89: 0 | CX89: 0 | CY89: 7.9804491 | CZ89: 171.27272
A90: Norte de Santander | B90: 2021 | C90: 110.93117 | D90: 71.745998 | E90: 52.9725 | F90: 0.26018355 | G90: 0.015961548 | H90: 52.69 | I90: 59.43 | J90: 95.905705 | K90: 0.074770124 | L90: 35.616918 | M90: 0.9275239 | N90: 18.797818 | O90: 0.5840393 | P90: 522.44898 | Q90: 0.64516129 | R90: 0.83973988 | S90: 0.76042464 | T90: 0.63828633 | U90: 99.352597 | V90: 502.62422 | W90: 0.78272646 | X90: 71.175549 | Y90: 5.1443116 | Z90: 0.57913224 | AA90: 24.553536 | AB90: 1.8334195 | AC90: 0.56054417 | AD90: 220.78523 | AE90: 199.44724 | AF90: 380655 | AG90: 0.2612 | AH90: 0.098923444 | AI90: 19.002612 | AJ90: 0.32110199 | AK90: 0.67936757 | AL90: 5387.901 | AM90: 632.468 | AN90: 1.7667 | AO90: 0.0045756764 | AP90: 12.731783 | AQ90: 0.33724785 | AR90: 0.40352017 | AS90: 3.6228721 | AT90: 9.685 | AU90: 0.97770701 | AV90: 0.99840319 | AW90: 79.12 | AX90: 12.022419 | AY90: 89.84726 | AZ90: 75.66 | BA90: 23.988283 | BB90: 4.9054846 | BC90: 1.4142062 | BD90: 128.36931 | BE90: 0.6442 | BF90: 0.9115 | BG90: 0.7609 | BH90: 0.4187 | BI90: 0.0325 | BJ90: 258.12363 | BK90: 261 | BL90: 0.5241579 | BM90: 27.065691 | BN90: 38.294 | BO90: 109.368 | BP90: 9.956 | BQ90: 141.81258 | BR90: 7.2390069 | BS90: 8.5838991 | BT90: 11.213279 | BU90: 54.267516 | BV90: 0.31979892 | BW90: 0.010693215 | BX90: 0.0115219 | BY90: 0.0073139 | BZ90: 8.98 | CA90: 4.89 | CB90: 0.040040419 | CC90: 55.039646 | CD90: 21.11864 | CE90: 18.637343 | CF90: 9.631823 | CG90: 0.69509321 | CH90: 36.562667 | CI90: 63.296445 | CJ90: 0.015366283 | CK90: 0.33908503 | CL90: 30.359926 | CM90: 27.821 | CN90: 10.342427 | CO90: 0.086 | CP90: 0.344 | CQ90: 1.7932129 | CR90: 0.37100956 | CS90: 233.11767 | CT90: 0.002 | CU90: 0.72 | CV90: 19.56 | CW90: 7.0271285 | CX90: 2.5553195 | CY90: 1.2776597 | CZ90: 394.15803
A91: Putumayo | B91: 2021 | C91: 91.189349 | D91: 79.979075 | E91: 47.681429 | F91: 0.11199831 | G91: 0.010654699 | H91: 23.1 | I91: 91.03 | J91: 99.452041 | K91: 0.12615067 | L91: 44.397793 | M91: 0.27406045 | N91: 22.747018 | O91: 0.58851431 | P91: 356.30769 | Q91: 0.69325153 | R91: 0.48086179 | S91: 0.6449286 | T91: 0.55798597 | U91: 87.902486 | V91: 733.04824 | W91: 0.4846631 | X91: 114.64613 | Y91: 1.629781 | Z91: 0.93685632 | AA91: 14.319659 | AB91: 0.20996584 | AC91: 0.39617225 | AD91: 431.28358 | AE91: 376.28691 | AF91: 10442 | AG91: 0.0106 | AH91: 0.047150744 | AI91: 5.547946 | AJ91: 0.20190179 | AK91: 0.44458164 | AL91: 1082.634 | AM91: 191.565 | AN91: 0.7143 | AO91: 0.004323488 | AP91: 19.182363 | AQ91: 0.11818674 | AR91: 0.30505449 | AS91: 4.7140986 | AT91: 8.1923077 | AU91: 0.96045765 | AV91: 0.98052498 | AW91: 80.78 | AX91: 9.3885963 | AY91: 91.596061 | AZ91: 74.13 | BA91: 22.294938 | BB91: 5.1005136 | BC91: 0.56933236 | BD91: 148.54077 | BE91: 0.4843 | BF91: 0.8113 | BG91: 0.7212 | BH91: 0.3716 | BI91: 0.0539 | BJ91: 242.76886 | BK91: 254 | BL91: 0.55156951 | BM91: 22.108464 | BN91: 4.865 | BO91: 13.003 | BP91: 11.201 | BQ91: 131.27901 | BR91: 0 | BS91: 5.4884547 | BT91: 2.3281596 | BU91: 0.17605634 | BV91: 0.35554172 | BW91: 0.0083194676 | BX91: 0.0212573 | BY91: 0.0566484 | BZ91: 8.6 | CA91: 3.88 | CB91: 0.023689878 | CC91: 55.76153 | CD91: 30.20067 | CE91: 29.020125 | CF91: 9.1185758 | CG91: 0.44720184 | CH91: 29.288416 | CI91: 52.907401 | CJ91: 0.0045601458 | CK91: 0.18175813 | CL91: 28.707706 | CM91: 27.175 | CN91: 28.594464 | CO91: 0.707 | CP91: 1 | CQ91: 0 | CR91: 0 | CS91: 0 | CT91: 0.002 | CU91: 0 | CV91: 0 | CW91: 0 | CX91: 2.8267832 | CY91: 0 | CZ91: 90.457063
A92: Quindío | B92: 2021 | C92: 119.72882 | D92: 82.125734 | E92: 82.50875 | F92: 0.37745141 | G92: 0.013860295 | H92: 43.23 | I92: 47.095 | J92: 99.822784 | K92: 0.22895838 | L92: 33.073026 | M92: 0 | N92: 12.289431 | O92: 0.64472632 | P92: 462.2 | Q92: 0.46605197 | R92: 0.9733149 | S92: 0.81711402 | T92: 0.87106836 | U92: 99.648786 | V92: 604.19878 | W92: 0.91007966 | X92: 34.175466 | Y92: 10.148076 | Z92: 0.53843903 | AA92: 47.84203 | AB92: 14.347967 | AC92: 0.35701874 | AD92: 445.65568 | AE92: 396.02252 | AF92: 157165 | AG92: 0.1516 | AH92: 0.18259211 | AI92: 11.650683 | AJ92: 0.39758348 | AK92: 0.73075957 | AL92: 6341.862 | AM92: 628.578 | AN92: 1.1429 | AO92: 1.0840108e-05 | AP92: 18.688721 | AQ92: 0.41620002 | AR92: 0.15137541 | AS92: 1.5713662 | AT92: 14.5 | AU92: 0.95487552 | AV92: 0.92339286 | AW92: 91.17 | AX92: 10.674157 | AY92: 37.453184 | AZ92: 75.39 | BA92: 29.67792 | BB92: 8.2008967 | BC92: 4.8860789 | BD92: 232.23409 | BE92: 0.6976 | BF92: 0.934 | BG92: 0.8785 | BH92: 0.5361 | BI92: 0.0394 | BJ92: 259.66929 | BK92: 254 | BL92: 0.58407543 | BM92: 23.418544 | BN92: 40.336 | BO92: 133.977 | BP92: 22.683 | BQ92: 144.59111 | BR92: 7.1810089 | BS92: 50.176629 | BT92: 22.780783 | BU92: 73.383018 | BV92: 0.51135371 | BW92: 0.029547553 | BX92: 0.0394386 | BY92: 0.0616701 | BZ92: 9.47 | CA92: 5.79 | CB92: 0.05842138 | CC92: 53.586801 | CD92: 23.266103 | CE92: 30.353327 | CF92: 9.1823995 | CG92: 0.42753762 | CH92: 32.993876 | CI92: 79.129604 | CJ92: 0.021662915 | CK92: 0.38807147 | CL92: 29.697011 | CM92: 27.627 | CN92: 13.435257 | CO92: 0.18 | CP92: 0.833 | CQ92: 1.0843615 | CR92: 0 | CS92: 285.54853 | CT92: 0.002 | CU92: 0.99 | CV92: 19.86 | CW92: 25.554207 | CX92: 9.1265025 | CY92: 10.951803 | CZ92: 658.93348
A93: Risaralda | B93: 2021 | C93: 130.25197 | D93: 74.700247 | E93: 73.806667 | F93: 0.436903 | G93: 0.010179489 | H93: 62.61 | I93: 54.82 | J93: 92.255357 | K93: 0.2062096 | L93: 21.084797 | M93: 0.103866 | N93: 11.632992 | O93: 0.6359936 | P93: 612.23469 | Q93: 0.61227024 | R93: 0.95860807 | S93: 0.77168792 | T93: n/a | U93: 99.768854 | V93: 590.06948 | W93: 0.81214286 | X93: 46.734473 | Y93: 10.75244 | Z93: 0.80515763 | AA93: 21.736037 | AB93: 5.0548309 | AC93: 0.41869355 | AD93: 600.26857 | AE93: 530.17635 | AF93: 597568 | AG93: 0.0672 | AH93: 0.18766397 | AI93: 14.598027 | AJ93: 0.45144131 | AK93: 0.77874369 | AL93: 10002.814 | AM93: 1579.815 | AN93: 1.6452 | AO93: 0.00012257106 | AP93: 26.783398 | AQ93: 0.45800376 | AR93: 0.15176719 | AS93: 2.4443474 | AT93: 7.7714286 | AU93: 0.99047975 | AV93: 0.98752193 | AW93: 89.11 | AX93: 9.4796289 | AY93: 40.338846 | AZ93: 76.83 | BA93: 34.058197 | BB93: 10.190726 | BC93: 6.703637 | BD93: 183.84281 | BE93: 0.6978 | BF93: 0.9557 | BG93: 0.8625 | BH93: 0.5047 | BI93: 0.0499 | BJ93: 259.38986 | BK93: 256 | BL93: 0.47812906 | BM93: 22.811607 | BN93: 42.605 | BO93: 237.583 | BP93: 18.324 | BQ93: 145.44991 | BR93: 8.5882353 | BS93: 47.039635 | BT93: 25.36676 | BU93: 49.93629 | BV93: 0.58413926 | BW93: 0.053558844 | BX93: 0.0247299 | BY93: 0.0395242 | BZ93: 8.83 | CA93: 7.69 | CB93: 0.067081417 | CC93: 58.831957 | CD93: 14.607105 | CE93: 35.333631 | CF93: 3.9948094 | CG93: 0.35414432 | CH93: 28.099691 | CI93: 81.274288 | CJ93: 0.027287731 | CK93: 0.44223487 | CL93: 30.494069 | CM93: 27.975 | CN93: 18.896986 | CO93: 0.138 | CP93: 0.213 | CQ93: 5.4010318 | CR93: 0.20773199 | CS93: 336.52583 | CT93: 0.003 | CU93: 0.93 | CV93: 30.23 | CW93: 25.196559 | CX93: 12.59828 | CY93: 19.947276 | CZ93: 1154.8423
A94: Archipiélago de San Andrés | B94: 2021 | C94: 122.913 | D94: 39.860804 | E94: 71.24 | F94: 0.30304383 | G94: 0.035239379 | H94: 48.41 | I94: 55.95 | J94: 78.666169 | K94: 0.26731333 | L94: 61.391321 | M94: 0 | N94: 21.002294 | O94: 0.56645937 | P94: 255.90476 | Q94: 0.43589744 | R94: 0.30420876 | S94: - | T94: n/a | U94: 100 | V94: 529.25032 | W94: 0.19263593 | X94: 73.217887 | Y94: 15.958075 | Z94: 0.68662587 | AA94: 35.80127 | AB94: 16.326723 | AC94: 0.029783031 | AD94: NA | AE94: - | AF94: 701340 | AG94: 0.2682 | AH94: 0.065522871 | AI94: 1.6868261 | AJ94: 0.36909532 | AK94: 0.77338454 | AL94: 5628.924 | AM94: 216.497 | AN94: 0.4444 | AO94: 0 | AP94: 2.2490909 | AQ94: 0.41342061 | AR94: 0.1304659 | AS94: 2.4879965 | AT94: 8.4 | AU94: 0.90470723 | AV94: 0.8933177 | AW94: 90.9 | AX94: 11.703511 | AY94: 260.07802 | AZ94: 74.81 | BA94: 57.283596 | BB94: 10.96087 | BC94: 2.1367173 | BD94: 222.94743 | BE94: 0.7312 | BF94: 0.9097 | BG94: 0.8213 | BH94: 0.4997 | BI94: 0.0208 | BJ94: 238 | BK94: 247 | BL94: 0.53005464 | BM94: 30.907104 | BN94: 1.71 | BO94: 12.804 | BP94: 27.257 | BQ94: 128.35699 | BR94: 29.72973 | BS94: 3.7371911 | BT94: 32.258065 | BU94: 90 | BV94: 0.66183575 | BW94: 0 | BX94: 0.243614 | BY94: 0.022234 | BZ94: 17.9 | CA94: 15.21 | CB94: 0.078431373 | CC94: 61.594125 | CD94: 21.824696 | CE94: - | CF94: - | CG94: 0.31264641 | CH94: 47.49606 | CI94: 109.55174 | CJ94: 0.0033692175 | CK94: 0.26225009 | CL94: 28.142948 | CM94: 19.905 | CN94: 1.7024652 | CO94: 0.267 | CP94: 0.246 | CQ94: 0 | CR94: 0 | CS94: 96.933665 | CT94: 0.004 | CU94: 0 | CV94: 0 | CW94: 16.004609 | CX94: 0 | CY94: 0 | CZ94: 1984.5716
A95: Santander | B95: 2021 | C95: 112.89371 | D95: 68.849706 | E95: 78.63375 | F95: 0.31552969 | G95: 0.0082273527 | H95: 39.12 | I95: 55.11 | J95: 94.428537 | K95: 0.084975319 | L95: 12.663175 | M95: 0.043817216 | N95: 8.938712 | O95: 0.5261118 | P95: 431.33956 | Q95: 0.50583756 | R95: 0.82034833 | S95: 0.89264806 | T95: 0.35765054 | U95: 99.330587 | V95: 508.46148 | W95: 0.7372849 | X95: 70.082549 | Y95: 5.135272 | Z95: 0.68521442 | AA95: 26.750848 | AB95: 1.9992468 | AC95: 0.60827832 | AD95: 381.1158 | AE95: 378.48865 | AF95: 606608 | AG95: 0.1916 | AH95: 0.14676748 | AI95: 17.055198 | AJ95: 0.39957684 | AK95: 0.73688093 | AL95: 6324.948 | AM95: 884.711 | AN95: 2.439 | AO95: 0.00089858205 | AP95: 26.271504 | AQ95: 0.47548847 | AR95: 0.15670601 | AS95: 5.1069402 | AT95: 11.477011 | AU95: 0.89297232 | AV95: 0.8642367 | AW95: 89.23 | AX95: 7.7771287 | AY95: 73.024682 | AZ95: 78.44 | BA95: 43.331085 | BB95: 9.2015079 | BC95: 4.3699126 | BD95: 189.59709 | BE95: 0.6764 | BF95: 0.9458 | BG95: 0.847 | BH95: 0.4996 | BI95: 0.0301 | BJ95: 270.72616 | BK95: 268 | BL95: 0.55030367 | BM95: 21.257856 | BN95: 37.036 | BO95: 418.933 | BP95: 21.773 | BQ95: 149.68856 | BR95: 8.1490531 | BS95: 36.622348 | BT95: 28.459219 | BU95: 55.333333 | BV95: 0.5093149 | BW95: 0.036775571 | BX95: 0.0123496 | BY95: 0.0040818 | BZ95: 10.72 | CA95: 7.98 | CB95: 0.056709529 | CC95: 60.789603 | CD95: 17.824106 | CE95: 32.959187 | CF95: 7.7152896 | CG95: 0.45576016 | CH95: 56.165298 | CI95: 87.419977 | CJ95: 0.011799265 | CK95: 0.25513423 | CL95: 31.851169 | CM95: 28.25 | CN95: 7.555768 | CO95: 0.15 | CP95: 0.217 | CQ95: 3.7682805 | CR95: 0.35053772 | CS95: 380.33343 | CT95: 0.016 | CU95: 1.09 | CV95: 19.36 | CW95: 14.74803 | CX95: 4.02219 | CY95: 7.15056 | CZ95: 736.95459
A96: Sucre | B96: 2021 | C96: 92.030256 | D96: 76.325314 | E96: 43.035 | F96: 0.21724833 | G96: 0.01316854 | H96: 51.01 | I96: 44.185 | J96: 98.13895 | K96: 0.13624799 | L96: 15.148136 | M96: 0 | N96: 9.5727805 | O96: 0.51721215 | P96: 378.06522 | Q96: 0.64041995 | R96: 0.84865089 | S96: 0.92564559 | T96: n/a | U96: 93.09205 | V96: 513.35209 | W96: 0.53683585 | X96: 38.32488 | Y96: 3.2612623 | Z96: 0.85864195 | AA96: 8.9310886 | AB96: 0.77768618 | AC96: 0.5958775 | AD96: 405.27209 | AE96: 359.92444 | AF96: 21306 | AG96: 0.1104 | AH96: 0.056664054 | AI96: 16.136551 | AJ96: 0.19657754 | AK96: 0.48424301 | AL96: 1407.194 | AM96: 330.685 | AN96: 1.24 | AO96: 0.00021617661 | AP96: 1.4390718 | AQ96: 0.33894156 | AR96: 0.08472125 | AS96: 2.1824531 | AT96: 9.3384615 | AU96: 0.99973024 | AV96: 1 | AW96: 86.92 | AX96: 12.597683 | AY96: 80.840744 | AZ96: 76.33 | BA96: 20.054285 | BB96: 5.5073044 | BC96: 1.6654701 | BD96: 210.60117 | BE96: 0.6835 | BF96: 0.9494 | BG96: 0.7635 | BH96: 0.419 | BI96: 0.03 | BJ96: 237 | BK96: 241 | BL96: 0.33283607 | BM96: 25.753854 | BN96: 25.583 | BO96: 31.863 | BP96: 5.296 | BQ96: 135.49383 | BR96: 5.2719665 | BS96: 6.5409948 | BT96: 10.357815 | BU96: 54.021448 | BV96: 0.25863284 | BW96: 0.0075244545 | BX96: 0.019493 | BY96: 0.0500241 | BZ96: 4.47 | CA96: 2.74 | CB96: 0.043093497 | CC96: 61.758316 | CD96: 14.118715 | CE96: 17.141904 | CF96: 9.7954648 | CG96: 0.69105323 | CH96: 29.700632 | CI96: 34.811981 | CJ96: 0.0057352664 | CK96: 0.23503688 | CL96: 29.148321 | CM96: 28.347 | CN96: 48.852794 | CO96: 0.289 | CP96: 0.982 | CQ96: 1.2623447 | CR96: 0 | CS96: 173.57239 | CT96: 0.003 | CU96: 0.57 | CV96: 30.84 | CW96: 1.0764448 | CX96: 0 | CY96: 0 | CZ96: 77.504026
A97: Tolima | B97: 2021 | C97: 122.21172 | D97: 67.077971 | E97: 59.125 | F97: 0.25903801 | G97: 0.010480268 | H97: 39.94 | I97: 92.31 | J97: 93.558366 | K97: 0.15838056 | L97: 16.90863 | M97: 0.22151044 | N97: 17.794672 | O97: 0.52809526 | P97: 381.195 | Q97: 0.69135802 | R97: 0.86105012 | S97: 0.77838968 | T97: 0.068414437 | U97: 98.678975 | V97: 572.81767 | W97: 0.69780066 | X97: 61.300759 | Y97: 3.4740557 | Z97: 0.86963769 | AA97: 66.679071 | AB97: 3.8326967 | AC97: 0.34621177 | AD97: 381.68013 | AE97: 349.65179 | AF97: 29106 | AG97: 0.1168 | AH97: 0.1139598 | AI97: 16.334804 | AJ97: 0.32645871 | AK97: 0.67995856 | AL97: 4561.808 | AM97: 887.904 | AN97: 1.9231 | AO97: 0.00011374247 | AP97: 12.602562 | AQ97: 0.37163971 | AR97: 0.19389642 | AS97: 3.7974684 | AT97: 4.1425532 | AU97: 0.97315168 | AV97: 0.94520628 | AW97: 88.86 | AX97: 8.2862524 | AY97: 87.884495 | AZ97: 76.73 | BA97: 26.100831 | BB97: 6.0820251 | BC97: 2.0894237 | BD97: 169.23397 | BE97: 0.7223 | BF97: 0.9758 | BG97: 0.8503 | BH97: 0.4877 | BI97: 0.037 | BJ97: 246.71335 | BK97: 247.97215 | BL97: 0.52635793 | BM97: 23.001335 | BN97: 23.638 | BO97: 101.849 | BP97: 18.259 | BQ97: 140.58958 | BR97: 11.43809 | BS97: 39.080053 | BT97: 14.426282 | BU97: 46.3125 | BV97: 0.43840074 | BW97: 0.0097765363 | BX97: 0.0193086 | BY97: 0.0520908 | BZ97: 8.4 | CA97: 4.82 | CB97: 0.034205231 | CC97: 56.142136 | CD97: 22.17548 | CE97: 25.308911 | CF97: 10.701812 | CG97: 0.43975959 | CH97: 50.810345 | CI97: 75.964148 | CJ97: 0.0096904399 | CK97: 0.32626472 | CL97: 30.732291 | CM97: 26.272 | CN97: 1.6484299 | CO97: 0.294 | CP97: 0.255 | CQ97: 1.0337154 | CR97: 0 | CS97: 165.39446 | CT97: 0.003 | CU97: 1.58 | CV97: 18.97 | CW97: 3.7444404 | CX97: 1.4977762 | CY97: 14.977762 | CZ97: 417.13067
A98: Valle del Cauca | B98: 2021 | C98: 164.37937 | D98: 74.622173 | E98: 68.97 | F98: 0.45093979 | G98: 0.010624846 | H98: 60.26 | I98: 87.21 | J98: 98.214253 | K98: 0.2937399 | L98: 48.6647 | M98: 0.50192291 | N98: 23.153922 | O98: 0.57687512 | P98: 525.83102 | Q98: 0.38549139 | R98: 0.94829051 | S98: 0.78262697 | T98: 0.054538367 | U98: 99.407516 | V98: 552.67711 | W98: 0.88695367 | X98: 22.890994 | Y98: 4.6596387 | Z98: 0.74228067 | AA98: 17.258721 | AB98: 3.5720853 | AC98: 0.36267205 | AD98: 394.62171 | AE98: 379.4546 | AF98: 1874335 | AG98: 0.3928 | AH98: 0.17362975 | AI98: 18.354622 | AJ98: 0.47339746 | AK98: 0.80063697 | AL98: 4101.176 | AM98: 671.683 | AN98: 1.9697 | AO98: 9.2140921e-05 | AP98: 25.262237 | AQ98: 0.55139035 | AR98: 0.17406294 | AS98: 6.8965517 | AT98: 18.357143 | AU98: 0.96064843 | AV98: 0.96493846 | AW98: 89.68 | AX98: 9.447151 | AY98: 72.01864 | AZ98: 75.75 | BA98: 40.446253 | BB98: 9.3070601 | BC98: 4.5416306 | BD98: 183.70379 | BE98: 0.5595 | BF98: 0.7671 | BG98: 0.7269 | BH98: 0.4195 | BI98: 0.0392 | BJ98: 256.30779 | BK98: 250 | BL98: 0.36120285 | BM98: 26.952373 | BN98: 30.707 | BO98: 160.825 | BP98: 14.195 | BQ98: 145.92994 | BR98: 11.95994 | BS98: 41.581463 | BT98: 27.155528 | BU98: 47.413475 | BV98: 0.54888057 | BW98: 0.056931998 | BX98: 0.011935 | BY98: 0.0069854 | BZ98: 10.98 | CA98: 9.27 | CB98: 0.067310896 | CC98: 61.674114 | CD98: 20.916255 | CE98: 34.148063 | CF98: 12.98851 | CG98: 0.40410245 | CH98: 46.148912 | CI98: 80.685613 | CJ98: 0.024065281 | CK98: 0.42869836 | CL98: 32.326449 | CM98: 29.53 | CN98: 18.0381 | CO98: 0.116 | CP98: 0.027 | CQ98: 3.6880423 | CR98: 0.3709865 | CS98: 287.1872 | CT98: 0.005 | CU98: 1.14 | CV98: 23.36 | CW98: 14.644641 | CX98: 5.5472125 | CY98: 7.7660976 | CZ98: 1271.643
A99: Vaupés | B99: 2021 | C99: 93.336924 | D99: 59.515174 | E99: 42.608571 | F99: 0.054990285 | G99: 0.025444402 | H99: 44.76 | I99: 93.02 | J99: 96.940973 | K99: 0.0012357121 | L99: 9.261832 | M99: 0 | N99: 6.946374 | O99: n/a | P99: n/a | Q99: 0 | R99: 0.24951884 | S99: - | T99: n/a | U99: 49.340086 | V99: 563.14459 | W99: 0.1934529 | X99: - | Y99: - | Z99: - | AA99: 4.8045753 | AB99: 0.0038330101 | AC99: 1 | AD99: NA | AE99: - | AF99: 11270 | AG99: 0.045 | AH99: 0.0022157629 | AI99: 4.0081287 | AJ99: 0.11855972 | AK99: 0.19856341 | AL99: 20.687 | AM99: 0 | AN99: 0.25 | AO99: 0.00038034543 | AP99: 11.678898 | AQ99: 0.38515979 | AR99: 0.068484652 | AS99: 0.91663029 | AT99: 5.4333333 | AU99: 0.8996328 | AV99: 0.76679341 | AW99: 36.27 | AX99: 22.988506 | AY99: 0 | AZ99: 64.5 | BA99: 13.287785 | BB99: 1.9341388 | BC99: 0.40189897 | BD99: 71.779198 | BE99: 0.2263 | BF99: 0.5502 | BG99: 0.2999 | BH99: 0.1308 | BI99: 0.0304 | BJ99: 212 | BK99: 223 | BL99: 0.18258427 | BM99: 26.876404 | BN99: 0.745 | BO99: 42.134 | BP99: 2.193 | BQ99: 130.66667 | BR99: 0 | BS99: 0 | BT99: 2.8985507 | BU99: 0 | BV99: 0.30693069 | BW99: 0.011695906 | BX99: 0.56299069 | BY99: 0.0581058 | BZ99: 3.8 | CA99: 1.34 | CB99: 0.016666667 | CC99: 55.488541 | CD99: 17.193017 | CE99: 40.308974 | CF99: 3.5237339 | CG99: 0.53084482 | CH99: 21.917529 | CI99: 26.143025 | CJ99: 0.0093824894 | CK99: 0.027323422 | CL99: 26.437146 | CM99: 15.303 | CN99: 0.016580934 | CO99: 0.977 | CP99: 0.977 | CQ99: 0 | CR99: 0 | CS99: 0 | CT99: 0.02268 | CU99: 0 | CV99: 0 | CW99: 0 | CX99: 0 | CY99: 0 | CZ99: 0
A100: Vichada | B100: 2021 | C100: 87.137365 | D100: 62.27916 | E100: 36.301429 | F100: 0.12789029 | G100: 0.030473047 | H100: 51.26 | I100: 51.28 | J100: 95.321603 | K100: 0.0042305658 | L100: 14.757457 | M100: 0 | N100: 9.5489427 | O100: n/a | P100: n/a | Q100: 0 | R100: 0.33465532 | S100: - | T100: n/a | U100: 39.252178 | V100: 432.06475 | W100: 0.0094885172 | X100: 86.925741 | Y100: 0.095906905 | Z100: 0.67405437 | AA100: 0 | AB100: 0 | AC100: 0 | AD100: NA | AE100: - | AF100: 16325 | AG100: 0.0124 | AH100: 0.010533549 | AI100: 1.4777066 | AJ100: 0.067020843 | AK100: 0.1801922 | AL100: 323.239 | AM100: 59.544 | AN100: 1 | AO100: 0.00055735121 | AP100: 5.691785 | AQ100: 0.3746625 | AR100: 0.15083713 | AS100: 0 | AT100: 7.925 | AU100: 0.93103448 | AV100: 0.68979131 | AW100: 28.99 | AX100: 29.411765 | AY100: 326.79739 | AZ100: 65.93 | BA100: 27.946202 | BB100: 3.6646075 | BC100: 0.47592305 | BD100: 72.919199 | BE100: 0.3598 | BF100: 0.5919 | BG100: 0.25 | BH100: 0.0873 | BI100: 0.0763 | BJ100: 225 | BK100: 237 | BL100: 0.2385466 | BM100: 32.894155 | BN100: 1.353 | BO100: 1.808 | BP100: 3.42 | BQ100: 126.77778 | BR100: 0 | BS100: 0 | BT100: 6.6666667 | BU100: 0 | BV100: 0.53974895 | BW100: 0.026315789 | BX100: 0.1869422 | BY100: 0.0385288 | BZ100: 3.63 | CA100: 1.69 | CB100: 0.02617801 | CC100: 63.929406 | CD100: 28.116283 | CE100: 27.382233 | CF100: 8.0717375 | CG100: 0.47721827 | CH100: 21.83908 | CI100: 26.609195 | CJ100: 0.0040496516 | CK100: 0.10726655 | CL100: 27.25307 | CM100: 0 | CN100: 0.47617416 | CO100: 1 | CP100: 1 | CQ100: 0 | CR100: 0 | CS100: 8.680857 | CT100: 0.003 | CU100: 0 | CV100: 0 | CW100: 0 | CX100: 0 | CY100: 0 | CZ100: 0
...

Sheet Valor_normalizado
A1: Departamento | B1: Año IDC | C1: INS-1-1 | D1: INS-1-2 | E1: INS-1-3 | F1: INS-1 | G1: INS-2-1 | H1: INS-2-2 | I1: INS-2-3 | J1: INS-2 | K1: INS-3-1 | L1: INS-3-2 | M1: INS-3-3 | N1: INS-3 | O1: INS-4-1 | P1: INS-4-2 | Q1: INS-4-3 | R1: INS-4-4 | S1: INS-4-5 | T1: INS-4-6 | U1: INS-4 | V1: INS | W1: INF-1-1 | X1: INF-1-2 | Y1: INF-1-3 | Z1: INF-1-4 | AA1: INF-1-5 | AB1: INF-1-6 | AC1: INF-1 | AD1: INF-2-1 | AE1: INF-2-2 | AF1: INF-2-3 | AG1: INF-2-4 | AH1: INF-2-5 | AI1: INF-2-6 | AJ1: INF-2 | AK1: INF-3-1 | AL1: INF-3-2 | AM1: INF-3-3 | AN1: INF-3-4 | AO1: INF-3 | AP1: INF | AQ1: TIC-1-1 | AR1: TIC-1-2 | AS1: TIC-1-3 | AT1: TIC-1-4 | AU1: TIC-1 | AV1: TIC-2-1 | AW1: TIC-2-2 | AX1: TIC-2-3 | AY1: TIC-2 | AZ1: TIC | BA1: AMB-1-1 | BB1: AMB-1-2 | BC1: AMB-1-3 | BD1: AMB-1-4 | BE1: AMB-1 | BF1: AMB-2-1 | BG1: AMB-2-2 | BH1: AMB-2 | BI1: AMB | BJ1: SAL-1-1 | BK1: SAL-1-2 | BL1: SAL-1-3 | BM1: SAL-1 | BN1: SAL-2-1 | BO1: SAL-2-2 | BP1: SAL-2-3 | BQ1: SAL-2 | BR1: SAL-3-1 | BS1: SAL-3-2 | BT1: SAL-3-3 | BU1: SAL-3-4 | BV1: SAL-3 | BW1: SAL | BX1: EDU-1-1 | BY1: EDU-1-2 | BZ1: EDU-1-3 | CA1: EDU-1-4 | CB1: EDU-1-5 | CC1: EDU-1 | CD1: EDU-2-1 | CE1: EDU-2-2 | CF1: EDU-2-3 | CG1: EDU-2-4 | CH1: EDU-2 | CI1: EDU | CJ1: EDS-1-1 | CK1: EDS-1-2 | CL1: EDS-1-3 | CM1: EDS-1 | CN1: EDS-2-1 | CO1: EDS-2-2 | CP1: EDS-2-3 | CQ1: EDS-2-4 | CR1: EDS-2 | CS1: EDS-3-1 | CT1: EDS-3-2 | CU1: EDS-3 | CV1: EDS | CW1: NEG-1-1 | CX1: NEG-1-2 | CY1: NEG-1-3 | CZ1: NEG-1 | DA1: NEG-2-1 | DB1: NEG-2-2 | DC1: NEG-2-3 | DD1: NEG-2 | DE1: NEG | DF1: LAB-1-1 | DG1: LAB-1-2 | DH1: LAB-1-3 | DI1: LAB-1-4 | DJ1: LAB-1-5 | DK1: LAB | DL1: FIN-1-1 | DM1: FIN-1-2 | DN1: FIN-1-3 | DO1: FIN-1-4 | DP1: FIN | DQ1: TAM-1-1 | DR1: TAM-1 | DS1: TAM-2-1 | DT1: TAM-2-2 | DU1: TAM-2 | DV1: TAM | DW1: SOF-1-1 | DX1: SOF-1-2 | DY1: SOF | DZ1: INN-1-1 | EA1: INN-1-2 | EB1: INN-1-3 | EC1: INN-1-4 | ED1: INN-1-5 | EE1: INN-1-6 | EF1: INN-1 | EG1: INN-2-1 | EH1: INN-2-2 | EI1: INN-2-3 | EJ1: INN-2-4 | EK1: INN-2 | EL1: INN | EM1: IDC
A2: Amazonas | B2: 2019 | C2: 3.577934 | D2: 8.499939 | E2: 0.43556492 | F2: 4.171146 | G2: 0.46150776 | H2: 3.0771104 | I2: 3.5775996 | J2: 2.3720726 | K2: 0.62533596 | L2: 7.3770469 | M2: 0 | N2: 2.667461 | O2: 8.4136039 | P2: 10 | Q2: 9.612593 | R2: NA | S2: NA | T2: 6.6666667 | U2: 8.6732159 | V2: 4.4709739 | W2: 0.83283709 | X2: NA | Y2: NA | Z2: 8.0715739 | AA2: 6.4163966 | AB2: 1.7771291 | AC2: 4.2744842 | AD2: 0.83617567 | AE2: 0 | AF2: 8.6619913 | AG2: 1.7469476 | AH2: 0.0042060525 | AI2: 2.8042328 | AJ2: 2.3422589 | AK2: NA | AL2: NA | AM2: 0.072431779 | AN2: 2.282 | AO2: 1.1772159 | AP2: 2.5979863 | AQ2: 0.14061513 | AR2: 0.030616025 | AS2: 1.0417018 | AT2: 2.4363296 | AU2: 0.91231564 | AV2: 0.40356885 | AW2: 0.18475486 | AX2: 1.8163986 | AY2: 0.8015741 | AZ2: 0.85694487 | BA2: 9.8918668 | BB2: 5.3319266 | BC2: 5.3153221 | BD2: 7.2575242 | BE2: 6.9491599 | BF2: 4.2016807 | BG2: 4.7415796 | BH2: 4.4716301 | BI2: 5.710395 | BJ2: 5.6842715 | BK2: 7.0027289 | BL2: 4.6478385 | BM2: 5.7782796 | BN2: 6.4405026 | BO2: 8.1854282 | BP2: 5.1704545 | BQ2: 6.5987951 | BR2: 4.7477271 | BS2: 4.038217 | BT2: 1.2170316 | BU2: 6.3241717 | BV2: 4.0817869 | BW2: 5.4862872 | BX2: 3.872679 | BY2: 5.5519282 | BZ2: 5.5859496 | CA2: 4.4733985 | CB2: 5.5102892 | CC2: 4.9988489 | CD2: 3.3195274 | CE2: 3.3377473 | CF2: 1.9181034 | CG2: 5.3626545 | CH2: 3.4845082 | CI2: 4.2416785 | CJ2: 0.55286565 | CK2: 0.46926369 | CL2: 0.90217838 | CM2: 0.64143591 | CN2: 6.215718 | CO2: 8.2124817 | CP2: 2.1228701 | CQ2: 1.7358741 | CR2: 4.571736 | CS2: 0 | CT2: 4.2423551 | CU2: 2.1211775 | CV2: 2.4447831 | CW2: 3.4214717 | CX2: 7.7777291 | CY2: 9.7928742 | CZ2: 6.9973583 | DA2: 1.3705938 | DB2: 1.1941689 | DC2: 3.9666406 | DD2: 2.1771344 | DE2: 4.5872464 | DF2: 4.704611 | DG2: 9.5825694 | DH2: 5.642377 | DI2: 9.0717091 | DJ2: 4.1186205 | DK2: 6.6239774 | DL2: 0.29993511 | DM2: 1.8628348 | DN2: 0.41402541 | DO2: 2.8349189 | DP2: 1.3529286 | DQ2: 1.3152121 | DR2: 1.3152121 | DS2: 0 | DT2: 1.1267858e-05 | DU2: 5.633929e-06 | DV2: 0.65760888 | DW2: 0 | DX2: 0 | DY2: 0 | DZ2: 5.9910244 | EA2: 0 | EB2: 2.7934448 | EC2: 9.3789809 | ED2: 2.4581006 | EE2: 5.3705866 | EF2: 4.3320229 | EG2: 0 | EH2: 0 | EI2: 0 | EJ2: 0.72360116 | EK2: 0.18090029 | EL2: 2.2564616 | EM2: 3.175944
A3: Antioquia | B3: 2019 | C3: 7.1721593 | D3: 6.7765982 | E3: 8.6608061 | F3: 7.5365212 | G3: 7.0041867 | H3: 1.1765798 | I3: 6.7612831 | J3: 4.9806832 | K3: 4.6210357 | L3: 8.0946449 | M3: 0.24302198 | N3: 4.3195675 | O3: 4.0786759 | P3: 9.2536048 | Q3: 7.2700414 | R3: 9.2021913 | S3: 8.3927574 | T3: 5.3897059 | U3: 7.2644961 | V3: 6.025317 | W3: 8.3985125 | X3: 6.5858386 | Y3: NA | Z3: 9.9111244 | AA3: 9.0252252 | AB3: 7.77453 | AC3: 8.3390462 | AD3: 1.2278334 | AE3: 1.8012324 | AF3: 8.6386965 | AG3: 3.2838591 | AH3: 1.1402591 | AI3: 7.5086135 | AJ3: 3.9334156 | AK3: 6.1406201 | AL3: 7.5469521 | AM3: 2.6702595 | AN3: 5.348 | AO3: 5.4264579 | AP3: 5.8996399 | AQ3: 5.7672659 | AR3: 0.35914533 | AS3: 6.1010435 | AT3: 7.9311538 | AU3: 5.0396521 | AV3: 5.4030325 | AW3: 3.2127648 | AX3: 8.3022754 | AY3: 5.6393576 | AZ3: 5.3395048 | BA3: 6.9255718 | BB3: 2.7427752 | BC3: 3.2590248 | BD3: 7.4396492 | BE3: 5.0917552 | BF3: 5.1207983 | BG3: 3.0474332 | BH3: 4.0841158 | BI3: 4.5879355 | BJ3: 8.8050337 | BK3: 8.9422979 | BL3: 9.535949 | BM3: 9.0944268 | BN3: 8.6102876 | BO3: 8.7006793 | BP3: 7.6388889 | BQ3: 8.3166186 | BR3: 3.9789664 | BS3: 5.1179619 | BT3: 8.4736468 | BU3: 4.834933 | BV3: 5.601377 | BW3: 7.6708075 | BX3: 7.5182361 | BY3: 8.3187105 | BZ3: 8.5362855 | CA3: 6.7028592 | CB3: 6.4265567 | CC3: 7.5005296 | CD3: 6.9219521 | CE3: 6.6754945 | CF3: 4.9146387 | CG3: 4.5849174 | CH3: 5.7742507 | CI3: 6.6373901 | CJ3: 4.3013336 | CK3: 3.5205721 | CL3: 4.4975536 | CM3: 4.1064864 | CN3: 9.5306512 | CO3: 1.9569061 | CP3: 4.7383168 | CQ3: 6.7166027 | CR3: 5.7356192 | CS3: 5.6235707 | CT3: 6.6927843 | CU3: 6.1581775 | CV3: 5.3334277 | CW3: 4.690067 | CX3: 9.9782404 | CY3: 9.6618033 | CZ3: 8.1100369 | DA3: 4.3063973 | DB3: 4.6094583 | DC3: 9.8029079 | DD3: 6.2395879 | DE3: 7.1748124 | DF3: 4.8787672 | DG3: 7.6401364 | DH3: 6.9553103 | DI3: 6.4299436 | DJ3: 9.1547111 | DK3: 7.0117737 | DL3: 0.96054012 | DM3: 6.2953704 | DN3: 8.3117516 | DO3: 8.0596884 | DP3: 5.9068376 | DQ3: 8.2844968 | DR3: 8.2844968 | DS3: 9.6317717 | DT3: 2.8647347 | DU3: 6.2482532 | DV3: 7.266375 | DW3: 8.6588219 | DX3: 9.1759919 | DY3: 8.9174069 | DZ3: 4.4759566 | EA3: 6.1841605 | EB3: 4.443016 | EC3: 3.9808917 | ED3: 5.8100559 | EE3: 3.0277699 | EF3: 4.6536418 | EG3: 3.810856 | EH3: 3.2825827 | EI3: 5.4483119 | EJ3: 7.3692735 | EK3: 4.977756 | EL3: 4.8156989 | EM3: 6.3528405
A4: Arauca | B4: 2019 | C4: 3.9272857 | D4: 7.949388 | E4: 0.043410916 | F4: 3.9733615 | G4: 0.55405449 | H4: 1.2858457 | I4: 5.096522 | J4: 2.3121407 | K4: 7.6617094 | L4: 7.6124827 | M4: 0.68021717 | N4: 5.3181364 | O4: 1.1947437 | P4: 1.964784 | Q4: 3.6622909 | R4: 7.266646 | S4: 3.5456743 | T4: 5.877193 | U4: 3.9185553 | V4: 3.8805485 | W4: 6.6730752 | X4: 0 | Y4: NA | Z4: 9.3511682 | AA4: 6.6476314 | AB4: 5.3697414 | AC4: 5.6083232 | AD4: 9.6727763 | AE4: 1.0155887 | AF4: 4.5406163 | AG4: 9.1487411 | AH4: 0.34716994 | AI4: 0 | AJ4: 4.1208154 | AK4: 5.791743 | AL4: 5.3501937 | AM4: 0.03168896 | AN4: 1.088 | AO4: 3.0654064 | AP4: 4.2648483 | AQ4: 1.3466831 | AR4: 0.25616983 | AS4: 1.9463349 | AT4: 6.4754125 | AU4: 2.5061501 | AV4: 0.52653843 | AW4: 0.7347147 | AX4: 1.225971 | AY4: 0.8290747 | AZ4: 1.6676124 | BA4: 7.296114 | BB4: 5.5080804 | BC4: 7.9690389 | BD4: 5.5716154 | BE4: 6.5862122 | BF4: 0.39390756 | BG4: 4.5793927 | BH4: 2.4866501 | BI4: 4.5364312 | BJ4: 10 | BK4: 10 | BL4: 8.2253493 | BM4: 9.4084498 | BN4: 8.067004 | BO4: 8.2823055 | BP4: 7.2916667 | BQ4: 7.8803254 | BR4: 3.4375153 | BS4: 3.5928765 | BT4: 1.3040005 | BU4: 5.0455462 | BV4: 3.3449846 | BW4: 6.8779199 | BX4: 6.4704907 | BY4: 8.7104673 | BZ4: 7.5458795 | CA4: 5.4053565 | CB4: 7.7907772 | CC4: 7.1845942 | CD4: 6.4570654 | CE4: 6.8344349 | CF4: 7.0653873 | CG4: 5.301898 | CH4: 6.4146964 | CI4: 6.7996453 | CJ4: 0.81789168 | CK4: 0.19992585 | CL4: 0.85549416 | CM4: 0.62443723 | CN4: 5.0919832 | CO4: 7.9325107 | CP4: 0.13381712 | CQ4: 0.49631577 | CR4: 3.4136567 | CS4: 3.0179445 | CT4: 4.5574721 | CU4: 3.7877083 | CV4: 2.6086007 | CW4: 4.0701856 | CX4: 8.8903706 | CY4: 2.6595901 | CZ4: 5.2067154 | DA4: 1.2256669 | DB4: 1.4502739 | DC4: 3.1455207 | DD4: 1.9404872 | DE4: 3.5736013 | DF4: 4.9033397 | DG4: 5.5381771 | DH4: 3.4552259 | DI4: 4.0949992 | DJ4: 5.4085051 | DK4: 4.6800494 | DL4: 0.97652705 | DM4: 2.0973687 | DN4: 0.053800405 | DO4: 1.5317884 | DP4: 1.1648711 | DQ4: 3.3252105 | DR4: 3.3252105 | DS4: 8.6703939 | DT4: 3.0685642 | DU4: 5.8694791 | DV4: 4.5973448 | DW4: 0 | DX4: 0 | DY4: 0 | DZ4: 0 | EA4: 0 | EB4: 0.045336123 | EC4: 1.1942675 | ED4: 0 | EE4: 0 | EF4: 0.20660061 | EG4: 0 | EH4: 0 | EI4: 0 | EJ4: 0.12396899 | EK4: 0.030992249 | EL4: 0.11879643 | EM4: 3.4438669
A5: Atlántico | B5: 2019 | C5: 6.6004326 | D5: 9.1048843 | E5: 7.2058044 | F5: 7.6370404 | G5: 6.8070922 | H5: 1.5622585 | I5: 9.0891969 | J5: 5.8195158 | K5: 6.041928 | L5: 8.2651582 | M5: 2.0583572 | N5: 5.4551478 | O5: 6.6156914 | P5: 9.8652788 | Q5: 9.1164842 | R5: 8.4288793 | S5: 4.1359152 | T5: 4.6442406 | U5: 7.1344149 | V5: 6.5115297 | W5: 9.8290229 | X5: 8.7011872 | Y5: NA | Z5: 9.9519707 | AA5: 9.0326747 | AB5: 8.601215 | AC5: 9.2232141 | AD5: 0.11852625 | AE5: 6.0560158 | AF5: 10 | AG5: 2.3403798 | AH5: 6.0381779 | AI5: 7.911338 | AJ5: 5.4107396 | AK5: 8.9192729 | AL5: 9.3607544 | AM5: 0.75233409 | AN5: 3.158 | AO5: 5.5475904 | AP5: 6.7271814 | AQ5: 4.5176805 | AR5: 0.33226803 | AS5: 6.2399175 | AT5: 8.5347082 | AU5: 4.9061436 | AV5: 5.1492243 | AW5: 3.1123417 | AX5: 7.7755983 | AY5: 5.3457214 | AZ5: 5.1259325 | BA5: 10 | BB5: 0.39191921 | BC5: 1.3802012 | BD5: 8.58885 | BE5: 5.0902426 | BF5: 1.0504202 | BG5: 9.5547813 | BH5: 5.3026007 | BI5: 5.1964217 | BJ5: 9.9088488 | BK5: 9.8907883 | BL5: 9.4424692 | BM5: 9.7473688 | BN5: 7.224142 | BO5: 8.0668684 | BP5: 8.5164141 | BQ5: 7.9358082 | BR5: 5.8090803 | BS5: 5.8437921 | BT5: 4.6882803 | BU5: 10 | BV5: 6.5852882 | BW5: 8.0894884 | BX5: 6.4505968 | BY5: 7.7331157 | BZ5: 7.8292788 | CA5: 7.6872964 | CB5: 8.8902982 | CC5: 7.7181172 | CD5: 6.4060022 | CE5: 5.0860911 | CF5: 6.5205553 | CG5: 4.1732579 | CH5: 5.5464766 | CI5: 6.6322969 | CJ5: 4.6880726 | CK5: 3.847506 | CL5: 4.243205 | CM5: 4.2595945 | CN5: 8.0635463 | CO5: 2.3376453 | CP5: 6.7431456 | CQ5: 5.8356822 | CR5: 5.7450049 | CS5: 5.8173619 | CT5: 4.8155016 | CU5: 5.3164318 | CV5: 5.1070104 | CW5: 1.8628926 | CX5: 9.7080902 | CY5: 9.0654811 | CZ5: 6.8788213 | DA5: 6.2732615 | DB5: 4.8540148 | DC5: 7.9585464 | DD5: 6.3619409 | DE5: 6.6203811 | DF5: 5.3343017 | DG5: 8.923655 | DH5: 4.0586761 | DI5: 4.640139 | DJ5: 5.5835977 | DK5: 5.7080739 | DL5: 1.5924485 | DM5: 3.8165617 | DN5: 5.8334563 | DO5: 7.5527456 | DP5: 4.698803 | DQ5: 6.8011653 | DR5: 6.8011653 | DS5: 9.2799306 | DT5: 3.4715699 | DU5: 6.3757502 | DV5: 6.5884578 | DW5: 9.162608 | DX5: 9.7660224 | DY5: 9.4643152 | DZ5: 4.6146752 | EA5: 3.9067522 | EB5: 4.3174478 | EC5: 1.9904459 | ED5: 5.5865922 | EE5: 3.1297818 | EF5: 3.9242825 | EG5: 1.5122037 | EH5: 0.52335685 | EI5: 0.18167817 | EJ5: 3.1530294 | EK5: 1.342567 | EL5: 2.6334248 | EM5: 6.0848705
A6: Bogotá, D.C. | B6: 2019 | C6: 8.4803499 | D6: 9.1060579 | E6: 10 | F6: 9.1954693 | G6: 8.1325388 | H6: 7.3215356 | I6: 8.636547 | J6: 8.0302071 | K6: 1.1386848 | L6: 9.3437653 | M6: 3.5625986 | N6: 4.6816829 | O6: 7.7912924 | P6: 9.493095 | Q6: 8.478931 | R6: 7.8663438 | S6: 9.1800449 | T6: 3.6015982 | U6: 7.7352176 | V6: 7.4106442 | W6: 9.9602487 | X6: 9.6096821 | Y6: NA | Z6: 9.9859574 | AA6: 8.5007192 | AB6: 9.9751714 | AC6: 9.6063558 | AD6: NA | AE6: NA | AF6: NA | AG6: NA | AH6: NA | AI6: NA | AJ6: NA | AK6: 6.9007969 | AL6: 8.8239188 | AM6: 7.8129655 | AN6: 10 | AO6: 8.3844203 | AP6: 8.995388 | AQ6: 7.7707144 | AR6: 0.50913416 | AS6: 9.6128326 | AT6: 10 | AU6: 6.9731703 | AV6: 9.616423 | AW6: 7.1661644 | AX6: 9.0414542 | AY6: 8.6080138 | AZ6: 7.7905921 | BA6: 9.8939399 | BB6: 9.3136168 | BC6: 1.4473722 | BD6: 7.6750579 | BE6: 7.0824967 | BF6: 1.9695378 | BG6: 1.8699187 | BH6: 1.9197283 | BI6: 4.5011125 | BJ6: 8.4023173 | BK6: 8.2460108 | BL6: 9.2174242 | BM6: 8.6219174 | BN6: 8.4903378 | BO6: 8.8582788 | BP6: 9.8232323 | BQ6: 9.057283 | BR6: 8.2706923 | BS6: 9.2782382 | BT6: 10 | BU6: 5.8113591 | BV6: 8.3400724 | BW6: 8.6730909 | BX6: 7.9608753 | BY6: 9.5266272 | BZ6: 9.2343428 | CA6: 8.9069852 | CB6: 8.7884907 | CC6: 8.8834642 | CD6: 9.417869 | CE6: 7.6291366 | CF6: 4.0093928 | CG6: 0.033805631 | CH6: 5.272551 | CI6: 7.0780076 | CJ6: 9.55829 | CK6: 10 | CL6: 6.9203038 | CM6: 8.8261979 | CN6: 10 | CO6: 1.4361163 | CP6: 4.205155 | CQ6: 7.5928184 | CR6: 5.8085224 | CS6: 2.986135 | CT6: 8.088537 | CU6: 5.537336 | CV6: 6.7240188 | CW6: 10 | CX6: 9.9952182 | CY6: 9.9612297 | CZ6: 9.9854826 | DA6: 6.5390987 | DB6: 7.2740081 | DC6: 9.2344403 | DD6: 7.6825157 | DE6: 8.8339992 | DF6: 6.9020741 | DG6: 8.0141065 | DH6: 8.0375429 | DI6: 6.7982525 | DJ6: 9.3054225 | DK6: 7.8114797 | DL6: 3.0744417 | DM6: 9.8347744 | DN6: 9.1890281 | DO6: 9.5357858 | DP6: 7.9085075 | DQ6: 9.3099096 | DR6: 9.3099096 | DS6: 9.4303065 | DT6: 3.8679752 | DU6: 6.6491409 | DV6: 7.9795253 | DW6: 9.1101302 | DX6: 9.9898271 | DY6: 9.5499787 | DZ6: 6.932932 | EA6: 8.3382789 | EB6: 6.9944099 | EC6: 3.9808917 | ED6: 10 | EE6: 2.6494758 | EF6: 6.4826647 | EG6: 4.4263938 | EH6: 4.1738478 | EI6: 5.6166534 | EJ6: 7.5926663 | EK6: 5.4523903 | EL6: 5.9675275 | EM6: 7.6326055
A7: Bolívar | B7: 2019 | C7: 4.8418807 | D7: 7.2784838 | E7: 3.4973301 | F7: 5.2058982 | G7: 4.0664844 | H7: 1.007121 | I7: 6.4214517 | J7: 3.8316857 | K7: 10 | L7: 7.7648483 | M7: 2.1255225 | N7: 6.6301236 | O7: 7.0653616 | P7: 9.8349905 | Q7: 8.6813538 | R7: 8.0426839 | S7: 4.1332784 | T7: 3.4727626 | U7: 6.8717385 | V7: 5.6348615 | W7: 7.7040422 | X7: 8.7561276 | Y7: 3.9245803 | Z7: 9.4425882 | AA7: 9.159673 | AB7: 4.5906892 | AC7: 7.2629501 | AD7: 1.7260661 | AE7: 1.7764944 | AF7: 9.5266282 | AG7: 1.1079906 | AH7: 0.30438288 | AI7: 8.7962963 | AJ7: 3.8729764 | AK7: 8.6399406 | AL7: 8.9508112 | AM7: 1.5974542 | AN7: 4.566 | AO7: 5.9385515 | AP7: 5.6914927 | AQ7: 2.8435468 | AR7: 0.33564405 | AS7: 3.1680739 | AT7: 6.0084771 | AU7: 3.0889355 | AV7: 2.4346568 | AW7: 2.1686501 | AX7: 4.7139401 | AY7: 3.105749 | AZ7: 3.0973422 | BA7: 8.3425119 | BB7: 6.7077339e-05 | BC7: 2.5913873 | BD7: 8.3819901 | BE7: 4.8289891 | BF7: 1.1817227 | BG7: 3.0584592 | BH7: 2.1200909 | BI7: 3.47454 | BJ7: 7.4099428 | BK7: 7.8975734 | BL7: 9.0922881 | BM7: 8.1332681 | BN7: 7.5477998 | BO7: 7.367876 | BP7: 7.8598485 | BQ7: 7.5918414 | BR7: 3.4059385 | BS7: 4.0574355 | BT7: 3.503292 | BU7: 6.3173091 | BV7: 4.3209938 | BW7: 6.6820344 | BX7: 7.8100133 | BY7: 9.4123648 | BZ7: 8.2513947 | CA7: 6.7643865 | CB7: 7.6686082 | CC7: 7.9813535 | CD7: 4.4419988 | CE7: 3.0198666 | CF7: 1.0837369 | CG7: 6.021599 | CH7: 3.6418003 | CI7: 5.8115769 | CJ7: 2.6227141 | CK7: 1.9408648 | CL7: 3.9352731 | CM7: 2.8329507 | CN7: 7.48244 | CO7: 1.0373283 | CP7: 5.3610361 | CQ7: 4.7172309 | CR7: 4.6495088 | CS7: 3.8269486 | CT7: 3.3770379 | CU7: 3.6019933 | CV7: 3.6948176 | CW7: 7.9794412 | CX7: 5.7034258 | CY7: 9.8681877 | CZ7: 7.8503516 | DA7: 3.7598161 | DB7: 2.7802577 | DC7: 7.7943224 | DD7: 4.7781321 | DE7: 6.3142418 | DF7: 6.3134088 | DG7: 9.6248286 | DH7: 2.5418425 | DI7: 5.4557076 | DJ7: 3.4467441 | DK7: 5.4765063 | DL7: 1.0513739 | DM7: 2.5830725 | DN7: 2.4493817 | DO7: 2.9970127 | DP7: 2.2702102 | DQ7: 6.4621182 | DR7: 6.4621182 | DS7: 9.3339117 | DT7: 4.0682334 | DU7: 6.7010725 | DV7: 6.5815954 | DW7: 9.4564831 | DX7: 9.2878942 | DY7: 9.3721887 | DZ7: 2.161119 | EA7: 2.1750352 | EB7: 1.9636617 | EC7: 0.79617834 | ED7: 5.7541899 | EE7: 3.1864551 | EF7: 2.6727732 | EG7: 0.26194901 | EH7: 0.21153448 | EI7: 0.3304445 | EJ7: 1.041144 | EK7: 0.461268 | EL7: 1.5670206 | EM7: 5.0514176
A8: Boyacá | B8: 2019 | C8: 4.971304 | D8: 6.464666 | E8: 7.5260081 | F8: 6.3206593 | G8: 3.2318401 | H8: 1.6745262 | I8: 6.7777931 | J8: 3.8947198 | K8: 1.041928 | L8: 5.7770453 | M8: 0.9424524 | N8: 2.5871419 | O8: 8.8522399 | P8: 9.4388129 | Q8: 7.6480046 | R8: 10 | S8: 0.86290868 | T8: 6.4 | U8: 7.2003277 | V8: 5.0007122 | W8: 8.2324308 | X8: 9.1811626 | Y8: 2.133723 | Z8: 9.8059495 | AA8: 8.8622146 | AB8: 6.2892781 | AC8: 7.4174598 | AD8: 5.7717741 | AE8: 3.0582006 | AF8: 5.1690356 | AG8: 8.3415426 | AH8: 1.5096822 | AI8: 4.3492507 | AJ8: 4.6999143 | AK8: 9.2012456 | AL8: 10 | AM8: NA | AN8: NA | AO8: 9.6006228 | AP8: 7.2393323 | AQ8: 2.8365289 | AR8: 0.28279119 | AS8: 4.6615111 | AT8: 6.7712121 | AU8: 3.6380108 | AV8: 5.3700807 | AW8: 3.2644798 | AX8: 8.2509481 | AY8: 5.6285029 | AZ8: 4.6332568 | BA8: 9.625635 | BB8: 4.1897521 | BC8: 2.9325021 | BD8: 6.7514529 | BE8: 5.8748355 | BF8: 3.019958 | BG8: 10 | BH8: 6.509979 | BI8: 6.1924073 | BJ8: 9.0823199 | BK8: 9.2270425 | BL8: 9.4472923 | BM8: 9.2522182 | BN8: 8.9088041 | BO8: 8.212585 | BP8: 8.5037879 | BQ8: 8.5417257 | BR8: 2.1559123 | BS8: 4.401389 | BT8: 2.5366811 | BU8: 4.224935 | BV8: 3.3297293 | BW8: 7.0412244 | BX8: 7.9625332 | BY8: 8.5145889 | BZ8: 9.7235795 | CA8: 9.2598625 | CB8: 8.3608992 | CC8: 8.7642926 | CD8: 8.1854491 | CE8: 8.1059576 | CF8: 8.8136097 | CG8: 8.1573886 | CH8: 8.3156012 | CI8: 8.5399469 | CJ8: 5.5030519 | CK8: 9.9746266 | CL8: 3.2628363 | CM8: 6.2468383 | CN8: 9.1638919 | CO8: 1.6155181 | CP8: 7.1631511 | CQ8: 3.5186637 | CR8: 5.3653062 | CS8: 1.0800781 | CT8: 5.7197863 | CU8: 3.3999322 | CV8: 5.0040256 | CW8: 3.2443251 | CX8: 6.1101722 | CY8: 9.905305 | CZ8: 6.4199341 | DA8: 2.2525771 | DB8: 1.9161922 | DC8: 3.2465816 | DD8: 2.4717836 | DE8: 4.4458589 | DF8: 4.5489917 | DG8: 8.9215618 | DH8: 3.4938041 | DI8: 7.3914404 | DJ8: 5.6579974 | DK8: 6.0027591 | DL8: 1.6656039 | DM8: 3.7932424 | DN8: 1.6218958 | DO8: 2.0957278 | DP8: 2.2941174 | DQ8: 5.9565309 | DR8: 5.9565309 | DS8: 8.8024549 | DT8: 0.72957312 | DU8: 4.766014 | DV8: 5.3612725 | DW8: 6.8221021 | DX8: 3.5808749 | DY8: 5.2014885 | DZ8: 1.5076577 | EA8: 5.9177275 | EB8: 2.743567 | EC8: 1.1942675 | ED8: 5.1396648 | EE8: 2.5177104 | EF8: 3.1700992 | EG8: 0.22077831 | EH8: 0.35657494 | EI8: 0.18567222 | EJ8: 0.81643483 | EK8: 0.39486508 | EL8: 1.7824821 | EM8: 5.2876065
A9: Caldas | B9: 2019 | C9: 6.3155248 | D9: 7.7691588 | E9: 8.2669601 | F9: 7.4505479 | G9: 4.3440382 | H9: 2.0478579 | I9: 5.8628624 | J9: 4.0849195 | K9: 0.88514603 | L9: 7.1207106 | M9: 0.74480958 | N9: 2.9168887 | O9: 6.8963216 | P9: 9.3156301 | Q9: 8.5138508 | R9: 8.411312 | S9: 5.2190064 | T9: 5.7094134 | U9: 7.3442557 | V9: 5.449153 | W9: 8.7154915 | X9: 7.4572828 | Y9: NA | Z9: 9.9612935 | AA9: 7.9553999 | AB9: 8.0075717 | AC9: 8.4194079 | AD9: 1.8626566 | AE9: 2.9811918 | AF9: 8.6765156 | AG9: 6.9430609 | AH9: 6.4825169 | AI9: 7.8803181 | AJ9: 5.8043766 | AK9: 8.2320465 | AL9: 9.2784495 | AM9: 0.063108633 | AN9: 1.268 | AO9: 4.7104012 | AP9: 6.3113952 | AQ9: 4.1627279 | AR9: 0.32130764 | AS9: 5.9410968 | AT9: 7.7876543 | AU9: 4.5531966 | AV9: 6.2236372 | AW9: 4.4697807 | AX9: 10 | AY9: 6.8978059 | AZ9: 5.7255013 | BA9: 9.4155346 | BB9: 1.183327 | BC9: 3.9465699 | BD9: 8.4203929 | BE9: 5.7414561 | BF9: 0.13130252 | BG9: 2.8757833 | BH9: 1.5035429 | BI9: 3.6224995 | BJ9: 8.8956337 | BK9: 9.5507082 | BL9: 9.9332448 | BM9: 9.4598622 | BN9: 8.5960714 | BO9: 9.1519634 | BP9: 8.9583333 | BQ9: 8.9021227 | BR9: 3.3436289 | BS9: 5.3862858 | BT9: 6.1086038 | BU9: 6.4468557 | BV9: 5.3213435 | BW9: 7.8944428 | BX9: 7.1369363 | BY9: 6.5068353 | BZ9: 8.0172173 | CA9: 6.9489685 | CB9: 7.4548125 | CC9: 7.212954 | CD9: 7.3680045 | CE9: 7.4160078 | CF9: 4.5970742 | CG9: 7.6802906 | CH9: 6.7653443 | CI9: 6.9891491 | CJ9: 4.7677989 | CK9: 4.8124848 | CL9: 3.6951828 | CM9: 4.4251555 | CN9: 9.0481253 | CO9: 2.9814816 | CP9: 8.3887954 | CQ9: 4.8410851 | CR9: 6.3148718 | CS9: 4.9375 | CT9: 5.8332724 | CU9: 5.3853862 | CV9: 5.3751379 | CW9: 4.5609408 | CX9: 9.276891 | CY9: 9.4595995 | CZ9: 7.7658104 | DA9: 1.8136558 | DB9: 2.0890053 | DC9: 8.2238313 | DD9: 4.0421641 | DE9: 5.9039873 | DF9: 4.185869 | DG9: 8.0494483 | DH9: 6.1461813 | DI9: 8.0624823 | DJ9: 9.1391704 | DK9: 7.1166303 | DL9: 1.2129437 | DM9: 4.0257514 | DN9: 4.422948 | DO9: 4.2155135 | DP9: 3.4692891 | DQ9: 5.1619002 | DR9: 5.1619002 | DS9: 9.0742883 | DT9: 2.8399106 | DU9: 5.9570994 | DV9: 5.5594998 | DW9: 8.9946793 | DX9: 6.1953204 | DY9: 7.5949999 | DZ9: 7.1245542 | EA9: 8.1187791 | EB9: 4.9889198 | EC9: 3.1847134 | ED9: 3.4636872 | EE9: 2.8889204 | EF9: 4.9615957 | EG9: 1.3447458 | EH9: 1.3031243 | EI9: 0.67855015 | EJ9: 2.8858189 | EK9: 1.5530598 | EL9: 3.2573277 | EM9: 5.713001
